.version 55 0 
.class final synthetic a 
.super java/lang/Object 

.method private static synthetic a : (Ljava/lang/invoke/MethodHandles$Lookup;Ljava/lang/String;Ljava/lang/invoke/MethodType;)Ljava/lang/invoke/CallSite; 
    .code stack 4 locals 4 
L0:     aload_0 
L1:     dup 
L2:     invokevirtual Method java/lang/invoke/MethodHandles$Lookup lookupClass ()Ljava/lang/Class; 
L5:     aload_1 
L6:     aload_2 
L7:     invokevirtual Method java/lang/invoke/MethodHandles$Lookup findStatic (Ljava/lang/Class;Ljava/lang/String;Ljava/lang/invoke/MethodType;)Ljava/lang/invoke/MethodHandle; 
L10:    astore_3 
L11:    new java/lang/invoke/ConstantCallSite 
L14:    dup 
L15:    aload_3 
L16:    invokespecial Method java/lang/invoke/ConstantCallSite <init> (Ljava/lang/invoke/MethodHandle;)V 
L19:    areturn 
L20:    
    .end code 
.end method 

.method private static synthetic a : (Ljava/lang/invoke/MethodHandles$Lookup;Ljava/lang/String;Ljava/lang/Class;)Ljava/lang/Class; 
    .code stack 5 locals 3 
L0:     aload_0 
L1:     ldc 1937 
L3:     newarray byte 
L5:     dup 
L6:     iconst_0 
L7:     bipush -54 
L9:     bastore 
L10:    dup 
L11:    iconst_1 
L12:    bipush -2 
L14:    bastore 
L15:    dup 
L16:    iconst_2 
L17:    bipush -70 
L19:    bastore 
L20:    dup 
L21:    iconst_3 
L22:    bipush -66 
L24:    bastore 
L25:    dup 
L26:    iconst_4 
L27:    bipush 0 
L29:    bastore 
L30:    dup 
L31:    iconst_5 
L32:    bipush 0 
L34:    bastore 
L35:    dup 
L36:    ldc 6 
L38:    bipush 0 
L40:    bastore 
L41:    dup 
L42:    ldc 7 
L44:    bipush 55 
L46:    bastore 
L47:    dup 
L48:    ldc 8 
L50:    bipush 0 
L52:    bastore 
L53:    dup 
L54:    ldc 9 
L56:    bipush 108 
L58:    bastore 
L59:    dup 
L60:    ldc 10 
L62:    bipush 1 
L64:    bastore 
L65:    dup 
L66:    ldc 11 
L68:    bipush 0 
L70:    bastore 
L71:    dup 
L72:    ldc 12 
L74:    bipush 1 
L76:    bastore 
L77:    dup 
L78:    ldc 13 
L80:    bipush 114 
L82:    bastore 
L83:    dup 
L84:    ldc 14 
L86:    bipush 7 
L88:    bastore 
L89:    dup 
L90:    ldc 15 
L92:    bipush 0 
L94:    bastore 
L95:    dup 
L96:    ldc 16 
L98:    bipush 1 
L100:   bastore 
L101:   dup 
L102:   ldc 17 
L104:   bipush 1 
L106:   bastore 
L107:   dup 
L108:   ldc 18 
L110:   bipush 0 
L112:   bastore 
L113:   dup 
L114:   ldc 19 
L116:   bipush 16 
L118:   bastore 
L119:   dup 
L120:   ldc 20 
L122:   bipush 106 
L124:   bastore 
L125:   dup 
L126:   ldc 21 
L128:   bipush 97 
L130:   bastore 
L131:   dup 
L132:   ldc 22 
L134:   bipush 118 
L136:   bastore 
L137:   dup 
L138:   ldc 23 
L140:   bipush 97 
L142:   bastore 
L143:   dup 
L144:   ldc 24 
L146:   bipush 47 
L148:   bastore 
L149:   dup 
L150:   ldc 25 
L152:   bipush 108 
L154:   bastore 
L155:   dup 
L156:   ldc 26 
L158:   bipush 97 
L160:   bastore 
L161:   dup 
L162:   ldc 27 
L164:   bipush 110 
L166:   bastore 
L167:   dup 
L168:   ldc 28 
L170:   bipush 103 
L172:   bastore 
L173:   dup 
L174:   ldc 29 
L176:   bipush 47 
L178:   bastore 
L179:   dup 
L180:   ldc 30 
L182:   bipush 79 
L184:   bastore 
L185:   dup 
L186:   ldc 31 
L188:   bipush 98 
L190:   bastore 
L191:   dup 
L192:   ldc 32 
L194:   bipush 106 
L196:   bastore 
L197:   dup 
L198:   ldc 33 
L200:   bipush 101 
L202:   bastore 
L203:   dup 
L204:   ldc 34 
L206:   bipush 99 
L208:   bastore 
L209:   dup 
L210:   ldc 35 
L212:   bipush 116 
L214:   bastore 
L215:   dup 
L216:   ldc 36 
L218:   bipush 7 
L220:   bastore 
L221:   dup 
L222:   ldc 37 
L224:   bipush 0 
L226:   bastore 
L227:   dup 
L228:   ldc 38 
L230:   bipush 3 
L232:   bastore 
L233:   dup 
L234:   ldc 39 
L236:   bipush 1 
L238:   bastore 
L239:   dup 
L240:   ldc 40 
L242:   bipush 0 
L244:   bastore 
L245:   dup 
L246:   ldc 41 
L248:   bipush 1 
L250:   bastore 
L251:   dup 
L252:   ldc 42 
L254:   bipush 97 
L256:   bastore 
L257:   dup 
L258:   ldc 43 
L260:   bipush 1 
L262:   bastore 
L263:   dup 
L264:   ldc 44 
L266:   bipush 0 
L268:   bastore 
L269:   dup 
L270:   ldc 45 
L272:   bipush 15 
L274:   bastore 
L275:   dup 
L276:   ldc 46 
L278:   bipush 76 
L280:   bastore 
L281:   dup 
L282:   ldc 47 
L284:   bipush 106 
L286:   bastore 
L287:   dup 
L288:   ldc 48 
L290:   bipush 97 
L292:   bastore 
L293:   dup 
L294:   ldc 49 
L296:   bipush 118 
L298:   bastore 
L299:   dup 
L300:   ldc 50 
L302:   bipush 97 
L304:   bastore 
L305:   dup 
L306:   ldc 51 
L308:   bipush 47 
L310:   bastore 
L311:   dup 
L312:   ldc 52 
L314:   bipush 117 
L316:   bastore 
L317:   dup 
L318:   ldc 53 
L320:   bipush 116 
L322:   bastore 
L323:   dup 
L324:   ldc 54 
L326:   bipush 105 
L328:   bastore 
L329:   dup 
L330:   ldc 55 
L332:   bipush 108 
L334:   bastore 
L335:   dup 
L336:   ldc 56 
L338:   bipush 47 
L340:   bastore 
L341:   dup 
L342:   ldc 57 
L344:   bipush 77 
L346:   bastore 
L347:   dup 
L348:   ldc 58 
L350:   bipush 97 
L352:   bastore 
L353:   dup 
L354:   ldc 59 
L356:   bipush 112 
L358:   bastore 
L359:   dup 
L360:   ldc 60 
L362:   bipush 59 
L364:   bastore 
L365:   dup 
L366:   ldc 61 
L368:   bipush 1 
L370:   bastore 
L371:   dup 
L372:   ldc 62 
L374:   bipush 0 
L376:   bastore 
L377:   dup 
L378:   ldc 63 
L380:   bipush 6 
L382:   bastore 
L383:   dup 
L384:   ldc 64 
L386:   bipush 60 
L388:   bastore 
L389:   dup 
L390:   ldc 65 
L392:   bipush 105 
L394:   bastore 
L395:   dup 
L396:   ldc 66 
L398:   bipush 110 
L400:   bastore 
L401:   dup 
L402:   ldc 67 
L404:   bipush 105 
L406:   bastore 
L407:   dup 
L408:   ldc 68 
L410:   bipush 116 
L412:   bastore 
L413:   dup 
L414:   ldc 69 
L416:   bipush 62 
L418:   bastore 
L419:   dup 
L420:   ldc 70 
L422:   bipush 1 
L424:   bastore 
L425:   dup 
L426:   ldc 71 
L428:   bipush 0 
L430:   bastore 
L431:   dup 
L432:   ldc 72 
L434:   bipush 3 
L436:   bastore 
L437:   dup 
L438:   ldc 73 
L440:   bipush 40 
L442:   bastore 
L443:   dup 
L444:   ldc 74 
L446:   bipush 41 
L448:   bastore 
L449:   dup 
L450:   ldc 75 
L452:   bipush 86 
L454:   bastore 
L455:   dup 
L456:   ldc 76 
L458:   bipush 12 
L460:   bastore 
L461:   dup 
L462:   ldc 77 
L464:   bipush 0 
L466:   bastore 
L467:   dup 
L468:   ldc 78 
L470:   bipush 7 
L472:   bastore 
L473:   dup 
L474:   ldc 79 
L476:   bipush 0 
L478:   bastore 
L479:   dup 
L480:   ldc 80 
L482:   bipush 8 
L484:   bastore 
L485:   dup 
L486:   ldc 81 
L488:   bipush 10 
L490:   bastore 
L491:   dup 
L492:   ldc 82 
L494:   bipush 0 
L496:   bastore 
L497:   dup 
L498:   ldc 83 
L500:   bipush 4 
L502:   bastore 
L503:   dup 
L504:   ldc 84 
L506:   bipush 0 
L508:   bastore 
L509:   dup 
L510:   ldc 85 
L512:   bipush 9 
L514:   bastore 
L515:   dup 
L516:   ldc 86 
L518:   bipush 1 
L520:   bastore 
L521:   dup 
L522:   ldc 87 
L524:   bipush 0 
L526:   bastore 
L527:   dup 
L528:   ldc 88 
L530:   bipush 19 
L532:   bastore 
L533:   dup 
L534:   ldc 89 
L536:   bipush 106 
L538:   bastore 
L539:   dup 
L540:   ldc 90 
L542:   bipush 97 
L544:   bastore 
L545:   dup 
L546:   ldc 91 
L548:   bipush 118 
L550:   bastore 
L551:   dup 
L552:   ldc 92 
L554:   bipush 97 
L556:   bastore 
L557:   dup 
L558:   ldc 93 
L560:   bipush 47 
L562:   bastore 
L563:   dup 
L564:   ldc 94 
L566:   bipush 117 
L568:   bastore 
L569:   dup 
L570:   ldc 95 
L572:   bipush 116 
L574:   bastore 
L575:   dup 
L576:   ldc 96 
L578:   bipush 105 
L580:   bastore 
L581:   dup 
L582:   ldc 97 
L584:   bipush 108 
L586:   bastore 
L587:   dup 
L588:   ldc 98 
L590:   bipush 47 
L592:   bastore 
L593:   dup 
L594:   ldc 99 
L596:   bipush 77 
L598:   bastore 
L599:   dup 
L600:   ldc 100 
L602:   bipush 97 
L604:   bastore 
L605:   dup 
L606:   ldc 101 
L608:   bipush 112 
L610:   bastore 
L611:   dup 
L612:   ldc 102 
L614:   bipush 36 
L616:   bastore 
L617:   dup 
L618:   ldc 103 
L620:   bipush 69 
L622:   bastore 
L623:   dup 
L624:   ldc 104 
L626:   bipush 110 
L628:   bastore 
L629:   dup 
L630:   ldc 105 
L632:   bipush 116 
L634:   bastore 
L635:   dup 
L636:   ldc 106 
L638:   bipush 114 
L640:   bastore 
L641:   dup 
L642:   ldc 107 
L644:   bipush 121 
L646:   bastore 
L647:   dup 
L648:   ldc 108 
L650:   bipush 7 
L652:   bastore 
L653:   dup 
L654:   ldc 109 
L656:   bipush 0 
L658:   bastore 
L659:   dup 
L660:   ldc 110 
L662:   bipush 11 
L664:   bastore 
L665:   dup 
L666:   ldc 111 
L668:   bipush 1 
L670:   bastore 
L671:   dup 
L672:   ldc 112 
L674:   bipush 0 
L676:   bastore 
L677:   dup 
L678:   ldc 113 
L680:   bipush 17 
L682:   bastore 
L683:   dup 
L684:   ldc 114 
L686:   bipush 106 
L688:   bastore 
L689:   dup 
L690:   ldc 115 
L692:   bipush 97 
L694:   bastore 
L695:   dup 
L696:   ldc 116 
L698:   bipush 118 
L700:   bastore 
L701:   dup 
L702:   ldc 117 
L704:   bipush 97 
L706:   bastore 
L707:   dup 
L708:   ldc 118 
L710:   bipush 47 
L712:   bastore 
L713:   dup 
L714:   ldc 119 
L716:   bipush 108 
L718:   bastore 
L719:   dup 
L720:   ldc 120 
L722:   bipush 97 
L724:   bastore 
L725:   dup 
L726:   ldc 121 
L728:   bipush 110 
L730:   bastore 
L731:   dup 
L732:   ldc 122 
L734:   bipush 103 
L736:   bastore 
L737:   dup 
L738:   ldc 123 
L740:   bipush 47 
L742:   bastore 
L743:   dup 
L744:   ldc 124 
L746:   bipush 73 
L748:   bastore 
L749:   dup 
L750:   ldc 125 
L752:   bipush 110 
L754:   bastore 
L755:   dup 
L756:   ldc 126 
L758:   bipush 116 
L760:   bastore 
L761:   dup 
L762:   ldc 127 
L764:   bipush 101 
L766:   bastore 
L767:   dup 
L768:   ldc 128 
L770:   bipush 103 
L772:   bastore 
L773:   dup 
L774:   ldc 129 
L776:   bipush 101 
L778:   bastore 
L779:   dup 
L780:   ldc 130 
L782:   bipush 114 
L784:   bastore 
L785:   dup 
L786:   ldc 131 
L788:   bipush 7 
L790:   bastore 
L791:   dup 
L792:   ldc 132 
L794:   bipush 0 
L796:   bastore 
L797:   dup 
L798:   ldc 133 
L800:   bipush 13 
L802:   bastore 
L803:   dup 
L804:   ldc 134 
L806:   bipush 1 
L808:   bastore 
L809:   dup 
L810:   ldc 135 
L812:   bipush 0 
L814:   bastore 
L815:   dup 
L816:   ldc 136 
L818:   bipush 7 
L820:   bastore 
L821:   dup 
L822:   ldc 137 
L824:   bipush 118 
L826:   bastore 
L827:   dup 
L828:   ldc 138 
L830:   bipush 97 
L832:   bastore 
L833:   dup 
L834:   ldc 139 
L836:   bipush 108 
L838:   bastore 
L839:   dup 
L840:   ldc 140 
L842:   bipush 117 
L844:   bastore 
L845:   dup 
L846:   ldc 141 
L848:   bipush 101 
L850:   bastore 
L851:   dup 
L852:   ldc 142 
L854:   bipush 79 
L856:   bastore 
L857:   dup 
L858:   ldc 143 
L860:   bipush 102 
L862:   bastore 
L863:   dup 
L864:   ldc 144 
L866:   bipush 1 
L868:   bastore 
L869:   dup 
L870:   ldc 145 
L872:   bipush 0 
L874:   bastore 
L875:   dup 
L876:   ldc 146 
L878:   bipush 22 
L880:   bastore 
L881:   dup 
L882:   ldc 147 
L884:   bipush 40 
L886:   bastore 
L887:   dup 
L888:   ldc 148 
L890:   bipush 73 
L892:   bastore 
L893:   dup 
L894:   ldc 149 
L896:   bipush 41 
L898:   bastore 
L899:   dup 
L900:   ldc 150 
L902:   bipush 76 
L904:   bastore 
L905:   dup 
L906:   ldc 151 
L908:   bipush 106 
L910:   bastore 
L911:   dup 
L912:   ldc 152 
L914:   bipush 97 
L916:   bastore 
L917:   dup 
L918:   ldc 153 
L920:   bipush 118 
L922:   bastore 
L923:   dup 
L924:   ldc 154 
L926:   bipush 97 
L928:   bastore 
L929:   dup 
L930:   ldc 155 
L932:   bipush 47 
L934:   bastore 
L935:   dup 
L936:   ldc 156 
L938:   bipush 108 
L940:   bastore 
L941:   dup 
L942:   ldc 157 
L944:   bipush 97 
L946:   bastore 
L947:   dup 
L948:   ldc 158 
L950:   bipush 110 
L952:   bastore 
L953:   dup 
L954:   ldc 159 
L956:   bipush 103 
L958:   bastore 
L959:   dup 
L960:   ldc 160 
L962:   bipush 47 
L964:   bastore 
L965:   dup 
L966:   ldc 161 
L968:   bipush 73 
L970:   bastore 
L971:   dup 
L972:   ldc 162 
L974:   bipush 110 
L976:   bastore 
L977:   dup 
L978:   ldc 163 
L980:   bipush 116 
L982:   bastore 
L983:   dup 
L984:   ldc 164 
L986:   bipush 101 
L988:   bastore 
L989:   dup 
L990:   ldc 165 
L992:   bipush 103 
L994:   bastore 
L995:   dup 
L996:   ldc 166 
L998:   bipush 101 
L1000:  bastore 
L1001:  dup 
L1002:  ldc 167 
L1004:  bipush 114 
L1006:  bastore 
L1007:  dup 
L1008:  ldc 168 
L1010:  bipush 59 
L1012:  bastore 
L1013:  dup 
L1014:  ldc 169 
L1016:  bipush 12 
L1018:  bastore 
L1019:  dup 
L1020:  ldc 170 
L1022:  bipush 0 
L1024:  bastore 
L1025:  dup 
L1026:  ldc 171 
L1028:  bipush 15 
L1030:  bastore 
L1031:  dup 
L1032:  ldc 172 
L1034:  bipush 0 
L1036:  bastore 
L1037:  dup 
L1038:  ldc 173 
L1040:  bipush 16 
L1042:  bastore 
L1043:  dup 
L1044:  ldc 174 
L1046:  bipush 10 
L1048:  bastore 
L1049:  dup 
L1050:  ldc 175 
L1052:  bipush 0 
L1054:  bastore 
L1055:  dup 
L1056:  ldc 176 
L1058:  bipush 14 
L1060:  bastore 
L1061:  dup 
L1062:  ldc 177 
L1064:  bipush 0 
L1066:  bastore 
L1067:  dup 
L1068:  ldc 178 
L1070:  bipush 17 
L1072:  bastore 
L1073:  dup 
L1074:  ldc 179 
L1076:  bipush 3 
L1078:  bastore 
L1079:  dup 
L1080:  ldc 180 
L1082:  bipush 0 
L1084:  bastore 
L1085:  dup 
L1086:  ldc 181 
L1088:  bipush 0 
L1090:  bastore 
L1091:  dup 
L1092:  ldc 182 
L1094:  bipush 0 
L1096:  bastore 
L1097:  dup 
L1098:  ldc 183 
L1100:  bipush 66 
L1102:  bastore 
L1103:  dup 
L1104:  ldc 184 
L1106:  bipush 3 
L1108:  bastore 
L1109:  dup 
L1110:  ldc 185 
L1112:  bipush 0 
L1114:  bastore 
L1115:  dup 
L1116:  ldc 186 
L1118:  bipush 0 
L1120:  bastore 
L1121:  dup 
L1122:  ldc 187 
L1124:  bipush 0 
L1126:  bastore 
L1127:  dup 
L1128:  ldc 188 
L1130:  bipush 6 
L1132:  bastore 
L1133:  dup 
L1134:  ldc 189 
L1136:  bipush 3 
L1138:  bastore 
L1139:  dup 
L1140:  ldc 190 
L1142:  bipush 0 
L1144:  bastore 
L1145:  dup 
L1146:  ldc 191 
L1148:  bipush 0 
L1150:  bastore 
L1151:  dup 
L1152:  ldc 192 
L1154:  bipush 0 
L1156:  bastore 
L1157:  dup 
L1158:  ldc 193 
L1160:  bipush 7 
L1162:  bastore 
L1163:  dup 
L1164:  ldc 194 
L1166:  bipush 3 
L1168:  bastore 
L1169:  dup 
L1170:  ldc 195 
L1172:  bipush 0 
L1174:  bastore 
L1175:  dup 
L1176:  ldc 196 
L1178:  bipush 0 
L1180:  bastore 
L1181:  dup 
L1182:  ldc 197 
L1184:  bipush 0 
L1186:  bastore 
L1187:  dup 
L1188:  ldc 198 
L1190:  bipush 8 
L1192:  bastore 
L1193:  dup 
L1194:  ldc 199 
L1196:  bipush 3 
L1198:  bastore 
L1199:  dup 
L1200:  ldc 200 
L1202:  bipush 0 
L1204:  bastore 
L1205:  dup 
L1206:  ldc 201 
L1208:  bipush 0 
L1210:  bastore 
L1211:  dup 
L1212:  ldc 202 
L1214:  bipush 0 
L1216:  bastore 
L1217:  dup 
L1218:  ldc 203 
L1220:  bipush 9 
L1222:  bastore 
L1223:  dup 
L1224:  ldc 204 
L1226:  bipush 3 
L1228:  bastore 
L1229:  dup 
L1230:  ldc 205 
L1232:  bipush 0 
L1234:  bastore 
L1235:  dup 
L1236:  ldc 206 
L1238:  bipush 0 
L1240:  bastore 
L1241:  dup 
L1242:  ldc 207 
L1244:  bipush 0 
L1246:  bastore 
L1247:  dup 
L1248:  ldc 208 
L1250:  bipush 10 
L1252:  bastore 
L1253:  dup 
L1254:  ldc 209 
L1256:  bipush 3 
L1258:  bastore 
L1259:  dup 
L1260:  ldc 210 
L1262:  bipush 0 
L1264:  bastore 
L1265:  dup 
L1266:  ldc 211 
L1268:  bipush 0 
L1270:  bastore 
L1271:  dup 
L1272:  ldc 212 
L1274:  bipush 0 
L1276:  bastore 
L1277:  dup 
L1278:  ldc 213 
L1280:  bipush 11 
L1282:  bastore 
L1283:  dup 
L1284:  ldc 214 
L1286:  bipush 3 
L1288:  bastore 
L1289:  dup 
L1290:  ldc 215 
L1292:  bipush 0 
L1294:  bastore 
L1295:  dup 
L1296:  ldc 216 
L1298:  bipush 0 
L1300:  bastore 
L1301:  dup 
L1302:  ldc 217 
L1304:  bipush 0 
L1306:  bastore 
L1307:  dup 
L1308:  ldc 218 
L1310:  bipush 12 
L1312:  bastore 
L1313:  dup 
L1314:  ldc 219 
L1316:  bipush 3 
L1318:  bastore 
L1319:  dup 
L1320:  ldc 220 
L1322:  bipush 0 
L1324:  bastore 
L1325:  dup 
L1326:  ldc 221 
L1328:  bipush 0 
L1330:  bastore 
L1331:  dup 
L1332:  ldc 222 
L1334:  bipush 0 
L1336:  bastore 
L1337:  dup 
L1338:  ldc 223 
L1340:  bipush 13 
L1342:  bastore 
L1343:  dup 
L1344:  ldc 224 
L1346:  bipush 3 
L1348:  bastore 
L1349:  dup 
L1350:  ldc 225 
L1352:  bipush 0 
L1354:  bastore 
L1355:  dup 
L1356:  ldc 226 
L1358:  bipush 0 
L1360:  bastore 
L1361:  dup 
L1362:  ldc 227 
L1364:  bipush 0 
L1366:  bastore 
L1367:  dup 
L1368:  ldc 228 
L1370:  bipush 14 
L1372:  bastore 
L1373:  dup 
L1374:  ldc 229 
L1376:  bipush 3 
L1378:  bastore 
L1379:  dup 
L1380:  ldc 230 
L1382:  bipush 0 
L1384:  bastore 
L1385:  dup 
L1386:  ldc 231 
L1388:  bipush 0 
L1390:  bastore 
L1391:  dup 
L1392:  ldc 232 
L1394:  bipush 0 
L1396:  bastore 
L1397:  dup 
L1398:  ldc 233 
L1400:  bipush 15 
L1402:  bastore 
L1403:  dup 
L1404:  ldc 234 
L1406:  bipush 3 
L1408:  bastore 
L1409:  dup 
L1410:  ldc 235 
L1412:  bipush 0 
L1414:  bastore 
L1415:  dup 
L1416:  ldc 236 
L1418:  bipush 0 
L1420:  bastore 
L1421:  dup 
L1422:  ldc 237 
L1424:  bipush 0 
L1426:  bastore 
L1427:  dup 
L1428:  ldc_w 238 
L1431:  bipush 16 
L1433:  bastore 
L1434:  dup 
L1435:  ldc_w 239 
L1438:  bipush 3 
L1440:  bastore 
L1441:  dup 
L1442:  ldc_w 240 
L1445:  bipush 0 
L1447:  bastore 
L1448:  dup 
L1449:  ldc_w 241 
L1452:  bipush 0 
L1454:  bastore 
L1455:  dup 
L1456:  ldc_w 242 
L1459:  bipush 0 
L1461:  bastore 
L1462:  dup 
L1463:  ldc_w 243 
L1466:  bipush 17 
L1468:  bastore 
L1469:  dup 
L1470:  ldc_w 244 
L1473:  bipush 3 
L1475:  bastore 
L1476:  dup 
L1477:  ldc_w 245 
L1480:  bipush 0 
L1482:  bastore 
L1483:  dup 
L1484:  ldc_w 246 
L1487:  bipush 0 
L1489:  bastore 
L1490:  dup 
L1491:  ldc_w 247 
L1494:  bipush 0 
L1496:  bastore 
L1497:  dup 
L1498:  ldc_w 248 
L1501:  bipush 18 
L1503:  bastore 
L1504:  dup 
L1505:  ldc_w 249 
L1508:  bipush 3 
L1510:  bastore 
L1511:  dup 
L1512:  ldc_w 250 
L1515:  bipush 0 
L1517:  bastore 
L1518:  dup 
L1519:  ldc_w 251 
L1522:  bipush 0 
L1524:  bastore 
L1525:  dup 
L1526:  ldc_w 252 
L1529:  bipush 0 
L1531:  bastore 
L1532:  dup 
L1533:  ldc_w 253 
L1536:  bipush 19 
L1538:  bastore 
L1539:  dup 
L1540:  ldc_w 254 
L1543:  bipush 3 
L1545:  bastore 
L1546:  dup 
L1547:  ldc_w 255 
L1550:  bipush 0 
L1552:  bastore 
L1553:  dup 
L1554:  ldc_w 256 
L1557:  bipush 0 
L1559:  bastore 
L1560:  dup 
L1561:  ldc_w 257 
L1564:  bipush 0 
L1566:  bastore 
L1567:  dup 
L1568:  ldc_w 258 
L1571:  bipush 20 
L1573:  bastore 
L1574:  dup 
L1575:  ldc_w 259 
L1578:  bipush 3 
L1580:  bastore 
L1581:  dup 
L1582:  ldc_w 260 
L1585:  bipush 0 
L1587:  bastore 
L1588:  dup 
L1589:  ldc_w 261 
L1592:  bipush 0 
L1594:  bastore 
L1595:  dup 
L1596:  ldc_w 262 
L1599:  bipush 0 
L1601:  bastore 
L1602:  dup 
L1603:  ldc_w 263 
L1606:  bipush 21 
L1608:  bastore 
L1609:  dup 
L1610:  ldc_w 264 
L1613:  bipush 3 
L1615:  bastore 
L1616:  dup 
L1617:  ldc_w 265 
L1620:  bipush 0 
L1622:  bastore 
L1623:  dup 
L1624:  ldc_w 266 
L1627:  bipush 0 
L1629:  bastore 
L1630:  dup 
L1631:  ldc_w 267 
L1634:  bipush 0 
L1636:  bastore 
L1637:  dup 
L1638:  ldc_w 268 
L1641:  bipush 22 
L1643:  bastore 
L1644:  dup 
L1645:  ldc_w 269 
L1648:  bipush 3 
L1650:  bastore 
L1651:  dup 
L1652:  ldc_w 270 
L1655:  bipush 0 
L1657:  bastore 
L1658:  dup 
L1659:  ldc_w 271 
L1662:  bipush 0 
L1664:  bastore 
L1665:  dup 
L1666:  ldc_w 272 
L1669:  bipush 0 
L1671:  bastore 
L1672:  dup 
L1673:  ldc_w 273 
L1676:  bipush 23 
L1678:  bastore 
L1679:  dup 
L1680:  ldc_w 274 
L1683:  bipush 3 
L1685:  bastore 
L1686:  dup 
L1687:  ldc_w 275 
L1690:  bipush 0 
L1692:  bastore 
L1693:  dup 
L1694:  ldc_w 276 
L1697:  bipush 0 
L1699:  bastore 
L1700:  dup 
L1701:  ldc_w 277 
L1704:  bipush 0 
L1706:  bastore 
L1707:  dup 
L1708:  ldc_w 278 
L1711:  bipush 24 
L1713:  bastore 
L1714:  dup 
L1715:  ldc_w 279 
L1718:  bipush 3 
L1720:  bastore 
L1721:  dup 
L1722:  ldc_w 280 
L1725:  bipush 0 
L1727:  bastore 
L1728:  dup 
L1729:  ldc_w 281 
L1732:  bipush 0 
L1734:  bastore 
L1735:  dup 
L1736:  ldc_w 282 
L1739:  bipush 0 
L1741:  bastore 
L1742:  dup 
L1743:  ldc_w 283 
L1746:  bipush 25 
L1748:  bastore 
L1749:  dup 
L1750:  ldc_w 284 
L1753:  bipush 3 
L1755:  bastore 
L1756:  dup 
L1757:  ldc_w 285 
L1760:  bipush 0 
L1762:  bastore 
L1763:  dup 
L1764:  ldc_w 286 
L1767:  bipush 0 
L1769:  bastore 
L1770:  dup 
L1771:  ldc_w 287 
L1774:  bipush 0 
L1776:  bastore 
L1777:  dup 
L1778:  ldc_w 288 
L1781:  bipush 26 
L1783:  bastore 
L1784:  dup 
L1785:  ldc_w 289 
L1788:  bipush 3 
L1790:  bastore 
L1791:  dup 
L1792:  ldc_w 290 
L1795:  bipush 0 
L1797:  bastore 
L1798:  dup 
L1799:  ldc_w 291 
L1802:  bipush 0 
L1804:  bastore 
L1805:  dup 
L1806:  ldc_w 292 
L1809:  bipush 0 
L1811:  bastore 
L1812:  dup 
L1813:  ldc_w 293 
L1816:  bipush 27 
L1818:  bastore 
L1819:  dup 
L1820:  ldc_w 294 
L1823:  bipush 3 
L1825:  bastore 
L1826:  dup 
L1827:  ldc_w 295 
L1830:  bipush 0 
L1832:  bastore 
L1833:  dup 
L1834:  ldc_w 296 
L1837:  bipush 0 
L1839:  bastore 
L1840:  dup 
L1841:  ldc_w 297 
L1844:  bipush 0 
L1846:  bastore 
L1847:  dup 
L1848:  ldc_w 298 
L1851:  bipush 28 
L1853:  bastore 
L1854:  dup 
L1855:  ldc_w 299 
L1858:  bipush 3 
L1860:  bastore 
L1861:  dup 
L1862:  ldc_w 300 
L1865:  bipush 0 
L1867:  bastore 
L1868:  dup 
L1869:  ldc_w 301 
L1872:  bipush 0 
L1874:  bastore 
L1875:  dup 
L1876:  ldc_w 302 
L1879:  bipush 0 
L1881:  bastore 
L1882:  dup 
L1883:  ldc_w 303 
L1886:  bipush 29 
L1888:  bastore 
L1889:  dup 
L1890:  ldc_w 304 
L1893:  bipush 3 
L1895:  bastore 
L1896:  dup 
L1897:  ldc_w 305 
L1900:  bipush 0 
L1902:  bastore 
L1903:  dup 
L1904:  ldc_w 306 
L1907:  bipush 0 
L1909:  bastore 
L1910:  dup 
L1911:  ldc_w 307 
L1914:  bipush 0 
L1916:  bastore 
L1917:  dup 
L1918:  ldc_w 308 
L1921:  bipush 30 
L1923:  bastore 
L1924:  dup 
L1925:  ldc_w 309 
L1928:  bipush 3 
L1930:  bastore 
L1931:  dup 
L1932:  ldc_w 310 
L1935:  bipush 0 
L1937:  bastore 
L1938:  dup 
L1939:  ldc_w 311 
L1942:  bipush 0 
L1944:  bastore 
L1945:  dup 
L1946:  ldc_w 312 
L1949:  bipush 0 
L1951:  bastore 
L1952:  dup 
L1953:  ldc_w 313 
L1956:  bipush 31 
L1958:  bastore 
L1959:  dup 
L1960:  ldc_w 314 
L1963:  bipush 3 
L1965:  bastore 
L1966:  dup 
L1967:  ldc_w 315 
L1970:  bipush 0 
L1972:  bastore 
L1973:  dup 
L1974:  ldc_w 316 
L1977:  bipush 0 
L1979:  bastore 
L1980:  dup 
L1981:  ldc_w 317 
L1984:  bipush 0 
L1986:  bastore 
L1987:  dup 
L1988:  ldc_w 318 
L1991:  bipush 32 
L1993:  bastore 
L1994:  dup 
L1995:  ldc_w 319 
L1998:  bipush 3 
L2000:  bastore 
L2001:  dup 
L2002:  ldc_w 320 
L2005:  bipush 0 
L2007:  bastore 
L2008:  dup 
L2009:  ldc_w 321 
L2012:  bipush 0 
L2014:  bastore 
L2015:  dup 
L2016:  ldc_w 322 
L2019:  bipush 0 
L2021:  bastore 
L2022:  dup 
L2023:  ldc_w 323 
L2026:  bipush 33 
L2028:  bastore 
L2029:  dup 
L2030:  ldc_w 324 
L2033:  bipush 3 
L2035:  bastore 
L2036:  dup 
L2037:  ldc_w 325 
L2040:  bipush 0 
L2042:  bastore 
L2043:  dup 
L2044:  ldc_w 326 
L2047:  bipush 0 
L2049:  bastore 
L2050:  dup 
L2051:  ldc_w 327 
L2054:  bipush 0 
L2056:  bastore 
L2057:  dup 
L2058:  ldc_w 328 
L2061:  bipush 34 
L2063:  bastore 
L2064:  dup 
L2065:  ldc_w 329 
L2068:  bipush 3 
L2070:  bastore 
L2071:  dup 
L2072:  ldc_w 330 
L2075:  bipush 0 
L2077:  bastore 
L2078:  dup 
L2079:  ldc_w 331 
L2082:  bipush 0 
L2084:  bastore 
L2085:  dup 
L2086:  ldc_w 332 
L2089:  bipush 0 
L2091:  bastore 
L2092:  dup 
L2093:  ldc_w 333 
L2096:  bipush 35 
L2098:  bastore 
L2099:  dup 
L2100:  ldc_w 334 
L2103:  bipush 3 
L2105:  bastore 
L2106:  dup 
L2107:  ldc_w 335 
L2110:  bipush 0 
L2112:  bastore 
L2113:  dup 
L2114:  ldc_w 336 
L2117:  bipush 0 
L2119:  bastore 
L2120:  dup 
L2121:  ldc_w 337 
L2124:  bipush 0 
L2126:  bastore 
L2127:  dup 
L2128:  ldc_w 338 
L2131:  bipush 36 
L2133:  bastore 
L2134:  dup 
L2135:  ldc_w 339 
L2138:  bipush 3 
L2140:  bastore 
L2141:  dup 
L2142:  ldc_w 340 
L2145:  bipush 0 
L2147:  bastore 
L2148:  dup 
L2149:  ldc_w 341 
L2152:  bipush 0 
L2154:  bastore 
L2155:  dup 
L2156:  ldc_w 342 
L2159:  bipush 0 
L2161:  bastore 
L2162:  dup 
L2163:  ldc_w 343 
L2166:  bipush 37 
L2168:  bastore 
L2169:  dup 
L2170:  ldc_w 344 
L2173:  bipush 3 
L2175:  bastore 
L2176:  dup 
L2177:  ldc_w 345 
L2180:  bipush 0 
L2182:  bastore 
L2183:  dup 
L2184:  ldc_w 346 
L2187:  bipush 0 
L2189:  bastore 
L2190:  dup 
L2191:  ldc_w 347 
L2194:  bipush 0 
L2196:  bastore 
L2197:  dup 
L2198:  ldc_w 348 
L2201:  bipush 38 
L2203:  bastore 
L2204:  dup 
L2205:  ldc_w 349 
L2208:  bipush 3 
L2210:  bastore 
L2211:  dup 
L2212:  ldc_w 350 
L2215:  bipush 0 
L2217:  bastore 
L2218:  dup 
L2219:  ldc_w 351 
L2222:  bipush 0 
L2224:  bastore 
L2225:  dup 
L2226:  ldc_w 352 
L2229:  bipush 0 
L2231:  bastore 
L2232:  dup 
L2233:  ldc_w 353 
L2236:  bipush 39 
L2238:  bastore 
L2239:  dup 
L2240:  ldc_w 354 
L2243:  bipush 3 
L2245:  bastore 
L2246:  dup 
L2247:  ldc_w 355 
L2250:  bipush 0 
L2252:  bastore 
L2253:  dup 
L2254:  ldc_w 356 
L2257:  bipush 0 
L2259:  bastore 
L2260:  dup 
L2261:  ldc_w 357 
L2264:  bipush 0 
L2266:  bastore 
L2267:  dup 
L2268:  ldc_w 358 
L2271:  bipush 40 
L2273:  bastore 
L2274:  dup 
L2275:  ldc_w 359 
L2278:  bipush 3 
L2280:  bastore 
L2281:  dup 
L2282:  ldc_w 360 
L2285:  bipush 0 
L2287:  bastore 
L2288:  dup 
L2289:  ldc_w 361 
L2292:  bipush 0 
L2294:  bastore 
L2295:  dup 
L2296:  ldc_w 362 
L2299:  bipush 0 
L2301:  bastore 
L2302:  dup 
L2303:  ldc_w 363 
L2306:  bipush 41 
L2308:  bastore 
L2309:  dup 
L2310:  ldc_w 364 
L2313:  bipush 3 
L2315:  bastore 
L2316:  dup 
L2317:  ldc_w 365 
L2320:  bipush 0 
L2322:  bastore 
L2323:  dup 
L2324:  ldc_w 366 
L2327:  bipush 0 
L2329:  bastore 
L2330:  dup 
L2331:  ldc_w 367 
L2334:  bipush 0 
L2336:  bastore 
L2337:  dup 
L2338:  ldc_w 368 
L2341:  bipush 42 
L2343:  bastore 
L2344:  dup 
L2345:  ldc_w 369 
L2348:  bipush 3 
L2350:  bastore 
L2351:  dup 
L2352:  ldc_w 370 
L2355:  bipush 0 
L2357:  bastore 
L2358:  dup 
L2359:  ldc_w 371 
L2362:  bipush 0 
L2364:  bastore 
L2365:  dup 
L2366:  ldc_w 372 
L2369:  bipush 0 
L2371:  bastore 
L2372:  dup 
L2373:  ldc_w 373 
L2376:  bipush 43 
L2378:  bastore 
L2379:  dup 
L2380:  ldc_w 374 
L2383:  bipush 3 
L2385:  bastore 
L2386:  dup 
L2387:  ldc_w 375 
L2390:  bipush 0 
L2392:  bastore 
L2393:  dup 
L2394:  ldc_w 376 
L2397:  bipush 0 
L2399:  bastore 
L2400:  dup 
L2401:  ldc_w 377 
L2404:  bipush 0 
L2406:  bastore 
L2407:  dup 
L2408:  ldc_w 378 
L2411:  bipush 44 
L2413:  bastore 
L2414:  dup 
L2415:  ldc_w 379 
L2418:  bipush 3 
L2420:  bastore 
L2421:  dup 
L2422:  ldc_w 380 
L2425:  bipush 0 
L2427:  bastore 
L2428:  dup 
L2429:  ldc_w 381 
L2432:  bipush 0 
L2434:  bastore 
L2435:  dup 
L2436:  ldc_w 382 
L2439:  bipush 0 
L2441:  bastore 
L2442:  dup 
L2443:  ldc_w 383 
L2446:  bipush 45 
L2448:  bastore 
L2449:  dup 
L2450:  ldc_w 384 
L2453:  bipush 3 
L2455:  bastore 
L2456:  dup 
L2457:  ldc_w 385 
L2460:  bipush 0 
L2462:  bastore 
L2463:  dup 
L2464:  ldc_w 386 
L2467:  bipush 0 
L2469:  bastore 
L2470:  dup 
L2471:  ldc_w 387 
L2474:  bipush 0 
L2476:  bastore 
L2477:  dup 
L2478:  ldc_w 388 
L2481:  bipush 46 
L2483:  bastore 
L2484:  dup 
L2485:  ldc_w 389 
L2488:  bipush 3 
L2490:  bastore 
L2491:  dup 
L2492:  ldc_w 390 
L2495:  bipush 0 
L2497:  bastore 
L2498:  dup 
L2499:  ldc_w 391 
L2502:  bipush 0 
L2504:  bastore 
L2505:  dup 
L2506:  ldc_w 392 
L2509:  bipush 0 
L2511:  bastore 
L2512:  dup 
L2513:  ldc_w 393 
L2516:  bipush 47 
L2518:  bastore 
L2519:  dup 
L2520:  ldc_w 394 
L2523:  bipush 3 
L2525:  bastore 
L2526:  dup 
L2527:  ldc_w 395 
L2530:  bipush 0 
L2532:  bastore 
L2533:  dup 
L2534:  ldc_w 396 
L2537:  bipush 0 
L2539:  bastore 
L2540:  dup 
L2541:  ldc_w 397 
L2544:  bipush 0 
L2546:  bastore 
L2547:  dup 
L2548:  ldc_w 398 
L2551:  bipush 48 
L2553:  bastore 
L2554:  dup 
L2555:  ldc_w 399 
L2558:  bipush 3 
L2560:  bastore 
L2561:  dup 
L2562:  ldc_w 400 
L2565:  bipush 0 
L2567:  bastore 
L2568:  dup 
L2569:  ldc_w 401 
L2572:  bipush 0 
L2574:  bastore 
L2575:  dup 
L2576:  ldc_w 402 
L2579:  bipush 0 
L2581:  bastore 
L2582:  dup 
L2583:  ldc_w 403 
L2586:  bipush 49 
L2588:  bastore 
L2589:  dup 
L2590:  ldc_w 404 
L2593:  bipush 3 
L2595:  bastore 
L2596:  dup 
L2597:  ldc_w 405 
L2600:  bipush 0 
L2602:  bastore 
L2603:  dup 
L2604:  ldc_w 406 
L2607:  bipush 0 
L2609:  bastore 
L2610:  dup 
L2611:  ldc_w 407 
L2614:  bipush 0 
L2616:  bastore 
L2617:  dup 
L2618:  ldc_w 408 
L2621:  bipush 50 
L2623:  bastore 
L2624:  dup 
L2625:  ldc_w 409 
L2628:  bipush 3 
L2630:  bastore 
L2631:  dup 
L2632:  ldc_w 410 
L2635:  bipush 0 
L2637:  bastore 
L2638:  dup 
L2639:  ldc_w 411 
L2642:  bipush 0 
L2644:  bastore 
L2645:  dup 
L2646:  ldc_w 412 
L2649:  bipush 0 
L2651:  bastore 
L2652:  dup 
L2653:  ldc_w 413 
L2656:  bipush 51 
L2658:  bastore 
L2659:  dup 
L2660:  ldc_w 414 
L2663:  bipush 3 
L2665:  bastore 
L2666:  dup 
L2667:  ldc_w 415 
L2670:  bipush 0 
L2672:  bastore 
L2673:  dup 
L2674:  ldc_w 416 
L2677:  bipush 0 
L2679:  bastore 
L2680:  dup 
L2681:  ldc_w 417 
L2684:  bipush 0 
L2686:  bastore 
L2687:  dup 
L2688:  ldc_w 418 
L2691:  bipush 52 
L2693:  bastore 
L2694:  dup 
L2695:  ldc_w 419 
L2698:  bipush 3 
L2700:  bastore 
L2701:  dup 
L2702:  ldc_w 420 
L2705:  bipush 0 
L2707:  bastore 
L2708:  dup 
L2709:  ldc_w 421 
L2712:  bipush 0 
L2714:  bastore 
L2715:  dup 
L2716:  ldc_w 422 
L2719:  bipush 0 
L2721:  bastore 
L2722:  dup 
L2723:  ldc_w 423 
L2726:  bipush 53 
L2728:  bastore 
L2729:  dup 
L2730:  ldc_w 424 
L2733:  bipush 3 
L2735:  bastore 
L2736:  dup 
L2737:  ldc_w 425 
L2740:  bipush 0 
L2742:  bastore 
L2743:  dup 
L2744:  ldc_w 426 
L2747:  bipush 0 
L2749:  bastore 
L2750:  dup 
L2751:  ldc_w 427 
L2754:  bipush 0 
L2756:  bastore 
L2757:  dup 
L2758:  ldc_w 428 
L2761:  bipush 54 
L2763:  bastore 
L2764:  dup 
L2765:  ldc_w 429 
L2768:  bipush 3 
L2770:  bastore 
L2771:  dup 
L2772:  ldc_w 430 
L2775:  bipush 0 
L2777:  bastore 
L2778:  dup 
L2779:  ldc_w 431 
L2782:  bipush 0 
L2784:  bastore 
L2785:  dup 
L2786:  ldc_w 432 
L2789:  bipush 0 
L2791:  bastore 
L2792:  dup 
L2793:  ldc_w 433 
L2796:  bipush 55 
L2798:  bastore 
L2799:  dup 
L2800:  ldc_w 434 
L2803:  bipush 3 
L2805:  bastore 
L2806:  dup 
L2807:  ldc_w 435 
L2810:  bipush 0 
L2812:  bastore 
L2813:  dup 
L2814:  ldc_w 436 
L2817:  bipush 0 
L2819:  bastore 
L2820:  dup 
L2821:  ldc_w 437 
L2824:  bipush 0 
L2826:  bastore 
L2827:  dup 
L2828:  ldc_w 438 
L2831:  bipush 56 
L2833:  bastore 
L2834:  dup 
L2835:  ldc_w 439 
L2838:  bipush 3 
L2840:  bastore 
L2841:  dup 
L2842:  ldc_w 440 
L2845:  bipush 0 
L2847:  bastore 
L2848:  dup 
L2849:  ldc_w 441 
L2852:  bipush 0 
L2854:  bastore 
L2855:  dup 
L2856:  ldc_w 442 
L2859:  bipush 0 
L2861:  bastore 
L2862:  dup 
L2863:  ldc_w 443 
L2866:  bipush 57 
L2868:  bastore 
L2869:  dup 
L2870:  ldc_w 444 
L2873:  bipush 3 
L2875:  bastore 
L2876:  dup 
L2877:  ldc_w 445 
L2880:  bipush 0 
L2882:  bastore 
L2883:  dup 
L2884:  ldc_w 446 
L2887:  bipush 0 
L2889:  bastore 
L2890:  dup 
L2891:  ldc_w 447 
L2894:  bipush 0 
L2896:  bastore 
L2897:  dup 
L2898:  ldc_w 448 
L2901:  bipush 58 
L2903:  bastore 
L2904:  dup 
L2905:  ldc_w 449 
L2908:  bipush 3 
L2910:  bastore 
L2911:  dup 
L2912:  ldc_w 450 
L2915:  bipush 0 
L2917:  bastore 
L2918:  dup 
L2919:  ldc_w 451 
L2922:  bipush 0 
L2924:  bastore 
L2925:  dup 
L2926:  ldc_w 452 
L2929:  bipush 0 
L2931:  bastore 
L2932:  dup 
L2933:  ldc_w 453 
L2936:  bipush 59 
L2938:  bastore 
L2939:  dup 
L2940:  ldc_w 454 
L2943:  bipush 3 
L2945:  bastore 
L2946:  dup 
L2947:  ldc_w 455 
L2950:  bipush 0 
L2952:  bastore 
L2953:  dup 
L2954:  ldc_w 456 
L2957:  bipush 0 
L2959:  bastore 
L2960:  dup 
L2961:  ldc_w 457 
L2964:  bipush 0 
L2966:  bastore 
L2967:  dup 
L2968:  ldc_w 458 
L2971:  bipush 60 
L2973:  bastore 
L2974:  dup 
L2975:  ldc_w 459 
L2978:  bipush 3 
L2980:  bastore 
L2981:  dup 
L2982:  ldc_w 460 
L2985:  bipush 0 
L2987:  bastore 
L2988:  dup 
L2989:  ldc_w 461 
L2992:  bipush 0 
L2994:  bastore 
L2995:  dup 
L2996:  ldc_w 462 
L2999:  bipush 0 
L3001:  bastore 
L3002:  dup 
L3003:  ldc_w 463 
L3006:  bipush 61 
L3008:  bastore 
L3009:  dup 
L3010:  ldc_w 464 
L3013:  bipush 3 
L3015:  bastore 
L3016:  dup 
L3017:  ldc_w 465 
L3020:  bipush 0 
L3022:  bastore 
L3023:  dup 
L3024:  ldc_w 466 
L3027:  bipush 0 
L3029:  bastore 
L3030:  dup 
L3031:  ldc_w 467 
L3034:  bipush 0 
L3036:  bastore 
L3037:  dup 
L3038:  ldc_w 468 
L3041:  bipush 62 
L3043:  bastore 
L3044:  dup 
L3045:  ldc_w 469 
L3048:  bipush 3 
L3050:  bastore 
L3051:  dup 
L3052:  ldc_w 470 
L3055:  bipush 0 
L3057:  bastore 
L3058:  dup 
L3059:  ldc_w 471 
L3062:  bipush 0 
L3064:  bastore 
L3065:  dup 
L3066:  ldc_w 472 
L3069:  bipush 0 
L3071:  bastore 
L3072:  dup 
L3073:  ldc_w 473 
L3076:  bipush 63 
L3078:  bastore 
L3079:  dup 
L3080:  ldc_w 474 
L3083:  bipush 3 
L3085:  bastore 
L3086:  dup 
L3087:  ldc_w 475 
L3090:  bipush 0 
L3092:  bastore 
L3093:  dup 
L3094:  ldc_w 476 
L3097:  bipush 0 
L3099:  bastore 
L3100:  dup 
L3101:  ldc_w 477 
L3104:  bipush 0 
L3106:  bastore 
L3107:  dup 
L3108:  ldc_w 478 
L3111:  bipush 64 
L3113:  bastore 
L3114:  dup 
L3115:  ldc_w 479 
L3118:  bipush 3 
L3120:  bastore 
L3121:  dup 
L3122:  ldc_w 480 
L3125:  bipush 0 
L3127:  bastore 
L3128:  dup 
L3129:  ldc_w 481 
L3132:  bipush 0 
L3134:  bastore 
L3135:  dup 
L3136:  ldc_w 482 
L3139:  bipush 0 
L3141:  bastore 
L3142:  dup 
L3143:  ldc_w 483 
L3146:  bipush 65 
L3148:  bastore 
L3149:  dup 
L3150:  ldc_w 484 
L3153:  bipush 1 
L3155:  bastore 
L3156:  dup 
L3157:  ldc_w 485 
L3160:  bipush 0 
L3162:  bastore 
L3163:  dup 
L3164:  ldc_w 486 
L3167:  bipush 13 
L3169:  bastore 
L3170:  dup 
L3171:  ldc_w 487 
L3174:  bipush 106 
L3176:  bastore 
L3177:  dup 
L3178:  ldc_w 488 
L3181:  bipush 97 
L3183:  bastore 
L3184:  dup 
L3185:  ldc_w 489 
L3188:  bipush 118 
L3190:  bastore 
L3191:  dup 
L3192:  ldc_w 490 
L3195:  bipush 97 
L3197:  bastore 
L3198:  dup 
L3199:  ldc_w 491 
L3202:  bipush 47 
L3204:  bastore 
L3205:  dup 
L3206:  ldc_w 492 
L3209:  bipush 117 
L3211:  bastore 
L3212:  dup 
L3213:  ldc_w 493 
L3216:  bipush 116 
L3218:  bastore 
L3219:  dup 
L3220:  ldc_w 494 
L3223:  bipush 105 
L3225:  bastore 
L3226:  dup 
L3227:  ldc_w 495 
L3230:  bipush 108 
L3232:  bastore 
L3233:  dup 
L3234:  ldc_w 496 
L3237:  bipush 47 
L3239:  bastore 
L3240:  dup 
L3241:  ldc_w 497 
L3244:  bipush 77 
L3246:  bastore 
L3247:  dup 
L3248:  ldc_w 498 
L3251:  bipush 97 
L3253:  bastore 
L3254:  dup 
L3255:  ldc_w 499 
L3258:  bipush 112 
L3260:  bastore 
L3261:  dup 
L3262:  ldc_w 500 
L3265:  bipush 7 
L3267:  bastore 
L3268:  dup 
L3269:  ldc_w 501 
L3272:  bipush 0 
L3274:  bastore 
L3275:  dup 
L3276:  ldc_w 502 
L3279:  bipush 80 
L3281:  bastore 
L3282:  dup 
L3283:  ldc_w 503 
L3286:  bipush 1 
L3288:  bastore 
L3289:  dup 
L3290:  ldc_w 504 
L3293:  bipush 0 
L3295:  bastore 
L3296:  dup 
L3297:  ldc_w 505 
L3300:  bipush 5 
L3302:  bastore 
L3303:  dup 
L3304:  ldc_w 506 
L3307:  bipush 101 
L3309:  bastore 
L3310:  dup 
L3311:  ldc_w 507 
L3314:  bipush 110 
L3316:  bastore 
L3317:  dup 
L3318:  ldc_w 508 
L3321:  bipush 116 
L3323:  bastore 
L3324:  dup 
L3325:  ldc_w 509 
L3328:  bipush 114 
L3330:  bastore 
L3331:  dup 
L3332:  ldc_w 510 
L3335:  bipush 121 
L3337:  bastore 
L3338:  dup 
L3339:  ldc_w 511 
L3342:  bipush 1 
L3344:  bastore 
L3345:  dup 
L3346:  ldc_w 512 
L3349:  bipush 0 
L3351:  bastore 
L3352:  dup 
L3353:  ldc_w 513 
L3356:  bipush 59 
L3358:  bastore 
L3359:  dup 
L3360:  ldc_w 514 
L3363:  bipush 40 
L3365:  bastore 
L3366:  dup 
L3367:  ldc_w 515 
L3370:  bipush 76 
L3372:  bastore 
L3373:  dup 
L3374:  ldc_w 516 
L3377:  bipush 106 
L3379:  bastore 
L3380:  dup 
L3381:  ldc_w 517 
L3384:  bipush 97 
L3386:  bastore 
L3387:  dup 
L3388:  ldc_w 518 
L3391:  bipush 118 
L3393:  bastore 
L3394:  dup 
L3395:  ldc_w 519 
L3398:  bipush 97 
L3400:  bastore 
L3401:  dup 
L3402:  ldc_w 520 
L3405:  bipush 47 
L3407:  bastore 
L3408:  dup 
L3409:  ldc_w 521 
L3412:  bipush 108 
L3414:  bastore 
L3415:  dup 
L3416:  ldc_w 522 
L3419:  bipush 97 
L3421:  bastore 
L3422:  dup 
L3423:  ldc_w 523 
L3426:  bipush 110 
L3428:  bastore 
L3429:  dup 
L3430:  ldc_w 524 
L3433:  bipush 103 
L3435:  bastore 
L3436:  dup 
L3437:  ldc_w 525 
L3440:  bipush 47 
L3442:  bastore 
L3443:  dup 
L3444:  ldc_w 526 
L3447:  bipush 79 
L3449:  bastore 
L3450:  dup 
L3451:  ldc_w 527 
L3454:  bipush 98 
L3456:  bastore 
L3457:  dup 
L3458:  ldc_w 528 
L3461:  bipush 106 
L3463:  bastore 
L3464:  dup 
L3465:  ldc_w 529 
L3468:  bipush 101 
L3470:  bastore 
L3471:  dup 
L3472:  ldc_w 530 
L3475:  bipush 99 
L3477:  bastore 
L3478:  dup 
L3479:  ldc_w 531 
L3482:  bipush 116 
L3484:  bastore 
L3485:  dup 
L3486:  ldc_w 532 
L3489:  bipush 59 
L3491:  bastore 
L3492:  dup 
L3493:  ldc_w 533 
L3496:  bipush 76 
L3498:  bastore 
L3499:  dup 
L3500:  ldc_w 534 
L3503:  bipush 106 
L3505:  bastore 
L3506:  dup 
L3507:  ldc_w 535 
L3510:  bipush 97 
L3512:  bastore 
L3513:  dup 
L3514:  ldc_w 536 
L3517:  bipush 118 
L3519:  bastore 
L3520:  dup 
L3521:  ldc_w 537 
L3524:  bipush 97 
L3526:  bastore 
L3527:  dup 
L3528:  ldc_w 538 
L3531:  bipush 47 
L3533:  bastore 
L3534:  dup 
L3535:  ldc_w 539 
L3538:  bipush 108 
L3540:  bastore 
L3541:  dup 
L3542:  ldc_w 540 
L3545:  bipush 97 
L3547:  bastore 
L3548:  dup 
L3549:  ldc_w 541 
L3552:  bipush 110 
L3554:  bastore 
L3555:  dup 
L3556:  ldc_w 542 
L3559:  bipush 103 
L3561:  bastore 
L3562:  dup 
L3563:  ldc_w 543 
L3566:  bipush 47 
L3568:  bastore 
L3569:  dup 
L3570:  ldc_w 544 
L3573:  bipush 79 
L3575:  bastore 
L3576:  dup 
L3577:  ldc_w 545 
L3580:  bipush 98 
L3582:  bastore 
L3583:  dup 
L3584:  ldc_w 546 
L3587:  bipush 106 
L3589:  bastore 
L3590:  dup 
L3591:  ldc_w 547 
L3594:  bipush 101 
L3596:  bastore 
L3597:  dup 
L3598:  ldc_w 548 
L3601:  bipush 99 
L3603:  bastore 
L3604:  dup 
L3605:  ldc_w 549 
L3608:  bipush 116 
L3610:  bastore 
L3611:  dup 
L3612:  ldc_w 550 
L3615:  bipush 59 
L3617:  bastore 
L3618:  dup 
L3619:  ldc_w 551 
L3622:  bipush 41 
L3624:  bastore 
L3625:  dup 
L3626:  ldc_w 552 
L3629:  bipush 76 
L3631:  bastore 
L3632:  dup 
L3633:  ldc_w 553 
L3636:  bipush 106 
L3638:  bastore 
L3639:  dup 
L3640:  ldc_w 554 
L3643:  bipush 97 
L3645:  bastore 
L3646:  dup 
L3647:  ldc_w 555 
L3650:  bipush 118 
L3652:  bastore 
L3653:  dup 
L3654:  ldc_w 556 
L3657:  bipush 97 
L3659:  bastore 
L3660:  dup 
L3661:  ldc_w 557 
L3664:  bipush 47 
L3666:  bastore 
L3667:  dup 
L3668:  ldc_w 558 
L3671:  bipush 117 
L3673:  bastore 
L3674:  dup 
L3675:  ldc_w 559 
L3678:  bipush 116 
L3680:  bastore 
L3681:  dup 
L3682:  ldc_w 560 
L3685:  bipush 105 
L3687:  bastore 
L3688:  dup 
L3689:  ldc_w 561 
L3692:  bipush 108 
L3694:  bastore 
L3695:  dup 
L3696:  ldc_w 562 
L3699:  bipush 47 
L3701:  bastore 
L3702:  dup 
L3703:  ldc_w 563 
L3706:  bipush 77 
L3708:  bastore 
L3709:  dup 
L3710:  ldc_w 564 
L3713:  bipush 97 
L3715:  bastore 
L3716:  dup 
L3717:  ldc_w 565 
L3720:  bipush 112 
L3722:  bastore 
L3723:  dup 
L3724:  ldc_w 566 
L3727:  bipush 36 
L3729:  bastore 
L3730:  dup 
L3731:  ldc_w 567 
L3734:  bipush 69 
L3736:  bastore 
L3737:  dup 
L3738:  ldc_w 568 
L3741:  bipush 110 
L3743:  bastore 
L3744:  dup 
L3745:  ldc_w 569 
L3748:  bipush 116 
L3750:  bastore 
L3751:  dup 
L3752:  ldc_w 570 
L3755:  bipush 114 
L3757:  bastore 
L3758:  dup 
L3759:  ldc_w 571 
L3762:  bipush 121 
L3764:  bastore 
L3765:  dup 
L3766:  ldc_w 572 
L3769:  bipush 59 
L3771:  bastore 
L3772:  dup 
L3773:  ldc_w 573 
L3776:  bipush 12 
L3778:  bastore 
L3779:  dup 
L3780:  ldc_w 574 
L3783:  bipush 0 
L3785:  bastore 
L3786:  dup 
L3787:  ldc_w 575 
L3790:  bipush 82 
L3792:  bastore 
L3793:  dup 
L3794:  ldc_w 576 
L3797:  bipush 0 
L3799:  bastore 
L3800:  dup 
L3801:  ldc_w 577 
L3804:  bipush 83 
L3806:  bastore 
L3807:  dup 
L3808:  ldc_w 578 
L3811:  bipush 11 
L3813:  bastore 
L3814:  dup 
L3815:  ldc_w 579 
L3818:  bipush 0 
L3820:  bastore 
L3821:  dup 
L3822:  ldc_w 580 
L3825:  bipush 81 
L3827:  bastore 
L3828:  dup 
L3829:  ldc_w 581 
L3832:  bipush 0 
L3834:  bastore 
L3835:  dup 
L3836:  ldc_w 582 
L3839:  bipush 84 
L3841:  bastore 
L3842:  dup 
L3843:  ldc_w 583 
L3846:  bipush 1 
L3848:  bastore 
L3849:  dup 
L3850:  ldc_w 584 
L3853:  bipush 0 
L3855:  bastore 
L3856:  dup 
L3857:  ldc_w 585 
L3860:  bipush 9 
L3862:  bastore 
L3863:  dup 
L3864:  ldc_w 586 
L3867:  bipush 111 
L3869:  bastore 
L3870:  dup 
L3871:  ldc_w 587 
L3874:  bipush 102 
L3876:  bastore 
L3877:  dup 
L3878:  ldc_w 588 
L3881:  bipush 69 
L3883:  bastore 
L3884:  dup 
L3885:  ldc_w 589 
L3888:  bipush 110 
L3890:  bastore 
L3891:  dup 
L3892:  ldc_w 590 
L3895:  bipush 116 
L3897:  bastore 
L3898:  dup 
L3899:  ldc_w 591 
L3902:  bipush 114 
L3904:  bastore 
L3905:  dup 
L3906:  ldc_w 592 
L3909:  bipush 105 
L3911:  bastore 
L3912:  dup 
L3913:  ldc_w 593 
L3916:  bipush 101 
L3918:  bastore 
L3919:  dup 
L3920:  ldc_w 594 
L3923:  bipush 115 
L3925:  bastore 
L3926:  dup 
L3927:  ldc_w 595 
L3930:  bipush 1 
L3932:  bastore 
L3933:  dup 
L3934:  ldc_w 596 
L3937:  bipush 0 
L3939:  bastore 
L3940:  dup 
L3941:  ldc_w 597 
L3944:  bipush 39 
L3946:  bastore 
L3947:  dup 
L3948:  ldc_w 598 
L3951:  bipush 40 
L3953:  bastore 
L3954:  dup 
L3955:  ldc_w 599 
L3958:  bipush 91 
L3960:  bastore 
L3961:  dup 
L3962:  ldc_w 600 
L3965:  bipush 76 
L3967:  bastore 
L3968:  dup 
L3969:  ldc_w 601 
L3972:  bipush 106 
L3974:  bastore 
L3975:  dup 
L3976:  ldc_w 602 
L3979:  bipush 97 
L3981:  bastore 
L3982:  dup 
L3983:  ldc_w 603 
L3986:  bipush 118 
L3988:  bastore 
L3989:  dup 
L3990:  ldc_w 604 
L3993:  bipush 97 
L3995:  bastore 
L3996:  dup 
L3997:  ldc_w 605 
L4000:  bipush 47 
L4002:  bastore 
L4003:  dup 
L4004:  ldc_w 606 
L4007:  bipush 117 
L4009:  bastore 
L4010:  dup 
L4011:  ldc_w 607 
L4014:  bipush 116 
L4016:  bastore 
L4017:  dup 
L4018:  ldc_w 608 
L4021:  bipush 105 
L4023:  bastore 
L4024:  dup 
L4025:  ldc_w 609 
L4028:  bipush 108 
L4030:  bastore 
L4031:  dup 
L4032:  ldc_w 610 
L4035:  bipush 47 
L4037:  bastore 
L4038:  dup 
L4039:  ldc_w 611 
L4042:  bipush 77 
L4044:  bastore 
L4045:  dup 
L4046:  ldc_w 612 
L4049:  bipush 97 
L4051:  bastore 
L4052:  dup 
L4053:  ldc_w 613 
L4056:  bipush 112 
L4058:  bastore 
L4059:  dup 
L4060:  ldc_w 614 
L4063:  bipush 36 
L4065:  bastore 
L4066:  dup 
L4067:  ldc_w 615 
L4070:  bipush 69 
L4072:  bastore 
L4073:  dup 
L4074:  ldc_w 616 
L4077:  bipush 110 
L4079:  bastore 
L4080:  dup 
L4081:  ldc_w 617 
L4084:  bipush 116 
L4086:  bastore 
L4087:  dup 
L4088:  ldc_w 618 
L4091:  bipush 114 
L4093:  bastore 
L4094:  dup 
L4095:  ldc_w 619 
L4098:  bipush 121 
L4100:  bastore 
L4101:  dup 
L4102:  ldc_w 620 
L4105:  bipush 59 
L4107:  bastore 
L4108:  dup 
L4109:  ldc_w 621 
L4112:  bipush 41 
L4114:  bastore 
L4115:  dup 
L4116:  ldc_w 622 
L4119:  bipush 76 
L4121:  bastore 
L4122:  dup 
L4123:  ldc_w 623 
L4126:  bipush 106 
L4128:  bastore 
L4129:  dup 
L4130:  ldc_w 624 
L4133:  bipush 97 
L4135:  bastore 
L4136:  dup 
L4137:  ldc_w 625 
L4140:  bipush 118 
L4142:  bastore 
L4143:  dup 
L4144:  ldc_w 626 
L4147:  bipush 97 
L4149:  bastore 
L4150:  dup 
L4151:  ldc_w 627 
L4154:  bipush 47 
L4156:  bastore 
L4157:  dup 
L4158:  ldc_w 628 
L4161:  bipush 117 
L4163:  bastore 
L4164:  dup 
L4165:  ldc_w 629 
L4168:  bipush 116 
L4170:  bastore 
L4171:  dup 
L4172:  ldc_w 630 
L4175:  bipush 105 
L4177:  bastore 
L4178:  dup 
L4179:  ldc_w 631 
L4182:  bipush 108 
L4184:  bastore 
L4185:  dup 
L4186:  ldc_w 632 
L4189:  bipush 47 
L4191:  bastore 
L4192:  dup 
L4193:  ldc_w 633 
L4196:  bipush 77 
L4198:  bastore 
L4199:  dup 
L4200:  ldc_w 634 
L4203:  bipush 97 
L4205:  bastore 
L4206:  dup 
L4207:  ldc_w 635 
L4210:  bipush 112 
L4212:  bastore 
L4213:  dup 
L4214:  ldc_w 636 
L4217:  bipush 59 
L4219:  bastore 
L4220:  dup 
L4221:  ldc_w 637 
L4224:  bipush 12 
L4226:  bastore 
L4227:  dup 
L4228:  ldc_w 638 
L4231:  bipush 0 
L4233:  bastore 
L4234:  dup 
L4235:  ldc_w 639 
L4238:  bipush 86 
L4240:  bastore 
L4241:  dup 
L4242:  ldc_w 640 
L4245:  bipush 0 
L4247:  bastore 
L4248:  dup 
L4249:  ldc_w 641 
L4252:  bipush 87 
L4254:  bastore 
L4255:  dup 
L4256:  ldc_w 642 
L4259:  bipush 11 
L4261:  bastore 
L4262:  dup 
L4263:  ldc_w 643 
L4266:  bipush 0 
L4268:  bastore 
L4269:  dup 
L4270:  ldc_w 644 
L4273:  bipush 81 
L4275:  bastore 
L4276:  dup 
L4277:  ldc_w 645 
L4280:  bipush 0 
L4282:  bastore 
L4283:  dup 
L4284:  ldc_w 646 
L4287:  bipush 88 
L4289:  bastore 
L4290:  dup 
L4291:  ldc_w 647 
L4294:  bipush 12 
L4296:  bastore 
L4297:  dup 
L4298:  ldc_w 648 
L4301:  bipush 0 
L4303:  bastore 
L4304:  dup 
L4305:  ldc_w 649 
L4308:  bipush 5 
L4310:  bastore 
L4311:  dup 
L4312:  ldc_w 650 
L4315:  bipush 0 
L4317:  bastore 
L4318:  dup 
L4319:  ldc_w 651 
L4322:  bipush 6 
L4324:  bastore 
L4325:  dup 
L4326:  ldc_w 652 
L4329:  bipush 9 
L4331:  bastore 
L4332:  dup 
L4333:  ldc_w 653 
L4336:  bipush 0 
L4338:  bastore 
L4339:  dup 
L4340:  ldc_w 654 
L4343:  bipush 2 
L4345:  bastore 
L4346:  dup 
L4347:  ldc_w 655 
L4350:  bipush 0 
L4352:  bastore 
L4353:  dup 
L4354:  ldc_w 656 
L4357:  bipush 90 
L4359:  bastore 
L4360:  dup 
L4361:  ldc_w 657 
L4364:  bipush 1 
L4366:  bastore 
L4367:  dup 
L4368:  ldc_w 658 
L4371:  bipush 0 
L4373:  bastore 
L4374:  dup 
L4375:  ldc_w 659 
L4378:  bipush 21 
L4380:  bastore 
L4381:  dup 
L4382:  ldc_w 660 
L4385:  bipush 40 
L4387:  bastore 
L4388:  dup 
L4389:  ldc_w 661 
L4392:  bipush 73 
L4394:  bastore 
L4395:  dup 
L4396:  ldc_w 662 
L4399:  bipush 41 
L4401:  bastore 
L4402:  dup 
L4403:  ldc_w 663 
L4406:  bipush 76 
L4408:  bastore 
L4409:  dup 
L4410:  ldc_w 664 
L4413:  bipush 106 
L4415:  bastore 
L4416:  dup 
L4417:  ldc_w 665 
L4420:  bipush 97 
L4422:  bastore 
L4423:  dup 
L4424:  ldc_w 666 
L4427:  bipush 118 
L4429:  bastore 
L4430:  dup 
L4431:  ldc_w 667 
L4434:  bipush 97 
L4436:  bastore 
L4437:  dup 
L4438:  ldc_w 668 
L4441:  bipush 47 
L4443:  bastore 
L4444:  dup 
L4445:  ldc_w 669 
L4448:  bipush 108 
L4450:  bastore 
L4451:  dup 
L4452:  ldc_w 670 
L4455:  bipush 97 
L4457:  bastore 
L4458:  dup 
L4459:  ldc_w 671 
L4462:  bipush 110 
L4464:  bastore 
L4465:  dup 
L4466:  ldc_w 672 
L4469:  bipush 103 
L4471:  bastore 
L4472:  dup 
L4473:  ldc_w 673 
L4476:  bipush 47 
L4478:  bastore 
L4479:  dup 
L4480:  ldc_w 674 
L4483:  bipush 83 
L4485:  bastore 
L4486:  dup 
L4487:  ldc_w 675 
L4490:  bipush 116 
L4492:  bastore 
L4493:  dup 
L4494:  ldc_w 676 
L4497:  bipush 114 
L4499:  bastore 
L4500:  dup 
L4501:  ldc_w 677 
L4504:  bipush 105 
L4506:  bastore 
L4507:  dup 
L4508:  ldc_w 678 
L4511:  bipush 110 
L4513:  bastore 
L4514:  dup 
L4515:  ldc_w 679 
L4518:  bipush 103 
L4520:  bastore 
L4521:  dup 
L4522:  ldc_w 680 
L4525:  bipush 59 
L4527:  bastore 
L4528:  dup 
L4529:  ldc_w 681 
L4532:  bipush 1 
L4534:  bastore 
L4535:  dup 
L4536:  ldc_w 682 
L4539:  bipush 0 
L4541:  bastore 
L4542:  dup 
L4543:  ldc_w 683 
L4546:  bipush 16 
L4548:  bastore 
L4549:  dup 
L4550:  ldc_w 684 
L4553:  bipush 106 
L4555:  bastore 
L4556:  dup 
L4557:  ldc_w 685 
L4560:  bipush 97 
L4562:  bastore 
L4563:  dup 
L4564:  ldc_w 686 
L4567:  bipush 118 
L4569:  bastore 
L4570:  dup 
L4571:  ldc_w 687 
L4574:  bipush 97 
L4576:  bastore 
L4577:  dup 
L4578:  ldc_w 688 
L4581:  bipush 47 
L4583:  bastore 
L4584:  dup 
L4585:  ldc_w 689 
L4588:  bipush 108 
L4590:  bastore 
L4591:  dup 
L4592:  ldc_w 690 
L4595:  bipush 97 
L4597:  bastore 
L4598:  dup 
L4599:  ldc_w 691 
L4602:  bipush 110 
L4604:  bastore 
L4605:  dup 
L4606:  ldc_w 692 
L4609:  bipush 103 
L4611:  bastore 
L4612:  dup 
L4613:  ldc_w 693 
L4616:  bipush 47 
L4618:  bastore 
L4619:  dup 
L4620:  ldc_w 694 
L4623:  bipush 83 
L4625:  bastore 
L4626:  dup 
L4627:  ldc_w 695 
L4630:  bipush 116 
L4632:  bastore 
L4633:  dup 
L4634:  ldc_w 696 
L4637:  bipush 114 
L4639:  bastore 
L4640:  dup 
L4641:  ldc_w 697 
L4644:  bipush 105 
L4646:  bastore 
L4647:  dup 
L4648:  ldc_w 698 
L4651:  bipush 110 
L4653:  bastore 
L4654:  dup 
L4655:  ldc_w 699 
L4658:  bipush 103 
L4660:  bastore 
L4661:  dup 
L4662:  ldc_w 700 
L4665:  bipush 7 
L4667:  bastore 
L4668:  dup 
L4669:  ldc_w 701 
L4672:  bipush 0 
L4674:  bastore 
L4675:  dup 
L4676:  ldc_w 702 
L4679:  bipush 93 
L4681:  bastore 
L4682:  dup 
L4683:  ldc_w 703 
L4686:  bipush 1 
L4688:  bastore 
L4689:  dup 
L4690:  ldc_w 704 
L4693:  bipush 0 
L4695:  bastore 
L4696:  dup 
L4697:  ldc_w 705 
L4700:  bipush 3 
L4702:  bastore 
L4703:  dup 
L4704:  ldc_w 706 
L4707:  bipush 103 
L4709:  bastore 
L4710:  dup 
L4711:  ldc_w 707 
L4714:  bipush 101 
L4716:  bastore 
L4717:  dup 
L4718:  ldc_w 708 
L4721:  bipush 116 
L4723:  bastore 
L4724:  dup 
L4725:  ldc_w 709 
L4728:  bipush 1 
L4730:  bastore 
L4731:  dup 
L4732:  ldc_w 710 
L4735:  bipush 0 
L4737:  bastore 
L4738:  dup 
L4739:  ldc_w 711 
L4742:  bipush 38 
L4744:  bastore 
L4745:  dup 
L4746:  ldc_w 712 
L4749:  bipush 40 
L4751:  bastore 
L4752:  dup 
L4753:  ldc_w 713 
L4756:  bipush 76 
L4758:  bastore 
L4759:  dup 
L4760:  ldc_w 714 
L4763:  bipush 106 
L4765:  bastore 
L4766:  dup 
L4767:  ldc_w 715 
L4770:  bipush 97 
L4772:  bastore 
L4773:  dup 
L4774:  ldc_w 716 
L4777:  bipush 118 
L4779:  bastore 
L4780:  dup 
L4781:  ldc_w 717 
L4784:  bipush 97 
L4786:  bastore 
L4787:  dup 
L4788:  ldc_w 718 
L4791:  bipush 47 
L4793:  bastore 
L4794:  dup 
L4795:  ldc_w 719 
L4798:  bipush 108 
L4800:  bastore 
L4801:  dup 
L4802:  ldc_w 720 
L4805:  bipush 97 
L4807:  bastore 
L4808:  dup 
L4809:  ldc_w 721 
L4812:  bipush 110 
L4814:  bastore 
L4815:  dup 
L4816:  ldc_w 722 
L4819:  bipush 103 
L4821:  bastore 
L4822:  dup 
L4823:  ldc_w 723 
L4826:  bipush 47 
L4828:  bastore 
L4829:  dup 
L4830:  ldc_w 724 
L4833:  bipush 79 
L4835:  bastore 
L4836:  dup 
L4837:  ldc_w 725 
L4840:  bipush 98 
L4842:  bastore 
L4843:  dup 
L4844:  ldc_w 726 
L4847:  bipush 106 
L4849:  bastore 
L4850:  dup 
L4851:  ldc_w 727 
L4854:  bipush 101 
L4856:  bastore 
L4857:  dup 
L4858:  ldc_w 728 
L4861:  bipush 99 
L4863:  bastore 
L4864:  dup 
L4865:  ldc_w 729 
L4868:  bipush 116 
L4870:  bastore 
L4871:  dup 
L4872:  ldc_w 730 
L4875:  bipush 59 
L4877:  bastore 
L4878:  dup 
L4879:  ldc_w 731 
L4882:  bipush 41 
L4884:  bastore 
L4885:  dup 
L4886:  ldc_w 732 
L4889:  bipush 76 
L4891:  bastore 
L4892:  dup 
L4893:  ldc_w 733 
L4896:  bipush 106 
L4898:  bastore 
L4899:  dup 
L4900:  ldc_w 734 
L4903:  bipush 97 
L4905:  bastore 
L4906:  dup 
L4907:  ldc_w 735 
L4910:  bipush 118 
L4912:  bastore 
L4913:  dup 
L4914:  ldc_w 736 
L4917:  bipush 97 
L4919:  bastore 
L4920:  dup 
L4921:  ldc_w 737 
L4924:  bipush 47 
L4926:  bastore 
L4927:  dup 
L4928:  ldc_w 738 
L4931:  bipush 108 
L4933:  bastore 
L4934:  dup 
L4935:  ldc_w 739 
L4938:  bipush 97 
L4940:  bastore 
L4941:  dup 
L4942:  ldc_w 740 
L4945:  bipush 110 
L4947:  bastore 
L4948:  dup 
L4949:  ldc_w 741 
L4952:  bipush 103 
L4954:  bastore 
L4955:  dup 
L4956:  ldc_w 742 
L4959:  bipush 47 
L4961:  bastore 
L4962:  dup 
L4963:  ldc_w 743 
L4966:  bipush 79 
L4968:  bastore 
L4969:  dup 
L4970:  ldc_w 744 
L4973:  bipush 98 
L4975:  bastore 
L4976:  dup 
L4977:  ldc_w 745 
L4980:  bipush 106 
L4982:  bastore 
L4983:  dup 
L4984:  ldc_w 746 
L4987:  bipush 101 
L4989:  bastore 
L4990:  dup 
L4991:  ldc_w 747 
L4994:  bipush 99 
L4996:  bastore 
L4997:  dup 
L4998:  ldc_w 748 
L5001:  bipush 116 
L5003:  bastore 
L5004:  dup 
L5005:  ldc_w 749 
L5008:  bipush 59 
L5010:  bastore 
L5011:  dup 
L5012:  ldc_w 750 
L5015:  bipush 12 
L5017:  bastore 
L5018:  dup 
L5019:  ldc_w 751 
L5022:  bipush 0 
L5024:  bastore 
L5025:  dup 
L5026:  ldc_w 752 
L5029:  bipush 95 
L5031:  bastore 
L5032:  dup 
L5033:  ldc_w 753 
L5036:  bipush 0 
L5038:  bastore 
L5039:  dup 
L5040:  ldc_w 754 
L5043:  bipush 96 
L5045:  bastore 
L5046:  dup 
L5047:  ldc_w 755 
L5050:  bipush 11 
L5052:  bastore 
L5053:  dup 
L5054:  ldc_w 756 
L5057:  bipush 0 
L5059:  bastore 
L5060:  dup 
L5061:  ldc_w 757 
L5064:  bipush 81 
L5066:  bastore 
L5067:  dup 
L5068:  ldc_w 758 
L5071:  bipush 0 
L5073:  bastore 
L5074:  dup 
L5075:  ldc_w 759 
L5078:  bipush 97 
L5080:  bastore 
L5081:  dup 
L5082:  ldc_w 760 
L5085:  bipush 1 
L5087:  bastore 
L5088:  dup 
L5089:  ldc_w 761 
L5092:  bipush 0 
L5094:  bastore 
L5095:  dup 
L5096:  ldc_w 762 
L5099:  bipush 2 
L5101:  bastore 
L5102:  dup 
L5103:  ldc_w 763 
L5106:  bipush 91 
L5108:  bastore 
L5109:  dup 
L5110:  ldc_w 764 
L5113:  bipush 66 
L5115:  bastore 
L5116:  dup 
L5117:  ldc_w 765 
L5120:  bipush 7 
L5122:  bastore 
L5123:  dup 
L5124:  ldc_w 766 
L5127:  bipush 0 
L5129:  bastore 
L5130:  dup 
L5131:  ldc_w 767 
L5134:  bipush 99 
L5136:  bastore 
L5137:  dup 
L5138:  ldc_w 768 
L5141:  bipush 1 
L5143:  bastore 
L5144:  dup 
L5145:  ldc_w 769 
L5148:  bipush 0 
L5150:  bastore 
L5151:  dup 
L5152:  ldc_w 770 
L5155:  bipush 8 
L5157:  bastore 
L5158:  dup 
L5159:  ldc_w 771 
L5162:  bipush 85 
L5164:  bastore 
L5165:  dup 
L5166:  ldc_w 772 
L5169:  bipush 84 
L5171:  bastore 
L5172:  dup 
L5173:  ldc_w 773 
L5176:  bipush 70 
L5178:  bastore 
L5179:  dup 
L5180:  ldc_w 774 
L5183:  bipush 45 
L5185:  bastore 
L5186:  dup 
L5187:  ldc_w 775 
L5190:  bipush 49 
L5192:  bastore 
L5193:  dup 
L5194:  ldc_w 776 
L5197:  bipush 54 
L5199:  bastore 
L5200:  dup 
L5201:  ldc_w 777 
L5204:  bipush 76 
L5206:  bastore 
L5207:  dup 
L5208:  ldc_w 778 
L5211:  bipush 69 
L5213:  bastore 
L5214:  dup 
L5215:  ldc_w 779 
L5218:  bipush 8 
L5220:  bastore 
L5221:  dup 
L5222:  ldc_w 780 
L5225:  bipush 0 
L5227:  bastore 
L5228:  dup 
L5229:  ldc_w 781 
L5232:  bipush 101 
L5234:  bastore 
L5235:  dup 
L5236:  ldc_w 782 
L5239:  bipush 1 
L5241:  bastore 
L5242:  dup 
L5243:  ldc_w 783 
L5246:  bipush 0 
L5248:  bastore 
L5249:  dup 
L5250:  ldc_w 784 
L5253:  bipush 23 
L5255:  bastore 
L5256:  dup 
L5257:  ldc_w 785 
L5260:  bipush 40 
L5262:  bastore 
L5263:  dup 
L5264:  ldc_w 786 
L5267:  bipush 91 
L5269:  bastore 
L5270:  dup 
L5271:  ldc_w 787 
L5274:  bipush 66 
L5276:  bastore 
L5277:  dup 
L5278:  ldc_w 788 
L5281:  bipush 76 
L5283:  bastore 
L5284:  dup 
L5285:  ldc_w 789 
L5288:  bipush 106 
L5290:  bastore 
L5291:  dup 
L5292:  ldc_w 790 
L5295:  bipush 97 
L5297:  bastore 
L5298:  dup 
L5299:  ldc_w 791 
L5302:  bipush 118 
L5304:  bastore 
L5305:  dup 
L5306:  ldc_w 792 
L5309:  bipush 97 
L5311:  bastore 
L5312:  dup 
L5313:  ldc_w 793 
L5316:  bipush 47 
L5318:  bastore 
L5319:  dup 
L5320:  ldc_w 794 
L5323:  bipush 108 
L5325:  bastore 
L5326:  dup 
L5327:  ldc_w 795 
L5330:  bipush 97 
L5332:  bastore 
L5333:  dup 
L5334:  ldc_w 796 
L5337:  bipush 110 
L5339:  bastore 
L5340:  dup 
L5341:  ldc_w 797 
L5344:  bipush 103 
L5346:  bastore 
L5347:  dup 
L5348:  ldc_w 798 
L5351:  bipush 47 
L5353:  bastore 
L5354:  dup 
L5355:  ldc_w 799 
L5358:  bipush 83 
L5360:  bastore 
L5361:  dup 
L5362:  ldc_w 800 
L5365:  bipush 116 
L5367:  bastore 
L5368:  dup 
L5369:  ldc_w 801 
L5372:  bipush 114 
L5374:  bastore 
L5375:  dup 
L5376:  ldc_w 802 
L5379:  bipush 105 
L5381:  bastore 
L5382:  dup 
L5383:  ldc_w 803 
L5386:  bipush 110 
L5388:  bastore 
L5389:  dup 
L5390:  ldc_w 804 
L5393:  bipush 103 
L5395:  bastore 
L5396:  dup 
L5397:  ldc_w 805 
L5400:  bipush 59 
L5402:  bastore 
L5403:  dup 
L5404:  ldc_w 806 
L5407:  bipush 41 
L5409:  bastore 
L5410:  dup 
L5411:  ldc_w 807 
L5414:  bipush 86 
L5416:  bastore 
L5417:  dup 
L5418:  ldc_w 808 
L5421:  bipush 12 
L5423:  bastore 
L5424:  dup 
L5425:  ldc_w 809 
L5428:  bipush 0 
L5430:  bastore 
L5431:  dup 
L5432:  ldc_w 810 
L5435:  bipush 7 
L5437:  bastore 
L5438:  dup 
L5439:  ldc_w 811 
L5442:  bipush 0 
L5444:  bastore 
L5445:  dup 
L5446:  ldc_w 812 
L5449:  bipush 103 
L5451:  bastore 
L5452:  dup 
L5453:  ldc_w 813 
L5456:  bipush 10 
L5458:  bastore 
L5459:  dup 
L5460:  ldc_w 814 
L5463:  bipush 0 
L5465:  bastore 
L5466:  dup 
L5467:  ldc_w 815 
L5470:  bipush 94 
L5472:  bastore 
L5473:  dup 
L5474:  ldc_w 816 
L5477:  bipush 0 
L5479:  bastore 
L5480:  dup 
L5481:  ldc_w 817 
L5484:  bipush 104 
L5486:  bastore 
L5487:  dup 
L5488:  ldc_w 818 
L5491:  bipush 1 
L5493:  bastore 
L5494:  dup 
L5495:  ldc_w 819 
L5498:  bipush 0 
L5500:  bastore 
L5501:  dup 
L5502:  ldc_w 820 
L5505:  bipush 5 
L5507:  bastore 
L5508:  dup 
L5509:  ldc_w 821 
L5512:  bipush 40 
L5514:  bastore 
L5515:  dup 
L5516:  ldc_w 822 
L5519:  bipush 73 
L5521:  bastore 
L5522:  dup 
L5523:  ldc_w 823 
L5526:  bipush 41 
L5528:  bastore 
L5529:  dup 
L5530:  ldc_w 824 
L5533:  bipush 91 
L5535:  bastore 
L5536:  dup 
L5537:  ldc_w 825 
L5540:  bipush 66 
L5542:  bastore 
L5543:  dup 
L5544:  ldc_w 826 
L5547:  bipush 1 
L5549:  bastore 
L5550:  dup 
L5551:  ldc_w 827 
L5554:  bipush 0 
L5556:  bastore 
L5557:  dup 
L5558:  ldc_w 828 
L5561:  bipush 4 
L5563:  bastore 
L5564:  dup 
L5565:  ldc_w 829 
L5568:  bipush 67 
L5570:  bastore 
L5571:  dup 
L5572:  ldc_w 830 
L5575:  bipush 111 
L5577:  bastore 
L5578:  dup 
L5579:  ldc_w 831 
L5582:  bipush 100 
L5584:  bastore 
L5585:  dup 
L5586:  ldc_w 832 
L5589:  bipush 101 
L5591:  bastore 
L5592:  dup 
L5593:  ldc_w 833 
L5596:  bipush 16 
L5598:  bastore 
L5599:  dup 
L5600:  ldc_w 834 
L5603:  bipush 17 
L5605:  bastore 
L5606:  dup 
L5607:  ldc_w 835 
L5610:  bipush 0 
L5612:  bastore 
L5613:  dup 
L5614:  ldc_w 836 
L5617:  bipush 2 
L5619:  bastore 
L5620:  dup 
L5621:  ldc_w 837 
L5624:  bipush 0 
L5626:  bastore 
L5627:  dup 
L5628:  ldc_w 838 
L5631:  bipush 4 
L5633:  bastore 
L5634:  dup 
L5635:  ldc_w 839 
L5638:  bipush 0 
L5640:  bastore 
L5641:  dup 
L5642:  ldc_w 840 
L5645:  bipush 0 
L5647:  bastore 
L5648:  dup 
L5649:  ldc_w 841 
L5652:  bipush 0 
L5654:  bastore 
L5655:  dup 
L5656:  ldc_w 842 
L5659:  bipush 1 
L5661:  bastore 
L5662:  dup 
L5663:  ldc_w 843 
L5666:  bipush 16 
L5668:  bastore 
L5669:  dup 
L5670:  ldc_w 844 
L5673:  bipush 18 
L5675:  bastore 
L5676:  dup 
L5677:  ldc_w 845 
L5680:  bipush 0 
L5682:  bastore 
L5683:  dup 
L5684:  ldc_w 846 
L5687:  bipush 5 
L5689:  bastore 
L5690:  dup 
L5691:  ldc_w 847 
L5694:  bipush 0 
L5696:  bastore 
L5697:  dup 
L5698:  ldc_w 848 
L5701:  bipush 6 
L5703:  bastore 
L5704:  dup 
L5705:  ldc_w 849 
L5708:  bipush 0 
L5710:  bastore 
L5711:  dup 
L5712:  ldc_w 850 
L5715:  bipush 0 
L5717:  bastore 
L5718:  dup 
L5719:  ldc_w 851 
L5722:  bipush 0 
L5724:  bastore 
L5725:  dup 
L5726:  ldc_w 852 
L5729:  bipush 3 
L5731:  bastore 
L5732:  dup 
L5733:  ldc_w 853 
L5736:  bipush 16 
L5738:  bastore 
L5739:  dup 
L5740:  ldc_w 854 
L5743:  bipush 1 
L5745:  bastore 
L5746:  dup 
L5747:  ldc_w 855 
L5750:  bipush 0 
L5752:  bastore 
L5753:  dup 
L5754:  ldc_w 856 
L5757:  bipush 7 
L5759:  bastore 
L5760:  dup 
L5761:  ldc_w 857 
L5764:  bipush 0 
L5766:  bastore 
L5767:  dup 
L5768:  ldc_w 858 
L5771:  bipush 8 
L5773:  bastore 
L5774:  dup 
L5775:  ldc_w 859 
L5778:  bipush 0 
L5780:  bastore 
L5781:  dup 
L5782:  ldc_w 860 
L5785:  bipush 1 
L5787:  bastore 
L5788:  dup 
L5789:  ldc_w 861 
L5792:  bipush 0 
L5794:  bastore 
L5795:  dup 
L5796:  ldc_w 862 
L5799:  bipush 107 
L5801:  bastore 
L5802:  dup 
L5803:  ldc_w 863 
L5806:  bipush 0 
L5808:  bastore 
L5809:  dup 
L5810:  ldc_w 864 
L5813:  bipush 0 
L5815:  bastore 
L5816:  dup 
L5817:  ldc_w 865 
L5820:  bipush 3 
L5822:  bastore 
L5823:  dup 
L5824:  ldc_w 866 
L5827:  bipush -51 
L5829:  bastore 
L5830:  dup 
L5831:  ldc_w 867 
L5834:  bipush 0 
L5836:  bastore 
L5837:  dup 
L5838:  ldc_w 868 
L5841:  bipush 8 
L5843:  bastore 
L5844:  dup 
L5845:  ldc_w 869 
L5848:  bipush 0 
L5850:  bastore 
L5851:  dup 
L5852:  ldc_w 870 
L5855:  bipush 1 
L5857:  bastore 
L5858:  dup 
L5859:  ldc_w 871 
L5862:  bipush 0 
L5864:  bastore 
L5865:  dup 
L5866:  ldc_w 872 
L5869:  bipush 0 
L5871:  bastore 
L5872:  dup 
L5873:  ldc_w 873 
L5876:  bipush 3 
L5878:  bastore 
L5879:  dup 
L5880:  ldc_w 874 
L5883:  bipush -63 
L5885:  bastore 
L5886:  dup 
L5887:  ldc_w 875 
L5890:  bipush 42 
L5892:  bastore 
L5893:  dup 
L5894:  ldc_w 876 
L5897:  bipush -73 
L5899:  bastore 
L5900:  dup 
L5901:  ldc_w 877 
L5904:  bipush 0 
L5906:  bastore 
L5907:  dup 
L5908:  ldc_w 878 
L5911:  bipush 10 
L5913:  bastore 
L5914:  dup 
L5915:  ldc_w 879 
L5918:  bipush 7 
L5920:  bastore 
L5921:  dup 
L5922:  ldc_w 880 
L5925:  bipush -67 
L5927:  bastore 
L5928:  dup 
L5929:  ldc_w 881 
L5932:  bipush 0 
L5934:  bastore 
L5935:  dup 
L5936:  ldc_w 882 
L5939:  bipush 12 
L5941:  bastore 
L5942:  dup 
L5943:  ldc_w 883 
L5946:  bipush 89 
L5948:  bastore 
L5949:  dup 
L5950:  ldc_w 884 
L5953:  bipush 3 
L5955:  bastore 
L5956:  dup 
L5957:  ldc_w 885 
L5960:  bipush 89 
L5962:  bastore 
L5963:  dup 
L5964:  ldc_w 886 
L5967:  bipush -72 
L5969:  bastore 
L5970:  dup 
L5971:  ldc_w 887 
L5974:  bipush 0 
L5976:  bastore 
L5977:  dup 
L5978:  ldc_w 888 
L5981:  bipush 18 
L5983:  bastore 
L5984:  dup 
L5985:  ldc_w 889 
L5988:  bipush 18 
L5990:  bastore 
L5991:  dup 
L5992:  ldc_w 890 
L5995:  bipush 19 
L5997:  bastore 
L5998:  dup 
L5999:  ldc_w 891 
L6002:  bipush -68 
L6004:  bastore 
L6005:  dup 
L6006:  ldc_w 892 
L6009:  bipush 8 
L6011:  bastore 
L6012:  dup 
L6013:  ldc_w 893 
L6016:  bipush 89 
L6018:  bastore 
L6019:  dup 
L6020:  ldc_w 894 
L6023:  bipush 3 
L6025:  bastore 
L6026:  dup 
L6027:  ldc_w 895 
L6030:  bipush 16 
L6032:  bastore 
L6033:  dup 
L6034:  ldc_w 896 
L6037:  bipush 83 
L6039:  bastore 
L6040:  dup 
L6041:  ldc_w 897 
L6044:  bipush 84 
L6046:  bastore 
L6047:  dup 
L6048:  ldc_w 898 
L6051:  bipush 89 
L6053:  bastore 
L6054:  dup 
L6055:  ldc_w 899 
L6058:  bipush 4 
L6060:  bastore 
L6061:  dup 
L6062:  ldc_w 900 
L6065:  bipush 16 
L6067:  bastore 
L6068:  dup 
L6069:  ldc_w 901 
L6072:  bipush 0 
L6074:  bastore 
L6075:  dup 
L6076:  ldc_w 902 
L6079:  bipush 84 
L6081:  bastore 
L6082:  dup 
L6083:  ldc_w 903 
L6086:  bipush 89 
L6088:  bastore 
L6089:  dup 
L6090:  ldc_w 904 
L6093:  bipush 5 
L6095:  bastore 
L6096:  dup 
L6097:  ldc_w 905 
L6100:  bipush 16 
L6102:  bastore 
L6103:  dup 
L6104:  ldc_w 906 
L6107:  bipush 97 
L6109:  bastore 
L6110:  dup 
L6111:  ldc_w 907 
L6114:  bipush 84 
L6116:  bastore 
L6117:  dup 
L6118:  ldc_w 908 
L6121:  bipush 89 
L6123:  bastore 
L6124:  dup 
L6125:  ldc_w 909 
L6128:  bipush 6 
L6130:  bastore 
L6131:  dup 
L6132:  ldc_w 910 
L6135:  bipush 16 
L6137:  bastore 
L6138:  dup 
L6139:  ldc_w 911 
L6142:  bipush 0 
L6144:  bastore 
L6145:  dup 
L6146:  ldc_w 912 
L6149:  bipush 84 
L6151:  bastore 
L6152:  dup 
L6153:  ldc_w 913 
L6156:  bipush 89 
L6158:  bastore 
L6159:  dup 
L6160:  ldc_w 914 
L6163:  bipush 7 
L6165:  bastore 
L6166:  dup 
L6167:  ldc_w 915 
L6170:  bipush 16 
L6172:  bastore 
L6173:  dup 
L6174:  ldc_w 916 
L6177:  bipush 121 
L6179:  bastore 
L6180:  dup 
L6181:  ldc_w 917 
L6184:  bipush 84 
L6186:  bastore 
L6187:  dup 
L6188:  ldc_w 918 
L6191:  bipush 89 
L6193:  bastore 
L6194:  dup 
L6195:  ldc_w 919 
L6198:  bipush 8 
L6200:  bastore 
L6201:  dup 
L6202:  ldc_w 920 
L6205:  bipush 16 
L6207:  bastore 
L6208:  dup 
L6209:  ldc_w 921 
L6212:  bipush 0 
L6214:  bastore 
L6215:  dup 
L6216:  ldc_w 922 
L6219:  bipush 84 
L6221:  bastore 
L6222:  dup 
L6223:  ldc_w 923 
L6226:  bipush 89 
L6228:  bastore 
L6229:  dup 
L6230:  ldc_w 924 
L6233:  bipush 18 
L6235:  bastore 
L6236:  dup 
L6237:  ldc_w 925 
L6240:  bipush 20 
L6242:  bastore 
L6243:  dup 
L6244:  ldc_w 926 
L6247:  bipush 16 
L6249:  bastore 
L6250:  dup 
L6251:  ldc_w 927 
L6254:  bipush 32 
L6256:  bastore 
L6257:  dup 
L6258:  ldc_w 928 
L6261:  bipush 84 
L6263:  bastore 
L6264:  dup 
L6265:  ldc_w 929 
L6268:  bipush 89 
L6270:  bastore 
L6271:  dup 
L6272:  ldc_w 930 
L6275:  bipush 18 
L6277:  bastore 
L6278:  dup 
L6279:  ldc_w 931 
L6282:  bipush 21 
L6284:  bastore 
L6285:  dup 
L6286:  ldc_w 932 
L6289:  bipush 16 
L6291:  bastore 
L6292:  dup 
L6293:  ldc_w 933 
L6296:  bipush 0 
L6298:  bastore 
L6299:  dup 
L6300:  ldc_w 934 
L6303:  bipush 84 
L6305:  bastore 
L6306:  dup 
L6307:  ldc_w 935 
L6310:  bipush 89 
L6312:  bastore 
L6313:  dup 
L6314:  ldc_w 936 
L6317:  bipush 18 
L6319:  bastore 
L6320:  dup 
L6321:  ldc_w 937 
L6324:  bipush 22 
L6326:  bastore 
L6327:  dup 
L6328:  ldc_w 938 
L6331:  bipush 16 
L6333:  bastore 
L6334:  dup 
L6335:  ldc_w 939 
L6338:  bipush 116 
L6340:  bastore 
L6341:  dup 
L6342:  ldc_w 940 
L6345:  bipush 84 
L6347:  bastore 
L6348:  dup 
L6349:  ldc_w 941 
L6352:  bipush 89 
L6354:  bastore 
L6355:  dup 
L6356:  ldc_w 942 
L6359:  bipush 18 
L6361:  bastore 
L6362:  dup 
L6363:  ldc_w 943 
L6366:  bipush 23 
L6368:  bastore 
L6369:  dup 
L6370:  ldc_w 944 
L6373:  bipush 16 
L6375:  bastore 
L6376:  dup 
L6377:  ldc_w 945 
L6380:  bipush 0 
L6382:  bastore 
L6383:  dup 
L6384:  ldc_w 946 
L6387:  bipush 84 
L6389:  bastore 
L6390:  dup 
L6391:  ldc_w 947 
L6394:  bipush 89 
L6396:  bastore 
L6397:  dup 
L6398:  ldc_w 948 
L6401:  bipush 18 
L6403:  bastore 
L6404:  dup 
L6405:  ldc_w 949 
L6408:  bipush 24 
L6410:  bastore 
L6411:  dup 
L6412:  ldc_w 950 
L6415:  bipush 16 
L6417:  bastore 
L6418:  dup 
L6419:  ldc_w 951 
L6422:  bipush 104 
L6424:  bastore 
L6425:  dup 
L6426:  ldc_w 952 
L6429:  bipush 84 
L6431:  bastore 
L6432:  dup 
L6433:  ldc_w 953 
L6436:  bipush 89 
L6438:  bastore 
L6439:  dup 
L6440:  ldc_w 954 
L6443:  bipush 18 
L6445:  bastore 
L6446:  dup 
L6447:  ldc_w 955 
L6450:  bipush 25 
L6452:  bastore 
L6453:  dup 
L6454:  ldc_w 956 
L6457:  bipush 16 
L6459:  bastore 
L6460:  dup 
L6461:  ldc_w 957 
L6464:  bipush 0 
L6466:  bastore 
L6467:  dup 
L6468:  ldc_w 958 
L6471:  bipush 84 
L6473:  bastore 
L6474:  dup 
L6475:  ldc_w 959 
L6478:  bipush 89 
L6480:  bastore 
L6481:  dup 
L6482:  ldc_w 960 
L6485:  bipush 18 
L6487:  bastore 
L6488:  dup 
L6489:  ldc_w 961 
L6492:  bipush 26 
L6494:  bastore 
L6495:  dup 
L6496:  ldc_w 962 
L6499:  bipush 16 
L6501:  bastore 
L6502:  dup 
L6503:  ldc_w 963 
L6506:  bipush 101 
L6508:  bastore 
L6509:  dup 
L6510:  ldc_w 964 
L6513:  bipush 84 
L6515:  bastore 
L6516:  dup 
L6517:  ldc_w 965 
L6520:  bipush 89 
L6522:  bastore 
L6523:  dup 
L6524:  ldc_w 966 
L6527:  bipush 18 
L6529:  bastore 
L6530:  dup 
L6531:  ldc_w 967 
L6534:  bipush 27 
L6536:  bastore 
L6537:  dup 
L6538:  ldc_w 968 
L6541:  bipush 16 
L6543:  bastore 
L6544:  dup 
L6545:  ldc_w 969 
L6548:  bipush 0 
L6550:  bastore 
L6551:  dup 
L6552:  ldc_w 970 
L6555:  bipush 84 
L6557:  bastore 
L6558:  dup 
L6559:  ldc_w 971 
L6562:  bipush 89 
L6564:  bastore 
L6565:  dup 
L6566:  ldc_w 972 
L6569:  bipush 18 
L6571:  bastore 
L6572:  dup 
L6573:  ldc_w 973 
L6576:  bipush 28 
L6578:  bastore 
L6579:  dup 
L6580:  ldc_w 974 
L6583:  bipush 16 
L6585:  bastore 
L6586:  dup 
L6587:  ldc_w 975 
L6590:  bipush 32 
L6592:  bastore 
L6593:  dup 
L6594:  ldc_w 976 
L6597:  bipush 84 
L6599:  bastore 
L6600:  dup 
L6601:  ldc_w 977 
L6604:  bipush 89 
L6606:  bastore 
L6607:  dup 
L6608:  ldc_w 978 
L6611:  bipush 18 
L6613:  bastore 
L6614:  dup 
L6615:  ldc_w 979 
L6618:  bipush 29 
L6620:  bastore 
L6621:  dup 
L6622:  ldc_w 980 
L6625:  bipush 16 
L6627:  bastore 
L6628:  dup 
L6629:  ldc_w 981 
L6632:  bipush 0 
L6634:  bastore 
L6635:  dup 
L6636:  ldc_w 982 
L6639:  bipush 84 
L6641:  bastore 
L6642:  dup 
L6643:  ldc_w 983 
L6646:  bipush 89 
L6648:  bastore 
L6649:  dup 
L6650:  ldc_w 984 
L6653:  bipush 18 
L6655:  bastore 
L6656:  dup 
L6657:  ldc_w 985 
L6660:  bipush 30 
L6662:  bastore 
L6663:  dup 
L6664:  ldc_w 986 
L6667:  bipush 16 
L6669:  bastore 
L6670:  dup 
L6671:  ldc_w 987 
L6674:  bipush 119 
L6676:  bastore 
L6677:  dup 
L6678:  ldc_w 988 
L6681:  bipush 84 
L6683:  bastore 
L6684:  dup 
L6685:  ldc_w 989 
L6688:  bipush 89 
L6690:  bastore 
L6691:  dup 
L6692:  ldc_w 990 
L6695:  bipush 18 
L6697:  bastore 
L6698:  dup 
L6699:  ldc_w 991 
L6702:  bipush 31 
L6704:  bastore 
L6705:  dup 
L6706:  ldc_w 992 
L6709:  bipush 16 
L6711:  bastore 
L6712:  dup 
L6713:  ldc_w 993 
L6716:  bipush 0 
L6718:  bastore 
L6719:  dup 
L6720:  ldc_w 994 
L6723:  bipush 84 
L6725:  bastore 
L6726:  dup 
L6727:  ldc_w 995 
L6730:  bipush 89 
L6732:  bastore 
L6733:  dup 
L6734:  ldc_w 996 
L6737:  bipush 18 
L6739:  bastore 
L6740:  dup 
L6741:  ldc_w 997 
L6744:  bipush 32 
L6746:  bastore 
L6747:  dup 
L6748:  ldc_w 998 
L6751:  bipush 16 
L6753:  bastore 
L6754:  dup 
L6755:  ldc_w 999 
L6758:  bipush 111 
L6760:  bastore 
L6761:  dup 
L6762:  ldc_w 1000 
L6765:  bipush 84 
L6767:  bastore 
L6768:  dup 
L6769:  ldc_w 1001 
L6772:  bipush 89 
L6774:  bastore 
L6775:  dup 
L6776:  ldc_w 1002 
L6779:  bipush 18 
L6781:  bastore 
L6782:  dup 
L6783:  ldc_w 1003 
L6786:  bipush 33 
L6788:  bastore 
L6789:  dup 
L6790:  ldc_w 1004 
L6793:  bipush 16 
L6795:  bastore 
L6796:  dup 
L6797:  ldc_w 1005 
L6800:  bipush 0 
L6802:  bastore 
L6803:  dup 
L6804:  ldc_w 1006 
L6807:  bipush 84 
L6809:  bastore 
L6810:  dup 
L6811:  ldc_w 1007 
L6814:  bipush 89 
L6816:  bastore 
L6817:  dup 
L6818:  ldc_w 1008 
L6821:  bipush 18 
L6823:  bastore 
L6824:  dup 
L6825:  ldc_w 1009 
L6828:  bipush 34 
L6830:  bastore 
L6831:  dup 
L6832:  ldc_w 1010 
L6835:  bipush 16 
L6837:  bastore 
L6838:  dup 
L6839:  ldc_w 1011 
L6842:  bipush 114 
L6844:  bastore 
L6845:  dup 
L6846:  ldc_w 1012 
L6849:  bipush 84 
L6851:  bastore 
L6852:  dup 
L6853:  ldc_w 1013 
L6856:  bipush 89 
L6858:  bastore 
L6859:  dup 
L6860:  ldc_w 1014 
L6863:  bipush 18 
L6865:  bastore 
L6866:  dup 
L6867:  ldc_w 1015 
L6870:  bipush 35 
L6872:  bastore 
L6873:  dup 
L6874:  ldc_w 1016 
L6877:  bipush 16 
L6879:  bastore 
L6880:  dup 
L6881:  ldc_w 1017 
L6884:  bipush 0 
L6886:  bastore 
L6887:  dup 
L6888:  ldc_w 1018 
L6891:  bipush 84 
L6893:  bastore 
L6894:  dup 
L6895:  ldc_w 1019 
L6898:  bipush 89 
L6900:  bastore 
L6901:  dup 
L6902:  ldc_w 1020 
L6905:  bipush 18 
L6907:  bastore 
L6908:  dup 
L6909:  ldc_w 1021 
L6912:  bipush 36 
L6914:  bastore 
L6915:  dup 
L6916:  ldc_w 1022 
L6919:  bipush 16 
L6921:  bastore 
L6922:  dup 
L6923:  ldc_w 1023 
L6926:  bipush 100 
L6928:  bastore 
L6929:  dup 
L6930:  ldc_w 1024 
L6933:  bipush 84 
L6935:  bastore 
L6936:  dup 
L6937:  ldc_w 1025 
L6940:  bipush 89 
L6942:  bastore 
L6943:  dup 
L6944:  ldc_w 1026 
L6947:  bipush 18 
L6949:  bastore 
L6950:  dup 
L6951:  ldc_w 1027 
L6954:  bipush 37 
L6956:  bastore 
L6957:  dup 
L6958:  ldc_w 1028 
L6961:  bipush 16 
L6963:  bastore 
L6964:  dup 
L6965:  ldc_w 1029 
L6968:  bipush 0 
L6970:  bastore 
L6971:  dup 
L6972:  ldc_w 1030 
L6975:  bipush 84 
L6977:  bastore 
L6978:  dup 
L6979:  ldc_w 1031 
L6982:  bipush 89 
L6984:  bastore 
L6985:  dup 
L6986:  ldc_w 1032 
L6989:  bipush 18 
L6991:  bastore 
L6992:  dup 
L6993:  ldc_w 1033 
L6996:  bipush 38 
L6998:  bastore 
L6999:  dup 
L7000:  ldc_w 1034 
L7003:  bipush 16 
L7005:  bastore 
L7006:  dup 
L7007:  ldc_w 1035 
L7010:  bipush 115 
L7012:  bastore 
L7013:  dup 
L7014:  ldc_w 1036 
L7017:  bipush 84 
L7019:  bastore 
L7020:  dup 
L7021:  ldc_w 1037 
L7024:  bipush 89 
L7026:  bastore 
L7027:  dup 
L7028:  ldc_w 1038 
L7031:  bipush 18 
L7033:  bastore 
L7034:  dup 
L7035:  ldc_w 1039 
L7038:  bipush 39 
L7040:  bastore 
L7041:  dup 
L7042:  ldc_w 1040 
L7045:  bipush 16 
L7047:  bastore 
L7048:  dup 
L7049:  ldc_w 1041 
L7052:  bipush 0 
L7054:  bastore 
L7055:  dup 
L7056:  ldc_w 1042 
L7059:  bipush 84 
L7061:  bastore 
L7062:  dup 
L7063:  ldc_w 1043 
L7066:  bipush 89 
L7068:  bastore 
L7069:  dup 
L7070:  ldc_w 1044 
L7073:  bipush 18 
L7075:  bastore 
L7076:  dup 
L7077:  ldc_w 1045 
L7080:  bipush 40 
L7082:  bastore 
L7083:  dup 
L7084:  ldc_w 1046 
L7087:  bipush 16 
L7089:  bastore 
L7090:  dup 
L7091:  ldc_w 1047 
L7094:  bipush 32 
L7096:  bastore 
L7097:  dup 
L7098:  ldc_w 1048 
L7101:  bipush 84 
L7103:  bastore 
L7104:  dup 
L7105:  ldc_w 1049 
L7108:  bipush 89 
L7110:  bastore 
L7111:  dup 
L7112:  ldc_w 1050 
L7115:  bipush 18 
L7117:  bastore 
L7118:  dup 
L7119:  ldc_w 1051 
L7122:  bipush 41 
L7124:  bastore 
L7125:  dup 
L7126:  ldc_w 1052 
L7129:  bipush 16 
L7131:  bastore 
L7132:  dup 
L7133:  ldc_w 1053 
L7136:  bipush 0 
L7138:  bastore 
L7139:  dup 
L7140:  ldc_w 1054 
L7143:  bipush 84 
L7145:  bastore 
L7146:  dup 
L7147:  ldc_w 1055 
L7150:  bipush 89 
L7152:  bastore 
L7153:  dup 
L7154:  ldc_w 1056 
L7157:  bipush 18 
L7159:  bastore 
L7160:  dup 
L7161:  ldc_w 1057 
L7164:  bipush 42 
L7166:  bastore 
L7167:  dup 
L7168:  ldc_w 1058 
L7171:  bipush 16 
L7173:  bastore 
L7174:  dup 
L7175:  ldc_w 1059 
L7178:  bipush 116 
L7180:  bastore 
L7181:  dup 
L7182:  ldc_w 1060 
L7185:  bipush 84 
L7187:  bastore 
L7188:  dup 
L7189:  ldc_w 1061 
L7192:  bipush 89 
L7194:  bastore 
L7195:  dup 
L7196:  ldc_w 1062 
L7199:  bipush 18 
L7201:  bastore 
L7202:  dup 
L7203:  ldc_w 1063 
L7206:  bipush 43 
L7208:  bastore 
L7209:  dup 
L7210:  ldc_w 1064 
L7213:  bipush 16 
L7215:  bastore 
L7216:  dup 
L7217:  ldc_w 1065 
L7220:  bipush 0 
L7222:  bastore 
L7223:  dup 
L7224:  ldc_w 1066 
L7227:  bipush 84 
L7229:  bastore 
L7230:  dup 
L7231:  ldc_w 1067 
L7234:  bipush 89 
L7236:  bastore 
L7237:  dup 
L7238:  ldc_w 1068 
L7241:  bipush 18 
L7243:  bastore 
L7244:  dup 
L7245:  ldc_w 1069 
L7248:  bipush 44 
L7250:  bastore 
L7251:  dup 
L7252:  ldc_w 1070 
L7255:  bipush 16 
L7257:  bastore 
L7258:  dup 
L7259:  ldc_w 1071 
L7262:  bipush 111 
L7264:  bastore 
L7265:  dup 
L7266:  ldc_w 1072 
L7269:  bipush 84 
L7271:  bastore 
L7272:  dup 
L7273:  ldc_w 1073 
L7276:  bipush 89 
L7278:  bastore 
L7279:  dup 
L7280:  ldc_w 1074 
L7283:  bipush 18 
L7285:  bastore 
L7286:  dup 
L7287:  ldc_w 1075 
L7290:  bipush 45 
L7292:  bastore 
L7293:  dup 
L7294:  ldc_w 1076 
L7297:  bipush 16 
L7299:  bastore 
L7300:  dup 
L7301:  ldc_w 1077 
L7304:  bipush 0 
L7306:  bastore 
L7307:  dup 
L7308:  ldc_w 1078 
L7311:  bipush 84 
L7313:  bastore 
L7314:  dup 
L7315:  ldc_w 1079 
L7318:  bipush 89 
L7320:  bastore 
L7321:  dup 
L7322:  ldc_w 1080 
L7325:  bipush 18 
L7327:  bastore 
L7328:  dup 
L7329:  ldc_w 1081 
L7332:  bipush 46 
L7334:  bastore 
L7335:  dup 
L7336:  ldc_w 1082 
L7339:  bipush 16 
L7341:  bastore 
L7342:  dup 
L7343:  ldc_w 1083 
L7346:  bipush 32 
L7348:  bastore 
L7349:  dup 
L7350:  ldc_w 1084 
L7353:  bipush 84 
L7355:  bastore 
L7356:  dup 
L7357:  ldc_w 1085 
L7360:  bipush 89 
L7362:  bastore 
L7363:  dup 
L7364:  ldc_w 1086 
L7367:  bipush 18 
L7369:  bastore 
L7370:  dup 
L7371:  ldc_w 1087 
L7374:  bipush 47 
L7376:  bastore 
L7377:  dup 
L7378:  ldc_w 1088 
L7381:  bipush 16 
L7383:  bastore 
L7384:  dup 
L7385:  ldc_w 1089 
L7388:  bipush 0 
L7390:  bastore 
L7391:  dup 
L7392:  ldc_w 1090 
L7395:  bipush 84 
L7397:  bastore 
L7398:  dup 
L7399:  ldc_w 1091 
L7402:  bipush 89 
L7404:  bastore 
L7405:  dup 
L7406:  ldc_w 1092 
L7409:  bipush 18 
L7411:  bastore 
L7412:  dup 
L7413:  ldc_w 1093 
L7416:  bipush 48 
L7418:  bastore 
L7419:  dup 
L7420:  ldc_w 1094 
L7423:  bipush 16 
L7425:  bastore 
L7426:  dup 
L7427:  ldc_w 1095 
L7430:  bipush 111 
L7432:  bastore 
L7433:  dup 
L7434:  ldc_w 1096 
L7437:  bipush 84 
L7439:  bastore 
L7440:  dup 
L7441:  ldc_w 1097 
L7444:  bipush 89 
L7446:  bastore 
L7447:  dup 
L7448:  ldc_w 1098 
L7451:  bipush 18 
L7453:  bastore 
L7454:  dup 
L7455:  ldc_w 1099 
L7458:  bipush 49 
L7460:  bastore 
L7461:  dup 
L7462:  ldc_w 1100 
L7465:  bipush 16 
L7467:  bastore 
L7468:  dup 
L7469:  ldc_w 1101 
L7472:  bipush 0 
L7474:  bastore 
L7475:  dup 
L7476:  ldc_w 1102 
L7479:  bipush 84 
L7481:  bastore 
L7482:  dup 
L7483:  ldc_w 1103 
L7486:  bipush 89 
L7488:  bastore 
L7489:  dup 
L7490:  ldc_w 1104 
L7493:  bipush 18 
L7495:  bastore 
L7496:  dup 
L7497:  ldc_w 1105 
L7500:  bipush 50 
L7502:  bastore 
L7503:  dup 
L7504:  ldc_w 1106 
L7507:  bipush 16 
L7509:  bastore 
L7510:  dup 
L7511:  ldc_w 1107 
L7514:  bipush 112 
L7516:  bastore 
L7517:  dup 
L7518:  ldc_w 1108 
L7521:  bipush 84 
L7523:  bastore 
L7524:  dup 
L7525:  ldc_w 1109 
L7528:  bipush 89 
L7530:  bastore 
L7531:  dup 
L7532:  ldc_w 1110 
L7535:  bipush 18 
L7537:  bastore 
L7538:  dup 
L7539:  ldc_w 1111 
L7542:  bipush 51 
L7544:  bastore 
L7545:  dup 
L7546:  ldc_w 1112 
L7549:  bipush 16 
L7551:  bastore 
L7552:  dup 
L7553:  ldc_w 1113 
L7556:  bipush 0 
L7558:  bastore 
L7559:  dup 
L7560:  ldc_w 1114 
L7563:  bipush 84 
L7565:  bastore 
L7566:  dup 
L7567:  ldc_w 1115 
L7570:  bipush 89 
L7572:  bastore 
L7573:  dup 
L7574:  ldc_w 1116 
L7577:  bipush 18 
L7579:  bastore 
L7580:  dup 
L7581:  ldc_w 1117 
L7584:  bipush 52 
L7586:  bastore 
L7587:  dup 
L7588:  ldc_w 1118 
L7591:  bipush 16 
L7593:  bastore 
L7594:  dup 
L7595:  ldc_w 1119 
L7598:  bipush 101 
L7600:  bastore 
L7601:  dup 
L7602:  ldc_w 1120 
L7605:  bipush 84 
L7607:  bastore 
L7608:  dup 
L7609:  ldc_w 1121 
L7612:  bipush 89 
L7614:  bastore 
L7615:  dup 
L7616:  ldc_w 1122 
L7619:  bipush 18 
L7621:  bastore 
L7622:  dup 
L7623:  ldc_w 1123 
L7626:  bipush 53 
L7628:  bastore 
L7629:  dup 
L7630:  ldc_w 1124 
L7633:  bipush 16 
L7635:  bastore 
L7636:  dup 
L7637:  ldc_w 1125 
L7640:  bipush 0 
L7642:  bastore 
L7643:  dup 
L7644:  ldc_w 1126 
L7647:  bipush 84 
L7649:  bastore 
L7650:  dup 
L7651:  ldc_w 1127 
L7654:  bipush 89 
L7656:  bastore 
L7657:  dup 
L7658:  ldc_w 1128 
L7661:  bipush 18 
L7663:  bastore 
L7664:  dup 
L7665:  ldc_w 1129 
L7668:  bipush 54 
L7670:  bastore 
L7671:  dup 
L7672:  ldc_w 1130 
L7675:  bipush 16 
L7677:  bastore 
L7678:  dup 
L7679:  ldc_w 1131 
L7682:  bipush 110 
L7684:  bastore 
L7685:  dup 
L7686:  ldc_w 1132 
L7689:  bipush 84 
L7691:  bastore 
L7692:  dup 
L7693:  ldc_w 1133 
L7696:  bipush 89 
L7698:  bastore 
L7699:  dup 
L7700:  ldc_w 1134 
L7703:  bipush 18 
L7705:  bastore 
L7706:  dup 
L7707:  ldc_w 1135 
L7710:  bipush 55 
L7712:  bastore 
L7713:  dup 
L7714:  ldc_w 1136 
L7717:  bipush 16 
L7719:  bastore 
L7720:  dup 
L7721:  ldc_w 1137 
L7724:  bipush 0 
L7726:  bastore 
L7727:  dup 
L7728:  ldc_w 1138 
L7731:  bipush 84 
L7733:  bastore 
L7734:  dup 
L7735:  ldc_w 1139 
L7738:  bipush 89 
L7740:  bastore 
L7741:  dup 
L7742:  ldc_w 1140 
L7745:  bipush 18 
L7747:  bastore 
L7748:  dup 
L7749:  ldc_w 1141 
L7752:  bipush 56 
L7754:  bastore 
L7755:  dup 
L7756:  ldc_w 1142 
L7759:  bipush 16 
L7761:  bastore 
L7762:  dup 
L7763:  ldc_w 1143 
L7766:  bipush 32 
L7768:  bastore 
L7769:  dup 
L7770:  ldc_w 1144 
L7773:  bipush 84 
L7775:  bastore 
L7776:  dup 
L7777:  ldc_w 1145 
L7780:  bipush 89 
L7782:  bastore 
L7783:  dup 
L7784:  ldc_w 1146 
L7787:  bipush 18 
L7789:  bastore 
L7790:  dup 
L7791:  ldc_w 1147 
L7794:  bipush 57 
L7796:  bastore 
L7797:  dup 
L7798:  ldc_w 1148 
L7801:  bipush 16 
L7803:  bastore 
L7804:  dup 
L7805:  ldc_w 1149 
L7808:  bipush 0 
L7810:  bastore 
L7811:  dup 
L7812:  ldc_w 1150 
L7815:  bipush 84 
L7817:  bastore 
L7818:  dup 
L7819:  ldc_w 1151 
L7822:  bipush 89 
L7824:  bastore 
L7825:  dup 
L7826:  ldc_w 1152 
L7829:  bipush 18 
L7831:  bastore 
L7832:  dup 
L7833:  ldc_w 1153 
L7836:  bipush 58 
L7838:  bastore 
L7839:  dup 
L7840:  ldc_w 1154 
L7843:  bipush 16 
L7845:  bastore 
L7846:  dup 
L7847:  ldc_w 1155 
L7850:  bipush 116 
L7852:  bastore 
L7853:  dup 
L7854:  ldc_w 1156 
L7857:  bipush 84 
L7859:  bastore 
L7860:  dup 
L7861:  ldc_w 1157 
L7864:  bipush 89 
L7866:  bastore 
L7867:  dup 
L7868:  ldc_w 1158 
L7871:  bipush 18 
L7873:  bastore 
L7874:  dup 
L7875:  ldc_w 1159 
L7878:  bipush 59 
L7880:  bastore 
L7881:  dup 
L7882:  ldc_w 1160 
L7885:  bipush 16 
L7887:  bastore 
L7888:  dup 
L7889:  ldc_w 1161 
L7892:  bipush 0 
L7894:  bastore 
L7895:  dup 
L7896:  ldc_w 1162 
L7899:  bipush 84 
L7901:  bastore 
L7902:  dup 
L7903:  ldc_w 1163 
L7906:  bipush 89 
L7908:  bastore 
L7909:  dup 
L7910:  ldc_w 1164 
L7913:  bipush 18 
L7915:  bastore 
L7916:  dup 
L7917:  ldc_w 1165 
L7920:  bipush 60 
L7922:  bastore 
L7923:  dup 
L7924:  ldc_w 1166 
L7927:  bipush 16 
L7929:  bastore 
L7930:  dup 
L7931:  ldc_w 1167 
L7934:  bipush 104 
L7936:  bastore 
L7937:  dup 
L7938:  ldc_w 1168 
L7941:  bipush 84 
L7943:  bastore 
L7944:  dup 
L7945:  ldc_w 1169 
L7948:  bipush 89 
L7950:  bastore 
L7951:  dup 
L7952:  ldc_w 1170 
L7955:  bipush 18 
L7957:  bastore 
L7958:  dup 
L7959:  ldc_w 1171 
L7962:  bipush 61 
L7964:  bastore 
L7965:  dup 
L7966:  ldc_w 1172 
L7969:  bipush 16 
L7971:  bastore 
L7972:  dup 
L7973:  ldc_w 1173 
L7976:  bipush 0 
L7978:  bastore 
L7979:  dup 
L7980:  ldc_w 1174 
L7983:  bipush 84 
L7985:  bastore 
L7986:  dup 
L7987:  ldc_w 1175 
L7990:  bipush 89 
L7992:  bastore 
L7993:  dup 
L7994:  ldc_w 1176 
L7997:  bipush 18 
L7999:  bastore 
L8000:  dup 
L8001:  ldc_w 1177 
L8004:  bipush 62 
L8006:  bastore 
L8007:  dup 
L8008:  ldc_w 1178 
L8011:  bipush 16 
L8013:  bastore 
L8014:  dup 
L8015:  ldc_w 1179 
L8018:  bipush 101 
L8020:  bastore 
L8021:  dup 
L8022:  ldc_w 1180 
L8025:  bipush 84 
L8027:  bastore 
L8028:  dup 
L8029:  ldc_w 1181 
L8032:  bipush 89 
L8034:  bastore 
L8035:  dup 
L8036:  ldc_w 1182 
L8039:  bipush 18 
L8041:  bastore 
L8042:  dup 
L8043:  ldc_w 1183 
L8046:  bipush 63 
L8048:  bastore 
L8049:  dup 
L8050:  ldc_w 1184 
L8053:  bipush 16 
L8055:  bastore 
L8056:  dup 
L8057:  ldc_w 1185 
L8060:  bipush 0 
L8062:  bastore 
L8063:  dup 
L8064:  ldc_w 1186 
L8067:  bipush 84 
L8069:  bastore 
L8070:  dup 
L8071:  ldc_w 1187 
L8074:  bipush 89 
L8076:  bastore 
L8077:  dup 
L8078:  ldc_w 1188 
L8081:  bipush 18 
L8083:  bastore 
L8084:  dup 
L8085:  ldc_w 1189 
L8088:  bipush 64 
L8090:  bastore 
L8091:  dup 
L8092:  ldc_w 1190 
L8095:  bipush 16 
L8097:  bastore 
L8098:  dup 
L8099:  ldc_w 1191 
L8102:  bipush 32 
L8104:  bastore 
L8105:  dup 
L8106:  ldc_w 1192 
L8109:  bipush 84 
L8111:  bastore 
L8112:  dup 
L8113:  ldc_w 1193 
L8116:  bipush 89 
L8118:  bastore 
L8119:  dup 
L8120:  ldc_w 1194 
L8123:  bipush 18 
L8125:  bastore 
L8126:  dup 
L8127:  ldc_w 1195 
L8130:  bipush 65 
L8132:  bastore 
L8133:  dup 
L8134:  ldc_w 1196 
L8137:  bipush 16 
L8139:  bastore 
L8140:  dup 
L8141:  ldc_w 1197 
L8144:  bipush 0 
L8146:  bastore 
L8147:  dup 
L8148:  ldc_w 1198 
L8151:  bipush 84 
L8153:  bastore 
L8154:  dup 
L8155:  ldc_w 1199 
L8158:  bipush 89 
L8160:  bastore 
L8161:  dup 
L8162:  ldc_w 1200 
L8165:  bipush 18 
L8167:  bastore 
L8168:  dup 
L8169:  ldc_w 1201 
L8172:  bipush 66 
L8174:  bastore 
L8175:  dup 
L8176:  ldc_w 1202 
L8179:  bipush 16 
L8181:  bastore 
L8182:  dup 
L8183:  ldc_w 1203 
L8186:  bipush 112 
L8188:  bastore 
L8189:  dup 
L8190:  ldc_w 1204 
L8193:  bipush 84 
L8195:  bastore 
L8196:  dup 
L8197:  ldc_w 1205 
L8200:  bipush 89 
L8202:  bastore 
L8203:  dup 
L8204:  ldc_w 1206 
L8207:  bipush 18 
L8209:  bastore 
L8210:  dup 
L8211:  ldc_w 1207 
L8214:  bipush 67 
L8216:  bastore 
L8217:  dup 
L8218:  ldc_w 1208 
L8221:  bipush 16 
L8223:  bastore 
L8224:  dup 
L8225:  ldc_w 1209 
L8228:  bipush 0 
L8230:  bastore 
L8231:  dup 
L8232:  ldc_w 1210 
L8235:  bipush 84 
L8237:  bastore 
L8238:  dup 
L8239:  ldc_w 1211 
L8242:  bipush 89 
L8244:  bastore 
L8245:  dup 
L8246:  ldc_w 1212 
L8249:  bipush 18 
L8251:  bastore 
L8252:  dup 
L8253:  ldc_w 1213 
L8256:  bipush 68 
L8258:  bastore 
L8259:  dup 
L8260:  ldc_w 1214 
L8263:  bipush 16 
L8265:  bastore 
L8266:  dup 
L8267:  ldc_w 1215 
L8270:  bipush 97 
L8272:  bastore 
L8273:  dup 
L8274:  ldc_w 1216 
L8277:  bipush 84 
L8279:  bastore 
L8280:  dup 
L8281:  ldc_w 1217 
L8284:  bipush 89 
L8286:  bastore 
L8287:  dup 
L8288:  ldc_w 1218 
L8291:  bipush 18 
L8293:  bastore 
L8294:  dup 
L8295:  ldc_w 1219 
L8298:  bipush 69 
L8300:  bastore 
L8301:  dup 
L8302:  ldc_w 1220 
L8305:  bipush 16 
L8307:  bastore 
L8308:  dup 
L8309:  ldc_w 1221 
L8312:  bipush 0 
L8314:  bastore 
L8315:  dup 
L8316:  ldc_w 1222 
L8319:  bipush 84 
L8321:  bastore 
L8322:  dup 
L8323:  ldc_w 1223 
L8326:  bipush 89 
L8328:  bastore 
L8329:  dup 
L8330:  ldc_w 1224 
L8333:  bipush 18 
L8335:  bastore 
L8336:  dup 
L8337:  ldc_w 1225 
L8340:  bipush 70 
L8342:  bastore 
L8343:  dup 
L8344:  ldc_w 1226 
L8347:  bipush 16 
L8349:  bastore 
L8350:  dup 
L8351:  ldc_w 1227 
L8354:  bipush 116 
L8356:  bastore 
L8357:  dup 
L8358:  ldc_w 1228 
L8361:  bipush 84 
L8363:  bastore 
L8364:  dup 
L8365:  ldc_w 1229 
L8368:  bipush 89 
L8370:  bastore 
L8371:  dup 
L8372:  ldc_w 1230 
L8375:  bipush 18 
L8377:  bastore 
L8378:  dup 
L8379:  ldc_w 1231 
L8382:  bipush 71 
L8384:  bastore 
L8385:  dup 
L8386:  ldc_w 1232 
L8389:  bipush 16 
L8391:  bastore 
L8392:  dup 
L8393:  ldc_w 1233 
L8396:  bipush 0 
L8398:  bastore 
L8399:  dup 
L8400:  ldc_w 1234 
L8403:  bipush 84 
L8405:  bastore 
L8406:  dup 
L8407:  ldc_w 1235 
L8410:  bipush 89 
L8412:  bastore 
L8413:  dup 
L8414:  ldc_w 1236 
L8417:  bipush 18 
L8419:  bastore 
L8420:  dup 
L8421:  ldc_w 1237 
L8424:  bipush 72 
L8426:  bastore 
L8427:  dup 
L8428:  ldc_w 1238 
L8431:  bipush 16 
L8433:  bastore 
L8434:  dup 
L8435:  ldc_w 1239 
L8438:  bipush 104 
L8440:  bastore 
L8441:  dup 
L8442:  ldc_w 1240 
L8445:  bipush 84 
L8447:  bastore 
L8448:  dup 
L8449:  ldc_w 1241 
L8452:  bipush 89 
L8454:  bastore 
L8455:  dup 
L8456:  ldc_w 1242 
L8459:  bipush 18 
L8461:  bastore 
L8462:  dup 
L8463:  ldc_w 1243 
L8466:  bipush 73 
L8468:  bastore 
L8469:  dup 
L8470:  ldc_w 1244 
L8473:  bipush 16 
L8475:  bastore 
L8476:  dup 
L8477:  ldc_w 1245 
L8480:  bipush 0 
L8482:  bastore 
L8483:  dup 
L8484:  ldc_w 1246 
L8487:  bipush 84 
L8489:  bastore 
L8490:  dup 
L8491:  ldc_w 1247 
L8494:  bipush 89 
L8496:  bastore 
L8497:  dup 
L8498:  ldc_w 1248 
L8501:  bipush 18 
L8503:  bastore 
L8504:  dup 
L8505:  ldc_w 1249 
L8508:  bipush 74 
L8510:  bastore 
L8511:  dup 
L8512:  ldc_w 1250 
L8515:  bipush 16 
L8517:  bastore 
L8518:  dup 
L8519:  ldc_w 1251 
L8522:  bipush 10 
L8524:  bastore 
L8525:  dup 
L8526:  ldc_w 1252 
L8529:  bipush 84 
L8531:  bastore 
L8532:  dup 
L8533:  ldc_w 1253 
L8536:  bipush 89 
L8538:  bastore 
L8539:  dup 
L8540:  ldc_w 1254 
L8543:  bipush 18 
L8545:  bastore 
L8546:  dup 
L8547:  ldc_w 1255 
L8550:  bipush 75 
L8552:  bastore 
L8553:  dup 
L8554:  ldc_w 1256 
L8557:  bipush 16 
L8559:  bastore 
L8560:  dup 
L8561:  ldc_w 1257 
L8564:  bipush 0 
L8566:  bastore 
L8567:  dup 
L8568:  ldc_w 1258 
L8571:  bipush 84 
L8573:  bastore 
L8574:  dup 
L8575:  ldc_w 1259 
L8578:  bipush 89 
L8580:  bastore 
L8581:  dup 
L8582:  ldc_w 1260 
L8585:  bipush 18 
L8587:  bastore 
L8588:  dup 
L8589:  ldc_w 1261 
L8592:  bipush 76 
L8594:  bastore 
L8595:  dup 
L8596:  ldc_w 1262 
L8599:  bipush 16 
L8601:  bastore 
L8602:  dup 
L8603:  ldc_w 1263 
L8606:  bipush 62 
L8608:  bastore 
L8609:  dup 
L8610:  ldc_w 1264 
L8613:  bipush 84 
L8615:  bastore 
L8616:  dup 
L8617:  ldc_w 1265 
L8620:  bipush 89 
L8622:  bastore 
L8623:  dup 
L8624:  ldc_w 1266 
L8627:  bipush 18 
L8629:  bastore 
L8630:  dup 
L8631:  ldc_w 1267 
L8634:  bipush 77 
L8636:  bastore 
L8637:  dup 
L8638:  ldc_w 1268 
L8641:  bipush 16 
L8643:  bastore 
L8644:  dup 
L8645:  ldc_w 1269 
L8648:  bipush 0 
L8650:  bastore 
L8651:  dup 
L8652:  ldc_w 1270 
L8655:  bipush 84 
L8657:  bastore 
L8658:  dup 
L8659:  ldc_w 1271 
L8662:  bipush 89 
L8664:  bastore 
L8665:  dup 
L8666:  ldc_w 1272 
L8669:  bipush 18 
L8671:  bastore 
L8672:  dup 
L8673:  ldc_w 1273 
L8676:  bipush 78 
L8678:  bastore 
L8679:  dup 
L8680:  ldc_w 1274 
L8683:  bipush 16 
L8685:  bastore 
L8686:  dup 
L8687:  ldc_w 1275 
L8690:  bipush 32 
L8692:  bastore 
L8693:  dup 
L8694:  ldc_w 1276 
L8697:  bipush 84 
L8699:  bastore 
L8700:  dup 
L8701:  ldc_w 1277 
L8704:  bipush 89 
L8706:  bastore 
L8707:  dup 
L8708:  ldc_w 1278 
L8711:  bipush 18 
L8713:  bastore 
L8714:  dup 
L8715:  ldc_w 1279 
L8718:  bipush 79 
L8720:  bastore 
L8721:  dup 
L8722:  ldc_w 1280 
L8725:  bipush 16 
L8727:  bastore 
L8728:  dup 
L8729:  ldc_w 1281 
L8732:  bipush 0 
L8734:  bastore 
L8735:  dup 
L8736:  ldc_w 1282 
L8739:  bipush 84 
L8741:  bastore 
L8742:  dup 
L8743:  ldc_w 1283 
L8746:  bipush -72 
L8748:  bastore 
L8749:  dup 
L8750:  ldc_w 1284 
L8753:  bipush 0 
L8755:  bastore 
L8756:  dup 
L8757:  ldc_w 1285 
L8760:  bipush 85 
L8762:  bastore 
L8763:  dup 
L8764:  ldc_w 1286 
L8767:  bipush 83 
L8769:  bastore 
L8770:  dup 
L8771:  ldc_w 1287 
L8774:  bipush 89 
L8776:  bastore 
L8777:  dup 
L8778:  ldc_w 1288 
L8781:  bipush 4 
L8783:  bastore 
L8784:  dup 
L8785:  ldc_w 1289 
L8788:  bipush 89 
L8790:  bastore 
L8791:  dup 
L8792:  ldc_w 1290 
L8795:  bipush -72 
L8797:  bastore 
L8798:  dup 
L8799:  ldc_w 1291 
L8802:  bipush 0 
L8804:  bastore 
L8805:  dup 
L8806:  ldc_w 1292 
L8809:  bipush 18 
L8811:  bastore 
L8812:  dup 
L8813:  ldc_w 1293 
L8816:  bipush 18 
L8818:  bastore 
L8819:  dup 
L8820:  ldc_w 1294 
L8823:  bipush 48 
L8825:  bastore 
L8826:  dup 
L8827:  ldc_w 1295 
L8830:  bipush -68 
L8832:  bastore 
L8833:  dup 
L8834:  ldc_w 1296 
L8837:  bipush 8 
L8839:  bastore 
L8840:  dup 
L8841:  ldc_w 1297 
L8844:  bipush 89 
L8846:  bastore 
L8847:  dup 
L8848:  ldc_w 1298 
L8851:  bipush 3 
L8853:  bastore 
L8854:  dup 
L8855:  ldc_w 1299 
L8858:  bipush 16 
L8860:  bastore 
L8861:  dup 
L8862:  ldc_w 1300 
L8865:  bipush 87 
L8867:  bastore 
L8868:  dup 
L8869:  ldc_w 1301 
L8872:  bipush 84 
L8874:  bastore 
L8875:  dup 
L8876:  ldc_w 1302 
L8879:  bipush 89 
L8881:  bastore 
L8882:  dup 
L8883:  ldc_w 1303 
L8886:  bipush 4 
L8888:  bastore 
L8889:  dup 
L8890:  ldc_w 1304 
L8893:  bipush 16 
L8895:  bastore 
L8896:  dup 
L8897:  ldc_w 1305 
L8900:  bipush 0 
L8902:  bastore 
L8903:  dup 
L8904:  ldc_w 1306 
L8907:  bipush 84 
L8909:  bastore 
L8910:  dup 
L8911:  ldc_w 1307 
L8914:  bipush 89 
L8916:  bastore 
L8917:  dup 
L8918:  ldc_w 1308 
L8921:  bipush 5 
L8923:  bastore 
L8924:  dup 
L8925:  ldc_w 1309 
L8928:  bipush 16 
L8930:  bastore 
L8931:  dup 
L8932:  ldc_w 1310 
L8935:  bipush 101 
L8937:  bastore 
L8938:  dup 
L8939:  ldc_w 1311 
L8942:  bipush 84 
L8944:  bastore 
L8945:  dup 
L8946:  ldc_w 1312 
L8949:  bipush 89 
L8951:  bastore 
L8952:  dup 
L8953:  ldc_w 1313 
L8956:  bipush 6 
L8958:  bastore 
L8959:  dup 
L8960:  ldc_w 1314 
L8963:  bipush 16 
L8965:  bastore 
L8966:  dup 
L8967:  ldc_w 1315 
L8970:  bipush 0 
L8972:  bastore 
L8973:  dup 
L8974:  ldc_w 1316 
L8977:  bipush 84 
L8979:  bastore 
L8980:  dup 
L8981:  ldc_w 1317 
L8984:  bipush 89 
L8986:  bastore 
L8987:  dup 
L8988:  ldc_w 1318 
L8991:  bipush 7 
L8993:  bastore 
L8994:  dup 
L8995:  ldc_w 1319 
L8998:  bipush 16 
L9000:  bastore 
L9001:  dup 
L9002:  ldc_w 1320 
L9005:  bipush 108 
L9007:  bastore 
L9008:  dup 
L9009:  ldc_w 1321 
L9012:  bipush 84 
L9014:  bastore 
L9015:  dup 
L9016:  ldc_w 1322 
L9019:  bipush 89 
L9021:  bastore 
L9022:  dup 
L9023:  ldc_w 1323 
L9026:  bipush 8 
L9028:  bastore 
L9029:  dup 
L9030:  ldc_w 1324 
L9033:  bipush 16 
L9035:  bastore 
L9036:  dup 
L9037:  ldc_w 1325 
L9040:  bipush 0 
L9042:  bastore 
L9043:  dup 
L9044:  ldc_w 1326 
L9047:  bipush 84 
L9049:  bastore 
L9050:  dup 
L9051:  ldc_w 1327 
L9054:  bipush 89 
L9056:  bastore 
L9057:  dup 
L9058:  ldc_w 1328 
L9061:  bipush 18 
L9063:  bastore 
L9064:  dup 
L9065:  ldc_w 1329 
L9068:  bipush 20 
L9070:  bastore 
L9071:  dup 
L9072:  ldc_w 1330 
L9075:  bipush 16 
L9077:  bastore 
L9078:  dup 
L9079:  ldc_w 1331 
L9082:  bipush 99 
L9084:  bastore 
L9085:  dup 
L9086:  ldc_w 1332 
L9089:  bipush 84 
L9091:  bastore 
L9092:  dup 
L9093:  ldc_w 1333 
L9096:  bipush 89 
L9098:  bastore 
L9099:  dup 
L9100:  ldc_w 1334 
L9103:  bipush 18 
L9105:  bastore 
L9106:  dup 
L9107:  ldc_w 1335 
L9110:  bipush 21 
L9112:  bastore 
L9113:  dup 
L9114:  ldc_w 1336 
L9117:  bipush 16 
L9119:  bastore 
L9120:  dup 
L9121:  ldc_w 1337 
L9124:  bipush 0 
L9126:  bastore 
L9127:  dup 
L9128:  ldc_w 1338 
L9131:  bipush 84 
L9133:  bastore 
L9134:  dup 
L9135:  ldc_w 1339 
L9138:  bipush 89 
L9140:  bastore 
L9141:  dup 
L9142:  ldc_w 1340 
L9145:  bipush 18 
L9147:  bastore 
L9148:  dup 
L9149:  ldc_w 1341 
L9152:  bipush 22 
L9154:  bastore 
L9155:  dup 
L9156:  ldc_w 1342 
L9159:  bipush 16 
L9161:  bastore 
L9162:  dup 
L9163:  ldc_w 1343 
L9166:  bipush 111 
L9168:  bastore 
L9169:  dup 
L9170:  ldc_w 1344 
L9173:  bipush 84 
L9175:  bastore 
L9176:  dup 
L9177:  ldc_w 1345 
L9180:  bipush 89 
L9182:  bastore 
L9183:  dup 
L9184:  ldc_w 1346 
L9187:  bipush 18 
L9189:  bastore 
L9190:  dup 
L9191:  ldc_w 1347 
L9194:  bipush 23 
L9196:  bastore 
L9197:  dup 
L9198:  ldc_w 1348 
L9201:  bipush 16 
L9203:  bastore 
L9204:  dup 
L9205:  ldc_w 1349 
L9208:  bipush 0 
L9210:  bastore 
L9211:  dup 
L9212:  ldc_w 1350 
L9215:  bipush 84 
L9217:  bastore 
L9218:  dup 
L9219:  ldc_w 1351 
L9222:  bipush 89 
L9224:  bastore 
L9225:  dup 
L9226:  ldc_w 1352 
L9229:  bipush 18 
L9231:  bastore 
L9232:  dup 
L9233:  ldc_w 1353 
L9236:  bipush 24 
L9238:  bastore 
L9239:  dup 
L9240:  ldc_w 1354 
L9243:  bipush 16 
L9245:  bastore 
L9246:  dup 
L9247:  ldc_w 1355 
L9250:  bipush 109 
L9252:  bastore 
L9253:  dup 
L9254:  ldc_w 1356 
L9257:  bipush 84 
L9259:  bastore 
L9260:  dup 
L9261:  ldc_w 1357 
L9264:  bipush 89 
L9266:  bastore 
L9267:  dup 
L9268:  ldc_w 1358 
L9271:  bipush 18 
L9273:  bastore 
L9274:  dup 
L9275:  ldc_w 1359 
L9278:  bipush 25 
L9280:  bastore 
L9281:  dup 
L9282:  ldc_w 1360 
L9285:  bipush 16 
L9287:  bastore 
L9288:  dup 
L9289:  ldc_w 1361 
L9292:  bipush 0 
L9294:  bastore 
L9295:  dup 
L9296:  ldc_w 1362 
L9299:  bipush 84 
L9301:  bastore 
L9302:  dup 
L9303:  ldc_w 1363 
L9306:  bipush 89 
L9308:  bastore 
L9309:  dup 
L9310:  ldc_w 1364 
L9313:  bipush 18 
L9315:  bastore 
L9316:  dup 
L9317:  ldc_w 1365 
L9320:  bipush 26 
L9322:  bastore 
L9323:  dup 
L9324:  ldc_w 1366 
L9327:  bipush 16 
L9329:  bastore 
L9330:  dup 
L9331:  ldc_w 1367 
L9334:  bipush 101 
L9336:  bastore 
L9337:  dup 
L9338:  ldc_w 1368 
L9341:  bipush 84 
L9343:  bastore 
L9344:  dup 
L9345:  ldc_w 1369 
L9348:  bipush 89 
L9350:  bastore 
L9351:  dup 
L9352:  ldc_w 1370 
L9355:  bipush 18 
L9357:  bastore 
L9358:  dup 
L9359:  ldc_w 1371 
L9362:  bipush 27 
L9364:  bastore 
L9365:  dup 
L9366:  ldc_w 1372 
L9369:  bipush 16 
L9371:  bastore 
L9372:  dup 
L9373:  ldc_w 1373 
L9376:  bipush 0 
L9378:  bastore 
L9379:  dup 
L9380:  ldc_w 1374 
L9383:  bipush 84 
L9385:  bastore 
L9386:  dup 
L9387:  ldc_w 1375 
L9390:  bipush 89 
L9392:  bastore 
L9393:  dup 
L9394:  ldc_w 1376 
L9397:  bipush 18 
L9399:  bastore 
L9400:  dup 
L9401:  ldc_w 1377 
L9404:  bipush 28 
L9406:  bastore 
L9407:  dup 
L9408:  ldc_w 1378 
L9411:  bipush 16 
L9413:  bastore 
L9414:  dup 
L9415:  ldc_w 1379 
L9418:  bipush 32 
L9420:  bastore 
L9421:  dup 
L9422:  ldc_w 1380 
L9425:  bipush 84 
L9427:  bastore 
L9428:  dup 
L9429:  ldc_w 1381 
L9432:  bipush 89 
L9434:  bastore 
L9435:  dup 
L9436:  ldc_w 1382 
L9439:  bipush 18 
L9441:  bastore 
L9442:  dup 
L9443:  ldc_w 1383 
L9446:  bipush 29 
L9448:  bastore 
L9449:  dup 
L9450:  ldc_w 1384 
L9453:  bipush 16 
L9455:  bastore 
L9456:  dup 
L9457:  ldc_w 1385 
L9460:  bipush 0 
L9462:  bastore 
L9463:  dup 
L9464:  ldc_w 1386 
L9467:  bipush 84 
L9469:  bastore 
L9470:  dup 
L9471:  ldc_w 1387 
L9474:  bipush 89 
L9476:  bastore 
L9477:  dup 
L9478:  ldc_w 1388 
L9481:  bipush 18 
L9483:  bastore 
L9484:  dup 
L9485:  ldc_w 1389 
L9488:  bipush 30 
L9490:  bastore 
L9491:  dup 
L9492:  ldc_w 1390 
L9495:  bipush 16 
L9497:  bastore 
L9498:  dup 
L9499:  ldc_w 1391 
L9502:  bipush 115 
L9504:  bastore 
L9505:  dup 
L9506:  ldc_w 1392 
L9509:  bipush 84 
L9511:  bastore 
L9512:  dup 
L9513:  ldc_w 1393 
L9516:  bipush 89 
L9518:  bastore 
L9519:  dup 
L9520:  ldc_w 1394 
L9523:  bipush 18 
L9525:  bastore 
L9526:  dup 
L9527:  ldc_w 1395 
L9530:  bipush 31 
L9532:  bastore 
L9533:  dup 
L9534:  ldc_w 1396 
L9537:  bipush 16 
L9539:  bastore 
L9540:  dup 
L9541:  ldc_w 1397 
L9544:  bipush 0 
L9546:  bastore 
L9547:  dup 
L9548:  ldc_w 1398 
L9551:  bipush 84 
L9553:  bastore 
L9554:  dup 
L9555:  ldc_w 1399 
L9558:  bipush 89 
L9560:  bastore 
L9561:  dup 
L9562:  ldc_w 1400 
L9565:  bipush 18 
L9567:  bastore 
L9568:  dup 
L9569:  ldc_w 1401 
L9572:  bipush 32 
L9574:  bastore 
L9575:  dup 
L9576:  ldc_w 1402 
L9579:  bipush 16 
L9581:  bastore 
L9582:  dup 
L9583:  ldc_w 1403 
L9586:  bipush 116 
L9588:  bastore 
L9589:  dup 
L9590:  ldc_w 1404 
L9593:  bipush 84 
L9595:  bastore 
L9596:  dup 
L9597:  ldc_w 1405 
L9600:  bipush 89 
L9602:  bastore 
L9603:  dup 
L9604:  ldc_w 1406 
L9607:  bipush 18 
L9609:  bastore 
L9610:  dup 
L9611:  ldc_w 1407 
L9614:  bipush 33 
L9616:  bastore 
L9617:  dup 
L9618:  ldc_w 1408 
L9621:  bipush 16 
L9623:  bastore 
L9624:  dup 
L9625:  ldc_w 1409 
L9628:  bipush 0 
L9630:  bastore 
L9631:  dup 
L9632:  ldc_w 1410 
L9635:  bipush 84 
L9637:  bastore 
L9638:  dup 
L9639:  ldc_w 1411 
L9642:  bipush 89 
L9644:  bastore 
L9645:  dup 
L9646:  ldc_w 1412 
L9649:  bipush 18 
L9651:  bastore 
L9652:  dup 
L9653:  ldc_w 1413 
L9656:  bipush 34 
L9658:  bastore 
L9659:  dup 
L9660:  ldc_w 1414 
L9663:  bipush 16 
L9665:  bastore 
L9666:  dup 
L9667:  ldc_w 1415 
L9670:  bipush 97 
L9672:  bastore 
L9673:  dup 
L9674:  ldc_w 1416 
L9677:  bipush 84 
L9679:  bastore 
L9680:  dup 
L9681:  ldc_w 1417 
L9684:  bipush 89 
L9686:  bastore 
L9687:  dup 
L9688:  ldc_w 1418 
L9691:  bipush 18 
L9693:  bastore 
L9694:  dup 
L9695:  ldc_w 1419 
L9698:  bipush 35 
L9700:  bastore 
L9701:  dup 
L9702:  ldc_w 1420 
L9705:  bipush 16 
L9707:  bastore 
L9708:  dup 
L9709:  ldc_w 1421 
L9712:  bipush 0 
L9714:  bastore 
L9715:  dup 
L9716:  ldc_w 1422 
L9719:  bipush 84 
L9721:  bastore 
L9722:  dup 
L9723:  ldc_w 1423 
L9726:  bipush 89 
L9728:  bastore 
L9729:  dup 
L9730:  ldc_w 1424 
L9733:  bipush 18 
L9735:  bastore 
L9736:  dup 
L9737:  ldc_w 1425 
L9740:  bipush 36 
L9742:  bastore 
L9743:  dup 
L9744:  ldc_w 1426 
L9747:  bipush 16 
L9749:  bastore 
L9750:  dup 
L9751:  ldc_w 1427 
L9754:  bipush 114 
L9756:  bastore 
L9757:  dup 
L9758:  ldc_w 1428 
L9761:  bipush 84 
L9763:  bastore 
L9764:  dup 
L9765:  ldc_w 1429 
L9768:  bipush 89 
L9770:  bastore 
L9771:  dup 
L9772:  ldc_w 1430 
L9775:  bipush 18 
L9777:  bastore 
L9778:  dup 
L9779:  ldc_w 1431 
L9782:  bipush 37 
L9784:  bastore 
L9785:  dup 
L9786:  ldc_w 1432 
L9789:  bipush 16 
L9791:  bastore 
L9792:  dup 
L9793:  ldc_w 1433 
L9796:  bipush 0 
L9798:  bastore 
L9799:  dup 
L9800:  ldc_w 1434 
L9803:  bipush 84 
L9805:  bastore 
L9806:  dup 
L9807:  ldc_w 1435 
L9810:  bipush 89 
L9812:  bastore 
L9813:  dup 
L9814:  ldc_w 1436 
L9817:  bipush 18 
L9819:  bastore 
L9820:  dup 
L9821:  ldc_w 1437 
L9824:  bipush 38 
L9826:  bastore 
L9827:  dup 
L9828:  ldc_w 1438 
L9831:  bipush 16 
L9833:  bastore 
L9834:  dup 
L9835:  ldc_w 1439 
L9838:  bipush 99 
L9840:  bastore 
L9841:  dup 
L9842:  ldc_w 1440 
L9845:  bipush 84 
L9847:  bastore 
L9848:  dup 
L9849:  ldc_w 1441 
L9852:  bipush 89 
L9854:  bastore 
L9855:  dup 
L9856:  ldc_w 1442 
L9859:  bipush 18 
L9861:  bastore 
L9862:  dup 
L9863:  ldc_w 1443 
L9866:  bipush 39 
L9868:  bastore 
L9869:  dup 
L9870:  ldc_w 1444 
L9873:  bipush 16 
L9875:  bastore 
L9876:  dup 
L9877:  ldc_w 1445 
L9880:  bipush 0 
L9882:  bastore 
L9883:  dup 
L9884:  ldc_w 1446 
L9887:  bipush 84 
L9889:  bastore 
L9890:  dup 
L9891:  ldc_w 1447 
L9894:  bipush 89 
L9896:  bastore 
L9897:  dup 
L9898:  ldc_w 1448 
L9901:  bipush 18 
L9903:  bastore 
L9904:  dup 
L9905:  ldc_w 1449 
L9908:  bipush 40 
L9910:  bastore 
L9911:  dup 
L9912:  ldc_w 1450 
L9915:  bipush 16 
L9917:  bastore 
L9918:  dup 
L9919:  ldc_w 1451 
L9922:  bipush 104 
L9924:  bastore 
L9925:  dup 
L9926:  ldc_w 1452 
L9929:  bipush 84 
L9931:  bastore 
L9932:  dup 
L9933:  ldc_w 1453 
L9936:  bipush 89 
L9938:  bastore 
L9939:  dup 
L9940:  ldc_w 1454 
L9943:  bipush 18 
L9945:  bastore 
L9946:  dup 
L9947:  ldc_w 1455 
L9950:  bipush 41 
L9952:  bastore 
L9953:  dup 
L9954:  ldc_w 1456 
L9957:  bipush 16 
L9959:  bastore 
L9960:  dup 
L9961:  ldc_w 1457 
L9964:  bipush 0 
L9966:  bastore 
L9967:  dup 
L9968:  ldc_w 1458 
L9971:  bipush 84 
L9973:  bastore 
L9974:  dup 
L9975:  ldc_w 1459 
L9978:  bipush 89 
L9980:  bastore 
L9981:  dup 
L9982:  ldc_w 1460 
L9985:  bipush 18 
L9987:  bastore 
L9988:  dup 
L9989:  ldc_w 1461 
L9992:  bipush 42 
L9994:  bastore 
L9995:  dup 
L9996:  ldc_w 1462 
L9999:  bipush 16 
L10001: bastore 
L10002: dup 
L10003: ldc_w 1463 
L10006: bipush 105 
L10008: bastore 
L10009: dup 
L10010: ldc_w 1464 
L10013: bipush 84 
L10015: bastore 
L10016: dup 
L10017: ldc_w 1465 
L10020: bipush 89 
L10022: bastore 
L10023: dup 
L10024: ldc_w 1466 
L10027: bipush 18 
L10029: bastore 
L10030: dup 
L10031: ldc_w 1467 
L10034: bipush 43 
L10036: bastore 
L10037: dup 
L10038: ldc_w 1468 
L10041: bipush 16 
L10043: bastore 
L10044: dup 
L10045: ldc_w 1469 
L10048: bipush 0 
L10050: bastore 
L10051: dup 
L10052: ldc_w 1470 
L10055: bipush 84 
L10057: bastore 
L10058: dup 
L10059: ldc_w 1471 
L10062: bipush 89 
L10064: bastore 
L10065: dup 
L10066: ldc_w 1472 
L10069: bipush 18 
L10071: bastore 
L10072: dup 
L10073: ldc_w 1473 
L10076: bipush 44 
L10078: bastore 
L10079: dup 
L10080: ldc_w 1474 
L10083: bipush 16 
L10085: bastore 
L10086: dup 
L10087: ldc_w 1475 
L10090: bipush 108 
L10092: bastore 
L10093: dup 
L10094: ldc_w 1476 
L10097: bipush 84 
L10099: bastore 
L10100: dup 
L10101: ldc_w 1477 
L10104: bipush 89 
L10106: bastore 
L10107: dup 
L10108: ldc_w 1478 
L10111: bipush 18 
L10113: bastore 
L10114: dup 
L10115: ldc_w 1479 
L10118: bipush 45 
L10120: bastore 
L10121: dup 
L10122: ldc_w 1480 
L10125: bipush 16 
L10127: bastore 
L10128: dup 
L10129: ldc_w 1481 
L10132: bipush 0 
L10134: bastore 
L10135: dup 
L10136: ldc_w 1482 
L10139: bipush 84 
L10141: bastore 
L10142: dup 
L10143: ldc_w 1483 
L10146: bipush 89 
L10148: bastore 
L10149: dup 
L10150: ldc_w 1484 
L10153: bipush 18 
L10155: bastore 
L10156: dup 
L10157: ldc_w 1485 
L10160: bipush 46 
L10162: bastore 
L10163: dup 
L10164: ldc_w 1486 
L10167: bipush 16 
L10169: bastore 
L10170: dup 
L10171: ldc_w 1487 
L10174: bipush 100 
L10176: bastore 
L10177: dup 
L10178: ldc_w 1488 
L10181: bipush 84 
L10183: bastore 
L10184: dup 
L10185: ldc_w 1489 
L10188: bipush 89 
L10190: bastore 
L10191: dup 
L10192: ldc_w 1490 
L10195: bipush 18 
L10197: bastore 
L10198: dup 
L10199: ldc_w 1491 
L10202: bipush 47 
L10204: bastore 
L10205: dup 
L10206: ldc_w 1492 
L10209: bipush 16 
L10211: bastore 
L10212: dup 
L10213: ldc_w 1493 
L10216: bipush 0 
L10218: bastore 
L10219: dup 
L10220: ldc_w 1494 
L10223: bipush 84 
L10225: bastore 
L10226: dup 
L10227: ldc_w 1495 
L10230: bipush -72 
L10232: bastore 
L10233: dup 
L10234: ldc_w 1496 
L10237: bipush 0 
L10239: bastore 
L10240: dup 
L10241: ldc_w 1497 
L10244: bipush 85 
L10246: bastore 
L10247: dup 
L10248: ldc_w 1498 
L10251: bipush 83 
L10253: bastore 
L10254: dup 
L10255: ldc_w 1499 
L10258: bipush 89 
L10260: bastore 
L10261: dup 
L10262: ldc_w 1500 
L10265: bipush 5 
L10267: bastore 
L10268: dup 
L10269: ldc_w 1501 
L10272: bipush 89 
L10274: bastore 
L10275: dup 
L10276: ldc_w 1502 
L10279: bipush -72 
L10281: bastore 
L10282: dup 
L10283: ldc_w 1503 
L10286: bipush 0 
L10288: bastore 
L10289: dup 
L10290: ldc_w 1504 
L10293: bipush 18 
L10295: bastore 
L10296: dup 
L10297: ldc_w 1505 
L10300: bipush 18 
L10302: bastore 
L10303: dup 
L10304: ldc_w 1506 
L10307: bipush 58 
L10309: bastore 
L10310: dup 
L10311: ldc_w 1507 
L10314: bipush -68 
L10316: bastore 
L10317: dup 
L10318: ldc_w 1508 
L10321: bipush 8 
L10323: bastore 
L10324: dup 
L10325: ldc_w 1509 
L10328: bipush 89 
L10330: bastore 
L10331: dup 
L10332: ldc_w 1510 
L10335: bipush 3 
L10337: bastore 
L10338: dup 
L10339: ldc_w 1511 
L10342: bipush 16 
L10344: bastore 
L10345: dup 
L10346: ldc_w 1512 
L10349: bipush 89 
L10351: bastore 
L10352: dup 
L10353: ldc_w 1513 
L10356: bipush 84 
L10358: bastore 
L10359: dup 
L10360: ldc_w 1514 
L10363: bipush 89 
L10365: bastore 
L10366: dup 
L10367: ldc_w 1515 
L10370: bipush 4 
L10372: bastore 
L10373: dup 
L10374: ldc_w 1516 
L10377: bipush 16 
L10379: bastore 
L10380: dup 
L10381: ldc_w 1517 
L10384: bipush 0 
L10386: bastore 
L10387: dup 
L10388: ldc_w 1518 
L10391: bipush 84 
L10393: bastore 
L10394: dup 
L10395: ldc_w 1519 
L10398: bipush 89 
L10400: bastore 
L10401: dup 
L10402: ldc_w 1520 
L10405: bipush 5 
L10407: bastore 
L10408: dup 
L10409: ldc_w 1521 
L10412: bipush 16 
L10414: bastore 
L10415: dup 
L10416: ldc_w 1522 
L10419: bipush 111 
L10421: bastore 
L10422: dup 
L10423: ldc_w 1523 
L10426: bipush 84 
L10428: bastore 
L10429: dup 
L10430: ldc_w 1524 
L10433: bipush 89 
L10435: bastore 
L10436: dup 
L10437: ldc_w 1525 
L10440: bipush 6 
L10442: bastore 
L10443: dup 
L10444: ldc_w 1526 
L10447: bipush 16 
L10449: bastore 
L10450: dup 
L10451: ldc_w 1527 
L10454: bipush 0 
L10456: bastore 
L10457: dup 
L10458: ldc_w 1528 
L10461: bipush 84 
L10463: bastore 
L10464: dup 
L10465: ldc_w 1529 
L10468: bipush 89 
L10470: bastore 
L10471: dup 
L10472: ldc_w 1530 
L10475: bipush 7 
L10477: bastore 
L10478: dup 
L10479: ldc_w 1531 
L10482: bipush 16 
L10484: bastore 
L10485: dup 
L10486: ldc_w 1532 
L10489: bipush 117 
L10491: bastore 
L10492: dup 
L10493: ldc_w 1533 
L10496: bipush 84 
L10498: bastore 
L10499: dup 
L10500: ldc_w 1534 
L10503: bipush 89 
L10505: bastore 
L10506: dup 
L10507: ldc_w 1535 
L10510: bipush 8 
L10512: bastore 
L10513: dup 
L10514: ldc_w 1536 
L10517: bipush 16 
L10519: bastore 
L10520: dup 
L10521: ldc_w 1537 
L10524: bipush 0 
L10526: bastore 
L10527: dup 
L10528: ldc_w 1538 
L10531: bipush 84 
L10533: bastore 
L10534: dup 
L10535: ldc_w 1539 
L10538: bipush 89 
L10540: bastore 
L10541: dup 
L10542: ldc_w 1540 
L10545: bipush 18 
L10547: bastore 
L10548: dup 
L10549: ldc_w 1541 
L10552: bipush 20 
L10554: bastore 
L10555: dup 
L10556: ldc_w 1542 
L10559: bipush 16 
L10561: bastore 
L10562: dup 
L10563: ldc_w 1543 
L10566: bipush 32 
L10568: bastore 
L10569: dup 
L10570: ldc_w 1544 
L10573: bipush 84 
L10575: bastore 
L10576: dup 
L10577: ldc_w 1545 
L10580: bipush 89 
L10582: bastore 
L10583: dup 
L10584: ldc_w 1546 
L10587: bipush 18 
L10589: bastore 
L10590: dup 
L10591: ldc_w 1547 
L10594: bipush 21 
L10596: bastore 
L10597: dup 
L10598: ldc_w 1548 
L10601: bipush 16 
L10603: bastore 
L10604: dup 
L10605: ldc_w 1549 
L10608: bipush 0 
L10610: bastore 
L10611: dup 
L10612: ldc_w 1550 
L10615: bipush 84 
L10617: bastore 
L10618: dup 
L10619: ldc_w 1551 
L10622: bipush 89 
L10624: bastore 
L10625: dup 
L10626: ldc_w 1552 
L10629: bipush 18 
L10631: bastore 
L10632: dup 
L10633: ldc_w 1553 
L10636: bipush 22 
L10638: bastore 
L10639: dup 
L10640: ldc_w 1554 
L10643: bipush 16 
L10645: bastore 
L10646: dup 
L10647: ldc_w 1555 
L10650: bipush 115 
L10652: bastore 
L10653: dup 
L10654: ldc_w 1556 
L10657: bipush 84 
L10659: bastore 
L10660: dup 
L10661: ldc_w 1557 
L10664: bipush 89 
L10666: bastore 
L10667: dup 
L10668: ldc_w 1558 
L10671: bipush 18 
L10673: bastore 
L10674: dup 
L10675: ldc_w 1559 
L10678: bipush 23 
L10680: bastore 
L10681: dup 
L10682: ldc_w 1560 
L10685: bipush 16 
L10687: bastore 
L10688: dup 
L10689: ldc_w 1561 
L10692: bipush 0 
L10694: bastore 
L10695: dup 
L10696: ldc_w 1562 
L10699: bipush 84 
L10701: bastore 
L10702: dup 
L10703: ldc_w 1563 
L10706: bipush 89 
L10708: bastore 
L10709: dup 
L10710: ldc_w 1564 
L10713: bipush 18 
L10715: bastore 
L10716: dup 
L10717: ldc_w 1565 
L10720: bipush 24 
L10722: bastore 
L10723: dup 
L10724: ldc_w 1566 
L10727: bipush 16 
L10729: bastore 
L10730: dup 
L10731: ldc_w 1567 
L10734: bipush 116 
L10736: bastore 
L10737: dup 
L10738: ldc_w 1568 
L10741: bipush 84 
L10743: bastore 
L10744: dup 
L10745: ldc_w 1569 
L10748: bipush 89 
L10750: bastore 
L10751: dup 
L10752: ldc_w 1570 
L10755: bipush 18 
L10757: bastore 
L10758: dup 
L10759: ldc_w 1571 
L10762: bipush 25 
L10764: bastore 
L10765: dup 
L10766: ldc_w 1572 
L10769: bipush 16 
L10771: bastore 
L10772: dup 
L10773: ldc_w 1573 
L10776: bipush 0 
L10778: bastore 
L10779: dup 
L10780: ldc_w 1574 
L10783: bipush 84 
L10785: bastore 
L10786: dup 
L10787: ldc_w 1575 
L10790: bipush 89 
L10792: bastore 
L10793: dup 
L10794: ldc_w 1576 
L10797: bipush 18 
L10799: bastore 
L10800: dup 
L10801: ldc_w 1577 
L10804: bipush 26 
L10806: bastore 
L10807: dup 
L10808: ldc_w 1578 
L10811: bipush 16 
L10813: bastore 
L10814: dup 
L10815: ldc_w 1579 
L10818: bipush 105 
L10820: bastore 
L10821: dup 
L10822: ldc_w 1580 
L10825: bipush 84 
L10827: bastore 
L10828: dup 
L10829: ldc_w 1581 
L10832: bipush 89 
L10834: bastore 
L10835: dup 
L10836: ldc_w 1582 
L10839: bipush 18 
L10841: bastore 
L10842: dup 
L10843: ldc_w 1583 
L10846: bipush 27 
L10848: bastore 
L10849: dup 
L10850: ldc_w 1584 
L10853: bipush 16 
L10855: bastore 
L10856: dup 
L10857: ldc_w 1585 
L10860: bipush 0 
L10862: bastore 
L10863: dup 
L10864: ldc_w 1586 
L10867: bipush 84 
L10869: bastore 
L10870: dup 
L10871: ldc_w 1587 
L10874: bipush 89 
L10876: bastore 
L10877: dup 
L10878: ldc_w 1588 
L10881: bipush 18 
L10883: bastore 
L10884: dup 
L10885: ldc_w 1589 
L10888: bipush 28 
L10890: bastore 
L10891: dup 
L10892: ldc_w 1590 
L10895: bipush 16 
L10897: bastore 
L10898: dup 
L10899: ldc_w 1591 
L10902: bipush 108 
L10904: bastore 
L10905: dup 
L10906: ldc_w 1592 
L10909: bipush 84 
L10911: bastore 
L10912: dup 
L10913: ldc_w 1593 
L10916: bipush 89 
L10918: bastore 
L10919: dup 
L10920: ldc_w 1594 
L10923: bipush 18 
L10925: bastore 
L10926: dup 
L10927: ldc_w 1595 
L10930: bipush 29 
L10932: bastore 
L10933: dup 
L10934: ldc_w 1596 
L10937: bipush 16 
L10939: bastore 
L10940: dup 
L10941: ldc_w 1597 
L10944: bipush 0 
L10946: bastore 
L10947: dup 
L10948: ldc_w 1598 
L10951: bipush 84 
L10953: bastore 
L10954: dup 
L10955: ldc_w 1599 
L10958: bipush 89 
L10960: bastore 
L10961: dup 
L10962: ldc_w 1600 
L10965: bipush 18 
L10967: bastore 
L10968: dup 
L10969: ldc_w 1601 
L10972: bipush 30 
L10974: bastore 
L10975: dup 
L10976: ldc_w 1602 
L10979: bipush 16 
L10981: bastore 
L10982: dup 
L10983: ldc_w 1603 
L10986: bipush 108 
L10988: bastore 
L10989: dup 
L10990: ldc_w 1604 
L10993: bipush 84 
L10995: bastore 
L10996: dup 
L10997: ldc_w 1605 
L11000: bipush 89 
L11002: bastore 
L11003: dup 
L11004: ldc_w 1606 
L11007: bipush 18 
L11009: bastore 
L11010: dup 
L11011: ldc_w 1607 
L11014: bipush 31 
L11016: bastore 
L11017: dup 
L11018: ldc_w 1608 
L11021: bipush 16 
L11023: bastore 
L11024: dup 
L11025: ldc_w 1609 
L11028: bipush 0 
L11030: bastore 
L11031: dup 
L11032: ldc_w 1610 
L11035: bipush 84 
L11037: bastore 
L11038: dup 
L11039: ldc_w 1611 
L11042: bipush 89 
L11044: bastore 
L11045: dup 
L11046: ldc_w 1612 
L11049: bipush 18 
L11051: bastore 
L11052: dup 
L11053: ldc_w 1613 
L11056: bipush 32 
L11058: bastore 
L11059: dup 
L11060: ldc_w 1614 
L11063: bipush 16 
L11065: bastore 
L11066: dup 
L11067: ldc_w 1615 
L11070: bipush 32 
L11072: bastore 
L11073: dup 
L11074: ldc_w 1616 
L11077: bipush 84 
L11079: bastore 
L11080: dup 
L11081: ldc_w 1617 
L11084: bipush 89 
L11086: bastore 
L11087: dup 
L11088: ldc_w 1618 
L11091: bipush 18 
L11093: bastore 
L11094: dup 
L11095: ldc_w 1619 
L11098: bipush 33 
L11100: bastore 
L11101: dup 
L11102: ldc_w 1620 
L11105: bipush 16 
L11107: bastore 
L11108: dup 
L11109: ldc_w 1621 
L11112: bipush 0 
L11114: bastore 
L11115: dup 
L11116: ldc_w 1622 
L11119: bipush 84 
L11121: bastore 
L11122: dup 
L11123: ldc_w 1623 
L11126: bipush 89 
L11128: bastore 
L11129: dup 
L11130: ldc_w 1624 
L11133: bipush 18 
L11135: bastore 
L11136: dup 
L11137: ldc_w 1625 
L11140: bipush 34 
L11142: bastore 
L11143: dup 
L11144: ldc_w 1626 
L11147: bipush 16 
L11149: bastore 
L11150: dup 
L11151: ldc_w 1627 
L11154: bipush 104 
L11156: bastore 
L11157: dup 
L11158: ldc_w 1628 
L11161: bipush 84 
L11163: bastore 
L11164: dup 
L11165: ldc_w 1629 
L11168: bipush 89 
L11170: bastore 
L11171: dup 
L11172: ldc_w 1630 
L11175: bipush 18 
L11177: bastore 
L11178: dup 
L11179: ldc_w 1631 
L11182: bipush 35 
L11184: bastore 
L11185: dup 
L11186: ldc_w 1632 
L11189: bipush 16 
L11191: bastore 
L11192: dup 
L11193: ldc_w 1633 
L11196: bipush 0 
L11198: bastore 
L11199: dup 
L11200: ldc_w 1634 
L11203: bipush 84 
L11205: bastore 
L11206: dup 
L11207: ldc_w 1635 
L11210: bipush 89 
L11212: bastore 
L11213: dup 
L11214: ldc_w 1636 
L11217: bipush 18 
L11219: bastore 
L11220: dup 
L11221: ldc_w 1637 
L11224: bipush 36 
L11226: bastore 
L11227: dup 
L11228: ldc_w 1638 
L11231: bipush 16 
L11233: bastore 
L11234: dup 
L11235: ldc_w 1639 
L11238: bipush 97 
L11240: bastore 
L11241: dup 
L11242: ldc_w 1640 
L11245: bipush 84 
L11247: bastore 
L11248: dup 
L11249: ldc_w 1641 
L11252: bipush 89 
L11254: bastore 
L11255: dup 
L11256: ldc_w 1642 
L11259: bipush 18 
L11261: bastore 
L11262: dup 
L11263: ldc_w 1643 
L11266: bipush 37 
L11268: bastore 
L11269: dup 
L11270: ldc_w 1644 
L11273: bipush 16 
L11275: bastore 
L11276: dup 
L11277: ldc_w 1645 
L11280: bipush 0 
L11282: bastore 
L11283: dup 
L11284: ldc_w 1646 
L11287: bipush 84 
L11289: bastore 
L11290: dup 
L11291: ldc_w 1647 
L11294: bipush 89 
L11296: bastore 
L11297: dup 
L11298: ldc_w 1648 
L11301: bipush 18 
L11303: bastore 
L11304: dup 
L11305: ldc_w 1649 
L11308: bipush 38 
L11310: bastore 
L11311: dup 
L11312: ldc_w 1650 
L11315: bipush 16 
L11317: bastore 
L11318: dup 
L11319: ldc_w 1651 
L11322: bipush 118 
L11324: bastore 
L11325: dup 
L11326: ldc_w 1652 
L11329: bipush 84 
L11331: bastore 
L11332: dup 
L11333: ldc_w 1653 
L11336: bipush 89 
L11338: bastore 
L11339: dup 
L11340: ldc_w 1654 
L11343: bipush 18 
L11345: bastore 
L11346: dup 
L11347: ldc_w 1655 
L11350: bipush 39 
L11352: bastore 
L11353: dup 
L11354: ldc_w 1656 
L11357: bipush 16 
L11359: bastore 
L11360: dup 
L11361: ldc_w 1657 
L11364: bipush 0 
L11366: bastore 
L11367: dup 
L11368: ldc_w 1658 
L11371: bipush 84 
L11373: bastore 
L11374: dup 
L11375: ldc_w 1659 
L11378: bipush 89 
L11380: bastore 
L11381: dup 
L11382: ldc_w 1660 
L11385: bipush 18 
L11387: bastore 
L11388: dup 
L11389: ldc_w 1661 
L11392: bipush 40 
L11394: bastore 
L11395: dup 
L11396: ldc_w 1662 
L11399: bipush 16 
L11401: bastore 
L11402: dup 
L11403: ldc_w 1663 
L11406: bipush 101 
L11408: bastore 
L11409: dup 
L11410: ldc_w 1664 
L11413: bipush 84 
L11415: bastore 
L11416: dup 
L11417: ldc_w 1665 
L11420: bipush 89 
L11422: bastore 
L11423: dup 
L11424: ldc_w 1666 
L11427: bipush 18 
L11429: bastore 
L11430: dup 
L11431: ldc_w 1667 
L11434: bipush 41 
L11436: bastore 
L11437: dup 
L11438: ldc_w 1668 
L11441: bipush 16 
L11443: bastore 
L11444: dup 
L11445: ldc_w 1669 
L11448: bipush 0 
L11450: bastore 
L11451: dup 
L11452: ldc_w 1670 
L11455: bipush 84 
L11457: bastore 
L11458: dup 
L11459: ldc_w 1671 
L11462: bipush 89 
L11464: bastore 
L11465: dup 
L11466: ldc_w 1672 
L11469: bipush 18 
L11471: bastore 
L11472: dup 
L11473: ldc_w 1673 
L11476: bipush 42 
L11478: bastore 
L11479: dup 
L11480: ldc_w 1674 
L11483: bipush 16 
L11485: bastore 
L11486: dup 
L11487: ldc_w 1675 
L11490: bipush 32 
L11492: bastore 
L11493: dup 
L11494: ldc_w 1676 
L11497: bipush 84 
L11499: bastore 
L11500: dup 
L11501: ldc_w 1677 
L11504: bipush 89 
L11506: bastore 
L11507: dup 
L11508: ldc_w 1678 
L11511: bipush 18 
L11513: bastore 
L11514: dup 
L11515: ldc_w 1679 
L11518: bipush 43 
L11520: bastore 
L11521: dup 
L11522: ldc_w 1680 
L11525: bipush 16 
L11527: bastore 
L11528: dup 
L11529: ldc_w 1681 
L11532: bipush 0 
L11534: bastore 
L11535: dup 
L11536: ldc_w 1682 
L11539: bipush 84 
L11541: bastore 
L11542: dup 
L11543: ldc_w 1683 
L11546: bipush 89 
L11548: bastore 
L11549: dup 
L11550: ldc_w 1684 
L11553: bipush 18 
L11555: bastore 
L11556: dup 
L11557: ldc_w 1685 
L11560: bipush 44 
L11562: bastore 
L11563: dup 
L11564: ldc_w 1686 
L11567: bipush 16 
L11569: bastore 
L11570: dup 
L11571: ldc_w 1687 
L11574: bipush 116 
L11576: bastore 
L11577: dup 
L11578: ldc_w 1688 
L11581: bipush 84 
L11583: bastore 
L11584: dup 
L11585: ldc_w 1689 
L11588: bipush 89 
L11590: bastore 
L11591: dup 
L11592: ldc_w 1690 
L11595: bipush 18 
L11597: bastore 
L11598: dup 
L11599: ldc_w 1691 
L11602: bipush 45 
L11604: bastore 
L11605: dup 
L11606: ldc_w 1692 
L11609: bipush 16 
L11611: bastore 
L11612: dup 
L11613: ldc_w 1693 
L11616: bipush 0 
L11618: bastore 
L11619: dup 
L11620: ldc_w 1694 
L11623: bipush 84 
L11625: bastore 
L11626: dup 
L11627: ldc_w 1695 
L11630: bipush 89 
L11632: bastore 
L11633: dup 
L11634: ldc_w 1696 
L11637: bipush 18 
L11639: bastore 
L11640: dup 
L11641: ldc_w 1697 
L11644: bipush 46 
L11646: bastore 
L11647: dup 
L11648: ldc_w 1698 
L11651: bipush 16 
L11653: bastore 
L11654: dup 
L11655: ldc_w 1699 
L11658: bipush 111 
L11660: bastore 
L11661: dup 
L11662: ldc_w 1700 
L11665: bipush 84 
L11667: bastore 
L11668: dup 
L11669: ldc_w 1701 
L11672: bipush 89 
L11674: bastore 
L11675: dup 
L11676: ldc_w 1702 
L11679: bipush 18 
L11681: bastore 
L11682: dup 
L11683: ldc_w 1703 
L11686: bipush 47 
L11688: bastore 
L11689: dup 
L11690: ldc_w 1704 
L11693: bipush 16 
L11695: bastore 
L11696: dup 
L11697: ldc_w 1705 
L11700: bipush 0 
L11702: bastore 
L11703: dup 
L11704: ldc_w 1706 
L11707: bipush 84 
L11709: bastore 
L11710: dup 
L11711: ldc_w 1707 
L11714: bipush 89 
L11716: bastore 
L11717: dup 
L11718: ldc_w 1708 
L11721: bipush 18 
L11723: bastore 
L11724: dup 
L11725: ldc_w 1709 
L11728: bipush 48 
L11730: bastore 
L11731: dup 
L11732: ldc_w 1710 
L11735: bipush 16 
L11737: bastore 
L11738: dup 
L11739: ldc_w 1711 
L11742: bipush 32 
L11744: bastore 
L11745: dup 
L11746: ldc_w 1712 
L11749: bipush 84 
L11751: bastore 
L11752: dup 
L11753: ldc_w 1713 
L11756: bipush 89 
L11758: bastore 
L11759: dup 
L11760: ldc_w 1714 
L11763: bipush 18 
L11765: bastore 
L11766: dup 
L11767: ldc_w 1715 
L11770: bipush 49 
L11772: bastore 
L11773: dup 
L11774: ldc_w 1716 
L11777: bipush 16 
L11779: bastore 
L11780: dup 
L11781: ldc_w 1717 
L11784: bipush 0 
L11786: bastore 
L11787: dup 
L11788: ldc_w 1718 
L11791: bipush 84 
L11793: bastore 
L11794: dup 
L11795: ldc_w 1719 
L11798: bipush 89 
L11800: bastore 
L11801: dup 
L11802: ldc_w 1720 
L11805: bipush 18 
L11807: bastore 
L11808: dup 
L11809: ldc_w 1721 
L11812: bipush 50 
L11814: bastore 
L11815: dup 
L11816: ldc_w 1722 
L11819: bipush 16 
L11821: bastore 
L11822: dup 
L11823: ldc_w 1723 
L11826: bipush 103 
L11828: bastore 
L11829: dup 
L11830: ldc_w 1724 
L11833: bipush 84 
L11835: bastore 
L11836: dup 
L11837: ldc_w 1725 
L11840: bipush 89 
L11842: bastore 
L11843: dup 
L11844: ldc_w 1726 
L11847: bipush 18 
L11849: bastore 
L11850: dup 
L11851: ldc_w 1727 
L11854: bipush 51 
L11856: bastore 
L11857: dup 
L11858: ldc_w 1728 
L11861: bipush 16 
L11863: bastore 
L11864: dup 
L11865: ldc_w 1729 
L11868: bipush 0 
L11870: bastore 
L11871: dup 
L11872: ldc_w 1730 
L11875: bipush 84 
L11877: bastore 
L11878: dup 
L11879: ldc_w 1731 
L11882: bipush 89 
L11884: bastore 
L11885: dup 
L11886: ldc_w 1732 
L11889: bipush 18 
L11891: bastore 
L11892: dup 
L11893: ldc_w 1733 
L11896: bipush 52 
L11898: bastore 
L11899: dup 
L11900: ldc_w 1734 
L11903: bipush 16 
L11905: bastore 
L11906: dup 
L11907: ldc_w 1735 
L11910: bipush 114 
L11912: bastore 
L11913: dup 
L11914: ldc_w 1736 
L11917: bipush 84 
L11919: bastore 
L11920: dup 
L11921: ldc_w 1737 
L11924: bipush 89 
L11926: bastore 
L11927: dup 
L11928: ldc_w 1738 
L11931: bipush 18 
L11933: bastore 
L11934: dup 
L11935: ldc_w 1739 
L11938: bipush 53 
L11940: bastore 
L11941: dup 
L11942: ldc_w 1740 
L11945: bipush 16 
L11947: bastore 
L11948: dup 
L11949: ldc_w 1741 
L11952: bipush 0 
L11954: bastore 
L11955: dup 
L11956: ldc_w 1742 
L11959: bipush 84 
L11961: bastore 
L11962: dup 
L11963: ldc_w 1743 
L11966: bipush 89 
L11968: bastore 
L11969: dup 
L11970: ldc_w 1744 
L11973: bipush 18 
L11975: bastore 
L11976: dup 
L11977: ldc_w 1745 
L11980: bipush 54 
L11982: bastore 
L11983: dup 
L11984: ldc_w 1746 
L11987: bipush 16 
L11989: bastore 
L11990: dup 
L11991: ldc_w 1747 
L11994: bipush 111 
L11996: bastore 
L11997: dup 
L11998: ldc_w 1748 
L12001: bipush 84 
L12003: bastore 
L12004: dup 
L12005: ldc_w 1749 
L12008: bipush 89 
L12010: bastore 
L12011: dup 
L12012: ldc_w 1750 
L12015: bipush 18 
L12017: bastore 
L12018: dup 
L12019: ldc_w 1751 
L12022: bipush 55 
L12024: bastore 
L12025: dup 
L12026: ldc_w 1752 
L12029: bipush 16 
L12031: bastore 
L12032: dup 
L12033: ldc_w 1753 
L12036: bipush 0 
L12038: bastore 
L12039: dup 
L12040: ldc_w 1754 
L12043: bipush 84 
L12045: bastore 
L12046: dup 
L12047: ldc_w 1755 
L12050: bipush 89 
L12052: bastore 
L12053: dup 
L12054: ldc_w 1756 
L12057: bipush 18 
L12059: bastore 
L12060: dup 
L12061: ldc_w 1757 
L12064: bipush 56 
L12066: bastore 
L12067: dup 
L12068: ldc_w 1758 
L12071: bipush 16 
L12073: bastore 
L12074: dup 
L12075: ldc_w 1759 
L12078: bipush 119 
L12080: bastore 
L12081: dup 
L12082: ldc_w 1760 
L12085: bipush 84 
L12087: bastore 
L12088: dup 
L12089: ldc_w 1761 
L12092: bipush 89 
L12094: bastore 
L12095: dup 
L12096: ldc_w 1762 
L12099: bipush 18 
L12101: bastore 
L12102: dup 
L12103: ldc_w 1763 
L12106: bipush 57 
L12108: bastore 
L12109: dup 
L12110: ldc_w 1764 
L12113: bipush 16 
L12115: bastore 
L12116: dup 
L12117: ldc_w 1765 
L12120: bipush 0 
L12122: bastore 
L12123: dup 
L12124: ldc_w 1766 
L12127: bipush 84 
L12129: bastore 
L12130: dup 
L12131: ldc_w 1767 
L12134: bipush -72 
L12136: bastore 
L12137: dup 
L12138: ldc_w 1768 
L12141: bipush 0 
L12143: bastore 
L12144: dup 
L12145: ldc_w 1769 
L12148: bipush 85 
L12150: bastore 
L12151: dup 
L12152: ldc_w 1770 
L12155: bipush 83 
L12157: bastore 
L12158: dup 
L12159: ldc_w 1771 
L12162: bipush 89 
L12164: bastore 
L12165: dup 
L12166: ldc_w 1772 
L12169: bipush 6 
L12171: bastore 
L12172: dup 
L12173: ldc_w 1773 
L12176: bipush 89 
L12178: bastore 
L12179: dup 
L12180: ldc_w 1774 
L12183: bipush -72 
L12185: bastore 
L12186: dup 
L12187: ldc_w 1775 
L12190: bipush 0 
L12192: bastore 
L12193: dup 
L12194: ldc_w 1776 
L12197: bipush 18 
L12199: bastore 
L12200: dup 
L12201: ldc_w 1777 
L12204: bipush 18 
L12206: bastore 
L12207: dup 
L12208: ldc_w 1778 
L12211: bipush 22 
L12213: bastore 
L12214: dup 
L12215: ldc_w 1779 
L12218: bipush -68 
L12220: bastore 
L12221: dup 
L12222: ldc_w 1780 
L12225: bipush 8 
L12227: bastore 
L12228: dup 
L12229: ldc_w 1781 
L12232: bipush 89 
L12234: bastore 
L12235: dup 
L12236: ldc_w 1782 
L12239: bipush 3 
L12241: bastore 
L12242: dup 
L12243: ldc_w 1783 
L12246: bipush 16 
L12248: bastore 
L12249: dup 
L12250: ldc_w 1784 
L12253: bipush 76 
L12255: bastore 
L12256: dup 
L12257: ldc_w 1785 
L12260: bipush 84 
L12262: bastore 
L12263: dup 
L12264: ldc_w 1786 
L12267: bipush 89 
L12269: bastore 
L12270: dup 
L12271: ldc_w 1787 
L12274: bipush 4 
L12276: bastore 
L12277: dup 
L12278: ldc_w 1788 
L12281: bipush 16 
L12283: bastore 
L12284: dup 
L12285: ldc_w 1789 
L12288: bipush 95 
L12290: bastore 
L12291: dup 
L12292: ldc_w 1790 
L12295: bipush 84 
L12297: bastore 
L12298: dup 
L12299: ldc_w 1791 
L12302: bipush 89 
L12304: bastore 
L12305: dup 
L12306: ldc_w 1792 
L12309: bipush 5 
L12311: bastore 
L12312: dup 
L12313: ldc_w 1793 
L12316: bipush 16 
L12318: bastore 
L12319: dup 
L12320: ldc_w 1794 
L12323: bipush 49 
L12325: bastore 
L12326: dup 
L12327: ldc_w 1795 
L12330: bipush 84 
L12332: bastore 
L12333: dup 
L12334: ldc_w 1796 
L12337: bipush 89 
L12339: bastore 
L12340: dup 
L12341: ldc_w 1797 
L12344: bipush 6 
L12346: bastore 
L12347: dup 
L12348: ldc_w 1798 
L12351: bipush 16 
L12353: bastore 
L12354: dup 
L12355: ldc_w 1799 
L12358: bipush 49 
L12360: bastore 
L12361: dup 
L12362: ldc_w 1800 
L12365: bipush 84 
L12367: bastore 
L12368: dup 
L12369: ldc_w 1801 
L12372: bipush 89 
L12374: bastore 
L12375: dup 
L12376: ldc_w 1802 
L12379: bipush 7 
L12381: bastore 
L12382: dup 
L12383: ldc_w 1803 
L12386: bipush 16 
L12388: bastore 
L12389: dup 
L12390: ldc_w 1804 
L12393: bipush 70 
L12395: bastore 
L12396: dup 
L12397: ldc_w 1805 
L12400: bipush 84 
L12402: bastore 
L12403: dup 
L12404: ldc_w 1806 
L12407: bipush 89 
L12409: bastore 
L12410: dup 
L12411: ldc_w 1807 
L12414: bipush 8 
L12416: bastore 
L12417: dup 
L12418: ldc_w 1808 
L12421: bipush 16 
L12423: bastore 
L12424: dup 
L12425: ldc_w 1809 
L12428: bipush 82 
L12430: bastore 
L12431: dup 
L12432: ldc_w 1810 
L12435: bipush 84 
L12437: bastore 
L12438: dup 
L12439: ldc_w 1811 
L12442: bipush 89 
L12444: bastore 
L12445: dup 
L12446: ldc_w 1812 
L12449: bipush 18 
L12451: bastore 
L12452: dup 
L12453: ldc_w 1813 
L12456: bipush 20 
L12458: bastore 
L12459: dup 
L12460: ldc_w 1814 
L12463: bipush 16 
L12465: bastore 
L12466: dup 
L12467: ldc_w 1815 
L12470: bipush 51 
L12472: bastore 
L12473: dup 
L12474: ldc_w 1816 
L12477: bipush 84 
L12479: bastore 
L12480: dup 
L12481: ldc_w 1817 
L12484: bipush 89 
L12486: bastore 
L12487: dup 
L12488: ldc_w 1818 
L12491: bipush 18 
L12493: bastore 
L12494: dup 
L12495: ldc_w 1819 
L12498: bipush 21 
L12500: bastore 
L12501: dup 
L12502: ldc_w 1820 
L12505: bipush 16 
L12507: bastore 
L12508: dup 
L12509: ldc_w 1821 
L12512: bipush 85 
L12514: bastore 
L12515: dup 
L12516: ldc_w 1822 
L12519: bipush 84 
L12521: bastore 
L12522: dup 
L12523: ldc_w 1823 
L12526: bipush -72 
L12528: bastore 
L12529: dup 
L12530: ldc_w 1824 
L12533: bipush 0 
L12535: bastore 
L12536: dup 
L12537: ldc_w 1825 
L12540: bipush 85 
L12542: bastore 
L12543: dup 
L12544: ldc_w 1826 
L12547: bipush 83 
L12549: bastore 
L12550: dup 
L12551: ldc_w 1827 
L12554: bipush -72 
L12556: bastore 
L12557: dup 
L12558: ldc_w 1828 
L12561: bipush 0 
L12563: bastore 
L12564: dup 
L12565: ldc_w 1829 
L12568: bipush 89 
L12570: bastore 
L12571: dup 
L12572: ldc_w 1830 
L12575: bipush 42 
L12577: bastore 
L12578: dup 
L12579: ldc_w 1831 
L12582: bipush 95 
L12584: bastore 
L12585: dup 
L12586: ldc_w 1832 
L12589: bipush -75 
L12591: bastore 
L12592: dup 
L12593: ldc_w 1833 
L12596: bipush 0 
L12598: bastore 
L12599: dup 
L12600: ldc_w 1834 
L12603: bipush 91 
L12605: bastore 
L12606: dup 
L12607: ldc_w 1835 
L12610: bipush -79 
L12612: bastore 
L12613: dup 
L12614: ldc_w 1836 
L12617: bipush 0 
L12619: bastore 
L12620: dup 
L12621: ldc_w 1837 
L12624: bipush 0 
L12626: bastore 
L12627: dup 
L12628: ldc_w 1838 
L12631: bipush 0 
L12633: bastore 
L12634: dup 
L12635: ldc_w 1839 
L12638: bipush 0 
L12640: bastore 
L12641: dup 
L12642: ldc_w 1840 
L12645: bipush 16 
L12647: bastore 
L12648: dup 
L12649: ldc_w 1841 
L12652: bipush 17 
L12654: bastore 
L12655: dup 
L12656: ldc_w 1842 
L12659: bipush 0 
L12661: bastore 
L12662: dup 
L12663: ldc_w 1843 
L12666: bipush 5 
L12668: bastore 
L12669: dup 
L12670: ldc_w 1844 
L12673: bipush 0 
L12675: bastore 
L12676: dup 
L12677: ldc_w 1845 
L12680: bipush 92 
L12682: bastore 
L12683: dup 
L12684: ldc_w 1846 
L12687: bipush 0 
L12689: bastore 
L12690: dup 
L12691: ldc_w 1847 
L12694: bipush 1 
L12696: bastore 
L12697: dup 
L12698: ldc_w 1848 
L12701: bipush 0 
L12703: bastore 
L12704: dup 
L12705: ldc_w 1849 
L12708: bipush 107 
L12710: bastore 
L12711: dup 
L12712: ldc_w 1850 
L12715: bipush 0 
L12717: bastore 
L12718: dup 
L12719: ldc_w 1851 
L12722: bipush 0 
L12724: bastore 
L12725: dup 
L12726: ldc_w 1852 
L12729: bipush 0 
L12731: bastore 
L12732: dup 
L12733: ldc_w 1853 
L12736: bipush 38 
L12738: bastore 
L12739: dup 
L12740: ldc_w 1854 
L12743: bipush 0 
L12745: bastore 
L12746: dup 
L12747: ldc_w 1855 
L12750: bipush 4 
L12752: bastore 
L12753: dup 
L12754: ldc_w 1856 
L12757: bipush 0 
L12759: bastore 
L12760: dup 
L12761: ldc_w 1857 
L12764: bipush 2 
L12766: bastore 
L12767: dup 
L12768: ldc_w 1858 
L12771: bipush 0 
L12773: bastore 
L12774: dup 
L12775: ldc_w 1859 
L12778: bipush 0 
L12780: bastore 
L12781: dup 
L12782: ldc_w 1860 
L12785: bipush 0 
L12787: bastore 
L12788: dup 
L12789: ldc_w 1861 
L12792: bipush 26 
L12794: bastore 
L12795: dup 
L12796: ldc_w 1862 
L12799: bipush -69 
L12801: bastore 
L12802: dup 
L12803: ldc_w 1863 
L12806: bipush 0 
L12808: bastore 
L12809: dup 
L12810: ldc_w 1864 
L12813: bipush 94 
L12815: bastore 
L12816: dup 
L12817: ldc_w 1865 
L12820: bipush 89 
L12822: bastore 
L12823: dup 
L12824: ldc_w 1866 
L12827: bipush 42 
L12829: bastore 
L12830: dup 
L12831: ldc_w 1867 
L12834: bipush -76 
L12836: bastore 
L12837: dup 
L12838: ldc_w 1868 
L12841: bipush 0 
L12843: bastore 
L12844: dup 
L12845: ldc_w 1869 
L12848: bipush 91 
L12850: bastore 
L12851: dup 
L12852: ldc_w 1870 
L12855: bipush 27 
L12857: bastore 
L12858: dup 
L12859: ldc_w 1871 
L12862: bipush -72 
L12864: bastore 
L12865: dup 
L12866: ldc_w 1872 
L12869: bipush 0 
L12871: bastore 
L12872: dup 
L12873: ldc_w 1873 
L12876: bipush 18 
L12878: bastore 
L12879: dup 
L12880: ldc_w 1874 
L12883: bipush -71 
L12885: bastore 
L12886: dup 
L12887: ldc_w 1875 
L12890: bipush 0 
L12892: bastore 
L12893: dup 
L12894: ldc_w 1876 
L12897: bipush 98 
L12899: bastore 
L12900: dup 
L12901: ldc_w 1877 
L12904: bipush 2 
L12906: bastore 
L12907: dup 
L12908: ldc_w 1878 
L12911: bipush 0 
L12913: bastore 
L12914: dup 
L12915: ldc_w 1879 
L12918: bipush -64 
L12920: bastore 
L12921: dup 
L12922: ldc_w 1880 
L12925: bipush 0 
L12927: bastore 
L12928: dup 
L12929: ldc_w 1881 
L12932: bipush 100 
L12934: bastore 
L12935: dup 
L12936: ldc_w 1882 
L12939: bipush 18 
L12941: bastore 
L12942: dup 
L12943: ldc_w 1883 
L12946: bipush 102 
L12948: bastore 
L12949: dup 
L12950: ldc_w 1884 
L12953: bipush -73 
L12955: bastore 
L12956: dup 
L12957: ldc_w 1885 
L12960: bipush 0 
L12962: bastore 
L12963: dup 
L12964: ldc_w 1886 
L12967: bipush 105 
L12969: bastore 
L12970: dup 
L12971: ldc_w 1887 
L12974: bipush -80 
L12976: bastore 
L12977: dup 
L12978: ldc_w 1888 
L12981: bipush 0 
L12983: bastore 
L12984: dup 
L12985: ldc_w 1889 
L12988: bipush 0 
L12990: bastore 
L12991: dup 
L12992: ldc_w 1890 
L12995: bipush 0 
L12997: bastore 
L12998: dup 
L12999: ldc_w 1891 
L13002: bipush 0 
L13004: bastore 
L13005: dup 
L13006: ldc_w 1892 
L13009: bipush 16 
L13011: bastore 
L13012: dup 
L13013: ldc_w 1893 
L13016: bipush 17 
L13018: bastore 
L13019: dup 
L13020: ldc_w 1894 
L13023: bipush 0 
L13025: bastore 
L13026: dup 
L13027: ldc_w 1895 
L13030: bipush 5 
L13032: bastore 
L13033: dup 
L13034: ldc_w 1896 
L13037: bipush 0 
L13039: bastore 
L13040: dup 
L13041: ldc_w 1897 
L13044: bipush 106 
L13046: bastore 
L13047: dup 
L13048: ldc_w 1898 
L13051: bipush 0 
L13053: bastore 
L13054: dup 
L13055: ldc_w 1899 
L13058: bipush 1 
L13060: bastore 
L13061: dup 
L13062: ldc_w 1900 
L13065: bipush 0 
L13067: bastore 
L13068: dup 
L13069: ldc_w 1901 
L13072: bipush 107 
L13074: bastore 
L13075: dup 
L13076: ldc_w 1902 
L13079: bipush 0 
L13081: bastore 
L13082: dup 
L13083: ldc_w 1903 
L13086: bipush 0 
L13088: bastore 
L13089: dup 
L13090: ldc_w 1904 
L13093: bipush 0 
L13095: bastore 
L13096: dup 
L13097: ldc_w 1905 
L13100: bipush 29 
L13102: bastore 
L13103: dup 
L13104: ldc_w 1906 
L13107: bipush 0 
L13109: bastore 
L13110: dup 
L13111: ldc_w 1907 
L13114: bipush 2 
L13116: bastore 
L13117: dup 
L13118: ldc_w 1908 
L13121: bipush 0 
L13123: bastore 
L13124: dup 
L13125: ldc_w 1909 
L13128: bipush 2 
L13130: bastore 
L13131: dup 
L13132: ldc_w 1910 
L13135: bipush 0 
L13137: bastore 
L13138: dup 
L13139: ldc_w 1911 
L13142: bipush 0 
L13144: bastore 
L13145: dup 
L13146: ldc_w 1912 
L13149: bipush 0 
L13151: bastore 
L13152: dup 
L13153: ldc_w 1913 
L13156: bipush 17 
L13158: bastore 
L13159: dup 
L13160: ldc_w 1914 
L13163: bipush 42 
L13165: bastore 
L13166: dup 
L13167: ldc_w 1915 
L13170: bipush -76 
L13172: bastore 
L13173: dup 
L13174: ldc_w 1916 
L13177: bipush 0 
L13179: bastore 
L13180: dup 
L13181: ldc_w 1917 
L13184: bipush 91 
L13186: bastore 
L13187: dup 
L13188: ldc_w 1918 
L13191: bipush 27 
L13193: bastore 
L13194: dup 
L13195: ldc_w 1919 
L13198: bipush -72 
L13200: bastore 
L13201: dup 
L13202: ldc_w 1920 
L13205: bipush 0 
L13207: bastore 
L13208: dup 
L13209: ldc_w 1921 
L13212: bipush 18 
L13214: bastore 
L13215: dup 
L13216: ldc_w 1922 
L13219: bipush -71 
L13221: bastore 
L13222: dup 
L13223: ldc_w 1923 
L13226: bipush 0 
L13228: bastore 
L13229: dup 
L13230: ldc_w 1924 
L13233: bipush 98 
L13235: bastore 
L13236: dup 
L13237: ldc_w 1925 
L13240: bipush 2 
L13242: bastore 
L13243: dup 
L13244: ldc_w 1926 
L13247: bipush 0 
L13249: bastore 
L13250: dup 
L13251: ldc_w 1927 
L13254: bipush -64 
L13256: bastore 
L13257: dup 
L13258: ldc_w 1928 
L13261: bipush 0 
L13263: bastore 
L13264: dup 
L13265: ldc_w 1929 
L13268: bipush 100 
L13270: bastore 
L13271: dup 
L13272: ldc_w 1930 
L13275: bipush -80 
L13277: bastore 
L13278: dup 
L13279: ldc_w 1931 
L13282: bipush 0 
L13284: bastore 
L13285: dup 
L13286: ldc_w 1932 
L13289: bipush 0 
L13291: bastore 
L13292: dup 
L13293: ldc_w 1933 
L13296: bipush 0 
L13298: bastore 
L13299: dup 
L13300: ldc_w 1934 
L13303: bipush 0 
L13305: bastore 
L13306: dup 
L13307: ldc_w 1935 
L13310: bipush 0 
L13312: bastore 
L13313: dup 
L13314: ldc_w 1936 
L13317: bipush 0 
L13319: bastore 
L13320: invokevirtual Method java/lang/invoke/MethodHandles$Lookup defineClass ([B)Ljava/lang/Class; 
L13323: areturn 
L13324: 
    .end code 
.end method 

.method private static synthetic a : (Ljava/lang/invoke/MethodHandles$Lookup;Ljava/lang/String;Ljava/lang/Class;I)Ljava/lang/String; 
    .code stack 5 locals 4 
L0:     aload_0 
L1:     ldc_w [1965] 
L4:     ldc_w 'a' 
L7:     aload_2 
L8:     getstatic Field java/lang/Integer TYPE Ljava/lang/Class; 
L11:    invokestatic Method java/lang/invoke/MethodType methodType (Ljava/lang/Class;Ljava/lang/Class;)Ljava/lang/invoke/MethodType; 
L14:    invokevirtual Method java/lang/invoke/MethodHandles$Lookup findVirtual (Ljava/lang/Class;Ljava/lang/String;Ljava/lang/invoke/MethodType;)Ljava/lang/invoke/MethodHandle; 
L17:    ldc_w [1965] 
L20:    invokevirtual Method java/lang/Class newInstance ()Ljava/lang/Object; 
L23:    iload_3 
L24:    invokevirtual Method java/lang/invoke/MethodHandle invoke (Ljava/lang/Object;I)Ljava/lang/String; 
L27:    areturn 
L28:    
    .end code 
.end method 

.method private static synthetic a : (Ljava/lang/invoke/MethodHandles$Lookup;Ljava/lang/String;Ljava/lang/Class;I)[B 
    .code stack 5 locals 4 
L0:     aload_0 
L1:     ldc_w [1965] 
L4:     ldc_w 'a' 
L7:     aload_2 
L8:     getstatic Field java/lang/Integer TYPE Ljava/lang/Class; 
L11:    invokestatic Method java/lang/invoke/MethodType methodType (Ljava/lang/Class;Ljava/lang/Class;)Ljava/lang/invoke/MethodType; 
L14:    invokevirtual Method java/lang/invoke/MethodHandles$Lookup findVirtual (Ljava/lang/Class;Ljava/lang/String;Ljava/lang/invoke/MethodType;)Ljava/lang/invoke/MethodHandle; 
L17:    ldc_w [1965] 
L20:    invokevirtual Method java/lang/Class newInstance ()Ljava/lang/Object; 
L23:    iload_3 
L24:    invokevirtual Method java/lang/invoke/MethodHandle invoke (Ljava/lang/Object;I)[B 
L27:    areturn 
L28:    
    .end code 
.end method 

.method public static main : ([Ljava/lang/String;)V 
    .code stack 0 locals 1 
L0:     invokedynamic InvokeDynamic invokeStatic Method a a (Ljava/lang/invoke/MethodHandles$Lookup;Ljava/lang/String;Ljava/lang/invoke/MethodType;)Ljava/lang/invoke/CallSite; : a ()V 
L5:     return 
L6:     
    .end code 
.end method 

.method private static final synthetic a : ([B)Z 
    .code stack 6 locals 8 
L0:     new '\U000f2158' 
L3:     dup 
L4:     invokespecial Method '\U000f2158' <init> ()V 
L7:     invokevirtual Method '\U000f2158' a ()Ljava/lang/String; 
L10:    new '\u2319\u4636\ua131\ua13d' 
L13:    dup 
L14:    invokespecial Method '\u2319\u4636\ua131\ua13d' <init> ()V 
L17:    swap 
L18:    invokevirtual Method '\u2319\u4636\ua131\ua13d' a (Ljava/lang/String;)[B 
L21:    astore_1 
L22:    new a$a 
L25:    dup 
L26:    invokespecial Method a$a <init> ()V 
L29:    invokevirtual Method a$a a ()[B 
L32:    astore_2 
L33:    ldc_w [2031] 
L36:    astore_3 
L37:    iconst_0 
L38:    istore 4 

        .stack full 
            locals Object [B Object [B Object [B Object [B Integer 
            stack 
        .end stack 
L40:    iload 4 
L42:    iconst_4 
L43:    if_icmpge L250 
L46:    ldc2_w +3.141592653589793 
L49:    iload 4 
L51:    i2d 
L52:    dmul 
L53:    invokestatic Method java/lang/Math floor (D)D 
L56:    d2i 
L57:    istore 5 
L59:    aload_0 
L60:    iload 5 
L62:    dup2 
L63:    baload 
L64:    aload_1 
L65:    iload 4 
L67:    baload 
L68:    isub 
L69:    i2b 
L70:    bastore 
L71:    aload_0 
L72:    iload 5 
L74:    bipush 12 
L76:    iadd 
L77:    dup2 
L78:    baload 
L79:    aload_1 
L80:    iload 4 
L82:    bipush 4 
L84:    iadd 
L85:    baload 
L86:    isub 
L87:    i2b 
L88:    bastore 
L89:    ldc2_w +4.0 
L92:    iload 4 
L94:    i2d 
L95:    invokestatic Method java/lang/Math pow (DD)D 
L98:    d2i 
L99:    istore 6 
L101:   iconst_0 
L102:   istore 5 

        .stack append Integer Integer 
L104:   iload 6 
L106:   ifle L129 
L109:   iload 5 
L111:   iload 6 
L113:   ldc 10 
L115:   irem 
L116:   iadd 
L117:   istore 5 
L119:   iload 6 
L121:   ldc 10 
L123:   idiv 
L124:   istore 6 
L126:   goto L104 

        .stack chop 1 
L129:   aload_0 
L130:   iload 5 
L132:   dup2 
L133:   baload 
L134:   aload_2 
L135:   iload 4 
L137:   baload 
L138:   isub 
L139:   i2b 
L140:   bastore 
L141:   aload_0 
L142:   iload 5 
L144:   bipush 12 
L146:   iadd 
L147:   dup2 
L148:   baload 
L149:   aload_2 
L150:   iload 4 
L152:   bipush 4 
L154:   iadd 
L155:   baload 
L156:   isub 
L157:   i2b 
L158:   bastore 
L159:   iload 4 
L161:   bipush 24 
L163:   iadd 
L164:   istore 6 
L166:   iconst_0 
L167:   istore 5 
L169:   iconst_1 
L170:   istore 7 

        .stack full 
            locals Object [B Object [B Object [B Object [B Integer Integer Integer Integer 
            stack 
        .end stack 
L172:   iload 6 
L174:   ifle L207 
L177:   iload 5 
L179:   iload 6 
L181:   ldc 10 
L183:   irem 
L184:   iadd 
L185:   istore 5 
L187:   iload 7 
L189:   iload 6 
L191:   ldc 10 
L193:   irem 
L194:   imul 
L195:   istore 7 
L197:   iload 6 
L199:   ldc 10 
L201:   idiv 
L202:   istore 6 
L204:   goto L172 

        .stack same 
L207:   iload 5 
L209:   iload 7 
L211:   iadd 
L212:   istore 5 
L214:   aload_0 
L215:   iload 5 
L217:   dup2 
L218:   baload 
L219:   aload_3 
L220:   iload 4 
L222:   bipush 4 
L224:   iadd 
L225:   baload 
L226:   isub 
L227:   i2b 
L228:   bastore 
L229:   aload_0 
L230:   iload 5 
L232:   bipush 12 
L234:   isub 
L235:   dup2 
L236:   baload 
L237:   aload_3 
L238:   iload 4 
L240:   baload 
L241:   isub 
L242:   i2b 
L243:   bastore 
L244:   iinc 4 1 
L247:   goto L40 

        .stack full 
            locals Object [B Object [B Object [B Object [B 
            stack 
        .end stack 
L250:   aload_0 
L251:   ldc 24 
L253:   dup2 
L254:   baload 
L255:   bipush 64 
L257:   isub 
L258:   i2b 
L259:   bastore 
L260:   aload_0 
L261:   ldc 25 
L263:   dup2 
L264:   baload 
L265:   bipush 125 
L267:   isub 
L268:   i2b 
L269:   bastore 
L270:   aload_0 
L271:   dup 
L272:   ldc 26 
L274:   iconst_0 
L275:   i2b 
L276:   bastore 
L277:   invokestatic Method java/util/BitSet valueOf ([B)Ljava/util/BitSet; 
L280:   invokevirtual Method java/util/BitSet cardinality ()I 
L283:   ifne L290 
L286:   ldc_w 1 
L289:   ireturn 

        .stack same 
L290:   ldc_w 0 
L293:   ireturn 
L294:   
    .end code 
.end method 

.method private static final synthetic a : ()V 
    .code stack 6 locals 2 
L0:     ldc_w [2064] 
L3:     getstatic Field java/lang/System out Ljava/io/PrintStream; 
L6:     swap 
L7:     invokevirtual Method java/io/PrintStream print (Ljava/lang/String;)V 
L10:    ldc_w 256 
L13:    newarray byte 
L15:    dup 
L16:    getstatic Field java/lang/System in Ljava/io/InputStream; 
L19:    swap 
L20:    invokevirtual Method java/io/InputStream read ([B)I 
L23:    pop 
L24:    invokestatic Method a a ([B)Z 
L27:    ifeq L43 
L30:    ldc_w [2089] 
L33:    getstatic Field java/lang/System out Ljava/io/PrintStream; 
L36:    swap 
L37:    invokevirtual Method java/io/PrintStream println (Ljava/lang/String;)V 
L40:    goto L53 

        .stack same 
L43:    ldc_w [2094] 
L46:    getstatic Field java/lang/System out Ljava/io/PrintStream; 
L49:    swap 
L50:    invokevirtual Method java/io/PrintStream println (Ljava/lang/String;)V 

        .stack same 
L53:    return 
L54:    
    .end code 
.end method 
.attribute NestMembers b'\x00\x02\x07\xd7\x07\xde' 
.end class 
